Workbook
Name RECAUDACION___ACUERDOS_DE_PAGO_EN_OFICINAS_COMERCIALES: #REF!
Name TABLE: '[1]Comparación (2)'!$D$15:$U$15
Name TABLE_2: '[1]Comparación (2)'!$D$16:$U$16
Name TABLE_201: '[1]Comparación (2)'!$B$12:$U$19
Name TABLE01: '[1]Comparación (2)'!$B$2:$T$9

Sheet Resumen PE
A1: Cartera
A2: PE Calls | B2: =SUM('Cartera_Viva-Calls'!AJ7:AJ8) -> 33128.766 | C2: =B2/$B$5 -> 0.0058335829
A3: PE Otros | B3: =+SUM('Cartera_Viva-Otros'!AN:AN) -> 4330544.1 | C3: =B3/$B$5 -> 0.76255747
A4: PE Saldos No Util | B4: =+SUM(Saldos_No_Util!O:O) -> 1315301.2 | C4: =B4/$B$5 -> 0.23160894 | D4: Unidades expresión | E4: 1000000
A5: TOTAL PE | B5: =+SUM(B2:B4) -> 5678974
A7: CUADRO A | D7: CUADRO B | G7: CUADRO C | J7: CUADRO D | M7: CUADRO E | S7: CUADRO F
A8: Montos de previsiones (en millones de $) | B8: Monto al | D8: Monto de previsiones (PCE) abiertas por stages (en millones de $) | E8: Monto PCE al | G8: Monto de las exposiciones totales (EAD) abiertas por stages (en millones de $) | H8: Monto exposiciones (EAD) al | J8: Monto de PCE y EAD abiertas por stage y segmento (en millones de $) Carteras/Segmentos (*) | K8: Monto al | M8: Integrar el total de PCE y los parámetros aplicados para cada segmento definido por la entidad (en millones de $) Cartera-Segmento (*)\Concepto | N8: Monto PCE | O8: % PD media (**) | P8: % LGD media (**) | Q8: Monto EAD | S8: Partidas fuera de balance (*) (en millones de $) | T8: Saldo contable PFB | U8: CCF (%) | V8: Monto Exposición (EAD) | W8: Monto
B9: 46112 | E9: =$B$9 -> 46112 | H9: =$B$9 -> 46112 | K9: =$B$9 -> 46112 | W9: PCE
A10: Previsiones totales según NIIF 9 (PCE) | B10: =+B5/$E$4 -> 5.678974 | D10: Stage 1 | E10: =+(SUMIF('Cartera_Viva-Otros'!AL:AL,"1",'Cartera_Viva-Otros'!AN:AN)+SUMIF(Saldos_No_Util!K:K,"1",Saldos_No_Util!O:O)+SUMIF('Cartera_Viva-Calls'!Z:Z,"1",'Cartera_Viva-Calls'!AJ:AJ))/$E$4 -> 3.5256465 | G10: Stage 1 | H10: =+(SUMIF('Cartera_Viva-Otros'!AL:AL,"1",'Cartera_Viva-Otros'!AM:AM)+SUMIF(Saldos_No_Util!K:K,"1",Saldos_No_Util!G:G)+SUMIF('Cartera_Viva-Calls'!Z:Z,"1",'Cartera_Viva-Calls'!AC:AC))/$E$4 -> 1270.3831 | I10: =H10*1000000 -> 1.2703831e+09 | J10: PCE Cartera minorista | K10: =+(SUMIFS('Cartera_Viva-Otros'!AN:AN,'Cartera_Viva-Otros'!P:P,"F")+SUMIFS(Saldos_No_Util!O:O,Saldos_No_Util!P:P,"F"))/$E$4 -> 1.1600159 | M10: Stage 1 | S10: Stage 1
A11: Previsiones regulatorias contabilizadas | D11: Stage 2 | E11: =+(SUMIF('Cartera_Viva-Otros'!AL:AL,"2",'Cartera_Viva-Otros'!AN:AN)+SUMIF(Saldos_No_Util!K:K,"2",Saldos_No_Util!O:O)+SUMIF('Cartera_Viva-Calls'!Z:Z,"2",'Cartera_Viva-Calls'!AJ:AJ))/$E$4 -> 0 | G11: Stage 2 | H11: =+(SUMIF('Cartera_Viva-Otros'!AL:AL,"2",'Cartera_Viva-Otros'!AM:AM)+SUMIF(Saldos_No_Util!K:K,"2",Saldos_No_Util!G:G)+SUMIF('Cartera_Viva-Calls'!Z:Z,"2",'Cartera_Viva-Calls'!AC:AC))/$E$4 -> 0 | I11: =H11*1000000 -> 0 | J11: EAD Cartera minorista | K11: =+(SUMIFS('Cartera_Viva-Otros'!AM:AM,'Cartera_Viva-Otros'!P:P,"f")+SUMIFS(Saldos_No_Util!G:G,Saldos_No_Util!P:P,"F"))/$E$4 -> 152.99962 | M11: Cartera Minorista | N11: =+(SUMIFS('Cartera_Viva-Otros'!AN:AN,'Cartera_Viva-Otros'!AL:AL,"1",'Cartera_Viva-Otros'!P:P,"F")+SUMIFS(Saldos_No_Util!O:O,Saldos_No_Util!K:K,"1",Saldos_No_Util!P:P,"F"))/$E$4 -> 0.80985861 | O11: =AVERAGEIFS('Cartera_Viva-Otros'!AJ:AJ,'Cartera_Viva-Otros'!AL:AL,"1",'Cartera_Viva-Otros'!P:P,"F") -> #DIV/0! | P11: =AVERAGEIFS('Cartera_Viva-Otros'!AK:AK,'Cartera_Viva-Otros'!AL:AL,"1",'Cartera_Viva-Otros'!P:P,"F") -> #DIV/0! | Q11: =+(SUMIFS('Cartera_Viva-Otros'!AM:AM,'Cartera_Viva-Otros'!AL:AL,"1",'Cartera_Viva-Otros'!P:P,"F")+SUMIFS(Saldos_No_Util!G:G,Saldos_No_Util!K:K,"1",Saldos_No_Util!P:P,"F"))/$E$4 -> 152.28764 | S11: Saldo no utilizado TC | T11: =+SUMIFS(Saldos_No_Util!G:G,Saldos_No_Util!K:K,"1",Saldos_No_Util!Q:Q,'Resumen PE'!S11)/$E$4 -> 168.32987 | U11: =+AVERAGEIFS(Saldos_No_Util!N:N,Saldos_No_Util!K:K,"1",Saldos_No_Util!Q:Q,'Resumen PE'!S11) -> 0.4 | V11: =+T11*U11 -> 67.331949 | W11: =SUMIFS(Saldos_No_Util!O:O,Saldos_No_Util!K:K,"1",Saldos_No_Util!Q:Q,'Resumen PE'!S11)/$E$4 -> 0.89517043
D12: Stage 3 | E12: =+(SUMIF('Cartera_Viva-Otros'!AL:AL,"3",'Cartera_Viva-Otros'!AN:AN)+SUMIF(Saldos_No_Util!K:K,"3",Saldos_No_Util!O:O)+SUMIF('Cartera_Viva-Calls'!Z:Z,"3",'Cartera_Viva-Calls'!AJ:AJ))/$E$4 -> 2.1533275 | G12: Stage 3 | H12: =+(SUMIF('Cartera_Viva-Otros'!AL:AL,"3",'Cartera_Viva-Otros'!AM:AM)+SUMIF(Saldos_No_Util!K:K,"3",Saldos_No_Util!G:G)+SUMIF('Cartera_Viva-Calls'!Z:Z,"3",'Cartera_Viva-Calls'!AC:AC))/$E$4 -> 2.5151449 | I12: =H12*1000000 -> 2515144.9 | J12: Tarjetas_de_Crédito | K12: =+SUMIFS('Cartera_Viva-Otros'!AM:AM,'Cartera_Viva-Otros'!AO:AO,'Resumen PE'!J12,'Cartera_Viva-Otros'!P:P,"F")/$E$4 -> 0 | M12: Tarjetas_de_Crédito | N12: =+SUMIFS('Cartera_Viva-Otros'!AN:AN,'Cartera_Viva-Otros'!AL:AL,"1",'Cartera_Viva-Otros'!P:P,"F",'Cartera_Viva-Otros'!AO:AO,'Resumen PE'!M12)/$E$4 -> 0 | O12: =IFERROR(AVERAGEIFS('Cartera_Viva-Otros'!AJ:AJ,'Cartera_Viva-Otros'!AL:AL,"1",'Cartera_Viva-Otros'!P:P,"F",'Cartera_Viva-Otros'!AO:AO,'Resumen PE'!M12),"-") -> - | P12: =IFERROR(AVERAGEIFS('Cartera_Viva-Otros'!AK:AK,'Cartera_Viva-Otros'!AL:AL,"1",'Cartera_Viva-Otros'!P:P,"F",'Cartera_Viva-Otros'!AO:AO,'Resumen PE'!M12),"-") -> - | Q12: =+SUMIFS('Cartera_Viva-Otros'!AM:AM,'Cartera_Viva-Otros'!AL:AL,"1",'Cartera_Viva-Otros'!P:P,"F",'Cartera_Viva-Otros'!AO:AO,'Resumen PE'!M12)/$E$4 -> 0 | S12: Saldo no utilizado ACC | T12: =+SUMIFS(Saldos_No_Util!G:G,Saldos_No_Util!K:K,"1",Saldos_No_Util!Q:Q,'Resumen PE'!S12)/$E$4 -> 11.526606 | U12: =+AVERAGEIFS(Saldos_No_Util!N:N,Saldos_No_Util!K:K,"1",Saldos_No_Util!Q:Q,'Resumen PE'!S12) -> 0.73333333 | V12: =+T12*U12 -> 8.4528444 | W12: =+SUMIFS(Saldos_No_Util!O:O,Saldos_No_Util!K:K,"1",Saldos_No_Util!Q:Q,'Resumen PE'!S12)/$E$4 -> 0.069973463
J13: Prestamos Personales | K13: =+SUMIFS('Cartera_Viva-Otros'!AM:AM,'Cartera_Viva-Otros'!AO:AO,'Resumen PE'!J13,'Cartera_Viva-Otros'!P:P,"F")/$E$4 -> 0 | M13: Prestamos Personales | N13: =+SUMIFS('Cartera_Viva-Otros'!AN:AN,'Cartera_Viva-Otros'!AL:AL,"1",'Cartera_Viva-Otros'!P:P,"F",'Cartera_Viva-Otros'!AO:AO,'Resumen PE'!M13)/$E$4 -> 0 | O13: =IFERROR(AVERAGEIFS('Cartera_Viva-Otros'!AJ:AJ,'Cartera_Viva-Otros'!AL:AL,"1",'Cartera_Viva-Otros'!P:P,"F",'Cartera_Viva-Otros'!AO:AO,'Resumen PE'!M13),"-") -> - | P13: =IFERROR(AVERAGEIFS('Cartera_Viva-Otros'!AK:AK,'Cartera_Viva-Otros'!AL:AL,"1",'Cartera_Viva-Otros'!P:P,"F",'Cartera_Viva-Otros'!AO:AO,'Resumen PE'!M13),"-") -> - | Q13: =+SUMIFS('Cartera_Viva-Otros'!AM:AM,'Cartera_Viva-Otros'!AL:AL,"1",'Cartera_Viva-Otros'!P:P,"F",'Cartera_Viva-Otros'!AO:AO,'Resumen PE'!M13)/$E$4 -> 0 | S13: Stage 2
J14: Prestamos a Sola Firma | K14: =+SUMIFS('Cartera_Viva-Otros'!AM:AM,'Cartera_Viva-Otros'!AO:AO,'Resumen PE'!J14,'Cartera_Viva-Otros'!P:P,"F")/$E$4 -> 0 | M14: Prestamos a Sola Firma | N14: =+SUMIFS('Cartera_Viva-Otros'!AN:AN,'Cartera_Viva-Otros'!AL:AL,"1",'Cartera_Viva-Otros'!P:P,"F",'Cartera_Viva-Otros'!AO:AO,'Resumen PE'!M14)/$E$4 -> 0 | O14: =IFERROR(AVERAGEIFS('Cartera_Viva-Otros'!AJ:AJ,'Cartera_Viva-Otros'!AL:AL,"1",'Cartera_Viva-Otros'!P:P,"F",'Cartera_Viva-Otros'!AO:AO,'Resumen PE'!M14),"-") -> - | P14: =IFERROR(AVERAGEIFS('Cartera_Viva-Otros'!AK:AK,'Cartera_Viva-Otros'!AL:AL,"1",'Cartera_Viva-Otros'!P:P,"F",'Cartera_Viva-Otros'!AO:AO,'Resumen PE'!M14),"-") -> - | Q14: =+SUMIFS('Cartera_Viva-Otros'!AM:AM,'Cartera_Viva-Otros'!AL:AL,"1",'Cartera_Viva-Otros'!P:P,"F",'Cartera_Viva-Otros'!AO:AO,'Resumen PE'!M14)/$E$4 -> 0 | S14: Saldo no utilizado TC | T14: =+SUMIFS(Saldos_No_Util!G:G,Saldos_No_Util!K:K,"2",Saldos_No_Util!Q:Q,'Resumen PE'!S14)/$E$4 -> 0 | U14: =+IFERROR(AVERAGEIFS(Saldos_No_Util!N:N,Saldos_No_Util!K:K,"2",Saldos_No_Util!Q:Q,'Resumen PE'!S14),"-") -> - | V14: =+IFERROR(T14*U14,"-") -> - | W14: =+IFERROR(SUMIFS(Saldos_No_Util!O:O,Saldos_No_Util!K:K,"2",Saldos_No_Util!Q:Q,'Resumen PE'!S14)/$E$4,"-") -> 0
J15: ACC | K15: =+SUMIFS('Cartera_Viva-Otros'!AM:AM,'Cartera_Viva-Otros'!AO:AO,'Resumen PE'!J15,'Cartera_Viva-Otros'!P:P,"F")/$E$4 -> 0 | M15: ACC | N15: =+SUMIFS('Cartera_Viva-Otros'!AN:AN,'Cartera_Viva-Otros'!AL:AL,"1",'Cartera_Viva-Otros'!P:P,"F",'Cartera_Viva-Otros'!AO:AO,'Resumen PE'!M15)/$E$4 -> 0 | O15: =IFERROR(AVERAGEIFS('Cartera_Viva-Otros'!AJ:AJ,'Cartera_Viva-Otros'!AL:AL,"1",'Cartera_Viva-Otros'!P:P,"F",'Cartera_Viva-Otros'!AO:AO,'Resumen PE'!M15),"-") -> - | P15: =IFERROR(AVERAGEIFS('Cartera_Viva-Otros'!AK:AK,'Cartera_Viva-Otros'!AL:AL,"1",'Cartera_Viva-Otros'!P:P,"F",'Cartera_Viva-Otros'!AO:AO,'Resumen PE'!M15),"-") -> - | Q15: =+SUMIFS('Cartera_Viva-Otros'!AM:AM,'Cartera_Viva-Otros'!AL:AL,"1",'Cartera_Viva-Otros'!P:P,"F",'Cartera_Viva-Otros'!AO:AO,'Resumen PE'!M15)/$E$4 -> 0 | S15: Saldo no utilizado ACC | T15: =+SUMIFS(Saldos_No_Util!G:G,Saldos_No_Util!K:K,"2",Saldos_No_Util!Q:Q,'Resumen PE'!S15)/$E$4 -> 0 | U15: =+IFERROR(AVERAGEIFS(Saldos_No_Util!N:N,Saldos_No_Util!K:K,"2",Saldos_No_Util!Q:Q,'Resumen PE'!S15),"-") -> - | V15: =+IFERROR(T15*U15,"-") -> - | W15: =+IFERROR(SUMIFS(Saldos_No_Util!O:O,Saldos_No_Util!K:K,"2",Saldos_No_Util!Q:Q,'Resumen PE'!S15)/$E$4,"-") -> 0
J16: Documentos descontados | K16: =+SUMIFS('Cartera_Viva-Otros'!AM:AM,'Cartera_Viva-Otros'!AO:AO,'Resumen PE'!J16,'Cartera_Viva-Otros'!P:P,"F")/$E$4 -> 0 | M16: Documentos descontados | N16: =+SUMIFS('Cartera_Viva-Otros'!AN:AN,'Cartera_Viva-Otros'!AL:AL,"1",'Cartera_Viva-Otros'!P:P,"F",'Cartera_Viva-Otros'!AO:AO,'Resumen PE'!M16)/$E$4 -> 0 | O16: =IFERROR(AVERAGEIFS('Cartera_Viva-Otros'!AJ:AJ,'Cartera_Viva-Otros'!AL:AL,"1",'Cartera_Viva-Otros'!P:P,"F",'Cartera_Viva-Otros'!AO:AO,'Resumen PE'!M16),"-") -> - | P16: =IFERROR(AVERAGEIFS('Cartera_Viva-Otros'!AK:AK,'Cartera_Viva-Otros'!AL:AL,"1",'Cartera_Viva-Otros'!P:P,"F",'Cartera_Viva-Otros'!AO:AO,'Resumen PE'!M16),"-") -> - | Q16: =+SUMIFS('Cartera_Viva-Otros'!AM:AM,'Cartera_Viva-Otros'!AL:AL,"1",'Cartera_Viva-Otros'!P:P,"F",'Cartera_Viva-Otros'!AO:AO,'Resumen PE'!M16)/$E$4 -> 0 | S16: Stage 3
J17: Saldo no utilizado TC | K17: =+SUMIFS(Saldos_No_Util!G:G,Saldos_No_Util!P:P,"F",Saldos_No_Util!Q:Q,J17)/$E$4 -> 152.99962 | M17: Saldo no utilizado TC | N17: =+SUMIFS(Saldos_No_Util!O:O,Saldos_No_Util!K:K,"1",Saldos_No_Util!P:P,"F",Saldos_No_Util!Q:Q,'Resumen PE'!M17)/$E$4 -> 0.80985861 | O17: =IFERROR(AVERAGEIFS(Saldos_No_Util!L:L,Saldos_No_Util!K:K,"1",Saldos_No_Util!P:P,"F",Saldos_No_Util!Q:Q,'Resumen PE'!M17),0) -> 0.015 | P17: =IFERROR(AVERAGEIFS(Saldos_No_Util!M:M,Saldos_No_Util!K:K,"1",Saldos_No_Util!P:P,"F",Saldos_No_Util!Q:Q,'Resumen PE'!M17),0) -> 0.66499986 | Q17: =+SUMIFS(Saldos_No_Util!G:G,Saldos_No_Util!K:K,"1",Saldos_No_Util!P:P,"F",Saldos_No_Util!Q:Q,'Resumen PE'!M17)/$E$4 -> 152.28764 | S17: Saldo no utilizado TC | T17: =+SUMIFS(Saldos_No_Util!G:G,Saldos_No_Util!K:K,"3",Saldos_No_Util!Q:Q,'Resumen PE'!S17)/$E$4 -> 0.7119747 | U17: =+IFERROR(AVERAGEIFS(Saldos_No_Util!N:N,Saldos_No_Util!K:K,"3",Saldos_No_Util!Q:Q,'Resumen PE'!S17),"-") -> 0.4 | V17: =+IFERROR(T17*U17,"-") -> 0.28478988 | W17: =+IFERROR(SUMIFS(Saldos_No_Util!O:O,Saldos_No_Util!K:K,"3",Saldos_No_Util!Q:Q,'Resumen PE'!S17)/$E$4,"-") -> 0.35015728
J18: Saldo no utilizado ACC | K18: =+SUMIFS(Saldos_No_Util!G:G,Saldos_No_Util!P:P,"F",Saldos_No_Util!Q:Q,J18)/$E$4 -> 0 | M18: Saldo no utilizado ACC | N18: =+SUMIFS(Saldos_No_Util!O:O,Saldos_No_Util!K:K,"1",Saldos_No_Util!P:P,"F",Saldos_No_Util!Q:Q,'Resumen PE'!M18)/$E$4 -> 0 | O18: =IFERROR(AVERAGEIFS(Saldos_No_Util!L:L,Saldos_No_Util!K:K,"1",Saldos_No_Util!P:P,"F",Saldos_No_Util!Q:Q,'Resumen PE'!M18),"-") -> - | P18: =IFERROR(AVERAGEIFS(Saldos_No_Util!M:M,Saldos_No_Util!K:K,"1",Saldos_No_Util!P:P,"F",Saldos_No_Util!Q:Q,'Resumen PE'!M18),"-") -> - | Q18: =+SUMIFS(Saldos_No_Util!G:G,Saldos_No_Util!K:K,"1",Saldos_No_Util!P:P,"F",Saldos_No_Util!Q:Q,'Resumen PE'!M18)/$E$4 -> 0 | S18: Saldo no utilizado ACC | T18: =+SUMIFS(Saldos_No_Util!G:G,Saldos_No_Util!K:K,"3",Saldos_No_Util!Q:Q,'Resumen PE'!S18)/$E$4 -> 0 | U18: =+IFERROR(AVERAGEIFS(Saldos_No_Util!N:N,Saldos_No_Util!K:K,"3",Saldos_No_Util!Q:Q,'Resumen PE'!S18),"-") -> - | V18: =+IFERROR(T18*U18,"-") -> - | W18: =+IFERROR(SUMIFS(Saldos_No_Util!O:O,Saldos_No_Util!K:K,"3",Saldos_No_Util!Q:Q,'Resumen PE'!S18)/$E$4,"-") -> 0
J19: Otros | K19: =+SUMIFS('Cartera_Viva-Otros'!AM:AM,'Cartera_Viva-Otros'!AO:AO,"IVA Debito Fiscal no Cobrados",'Cartera_Viva-Otros'!P:P,"F")/$E$4 -> 0 | M19: Otros | N19: =+SUMIFS('Cartera_Viva-Otros'!AN:AN,'Cartera_Viva-Otros'!AL:AL,"1",'Cartera_Viva-Otros'!P:P,"F",'Cartera_Viva-Otros'!AO:AO,"IVA Debito Fiscal no Cobrados")/$E$4 -> 0 | O19: =IFERROR(AVERAGEIFS('Cartera_Viva-Otros'!AJ:AJ,'Cartera_Viva-Otros'!AL:AL,"1",'Cartera_Viva-Otros'!P:P,"F",'Cartera_Viva-Otros'!AO:AO,"IVA Debito Fiscal no Cobrados"),"-") -> - | P19: =IFERROR(AVERAGEIFS('Cartera_Viva-Otros'!AK:AK,'Cartera_Viva-Otros'!AL:AL,"1",'Cartera_Viva-Otros'!P:P,"F",'Cartera_Viva-Otros'!AO:AO,"IVA Debito Fiscal no Cobrados"),"-") -> - | Q19: =+SUMIFS('Cartera_Viva-Otros'!AM:AM,'Cartera_Viva-Otros'!AL:AL,"1",'Cartera_Viva-Otros'!P:P,"F",'Cartera_Viva-Otros'!AO:AO,"IVA Debito Fiscal no Cobrados")/$E$4 -> 0
J20: PCE Cartera mayorista | K20: =+(SUMIFS('Cartera_Viva-Otros'!AN:AN,'Cartera_Viva-Otros'!P:P,"J")+SUMIFS(Saldos_No_Util!O:O,Saldos_No_Util!P:P,"J")+SUM('Cartera_Viva-Calls'!AJ7:AJ8))/$E$4 -> 0.18841405 | M20: Cartera Mayorista | N20: =+(SUMIFS('Cartera_Viva-Otros'!AN:AN,'Cartera_Viva-Otros'!AL:AL,"1",'Cartera_Viva-Otros'!P:P,"J")+SUMIFS(Saldos_No_Util!O:O,Saldos_No_Util!P:P,"J",Saldos_No_Util!K:K,"1")+SUMIF('Cartera_Viva-Calls'!AF:AF,"1",'Cartera_Viva-Calls'!AJ:AJ))/$E$4 -> 0.18841405 | O20: =AVERAGEIFS('Cartera_Viva-Otros'!AJ:AJ,'Cartera_Viva-Otros'!AL:AL,"1",'Cartera_Viva-Otros'!P:P,"J") -> #DIV/0! | P20: =AVERAGEIFS('Cartera_Viva-Otros'!AK:AK,'Cartera_Viva-Otros'!AL:AL,"1",'Cartera_Viva-Otros'!P:P,"J") -> #DIV/0! | Q20: =+(SUMIFS('Cartera_Viva-Otros'!AM:AM,'Cartera_Viva-Otros'!AL:AL,"1",'Cartera_Viva-Otros'!P:P,"J")+SUMIFS(Saldos_No_Util!G:G,Saldos_No_Util!P:P,"J",Saldos_No_Util!K:K,"1")+SUMIF('Cartera_Viva-Calls'!AF:AF,"1",'Cartera_Viva-Calls'!AC:AC))/$E$4 -> 927.99418
J21: EAD Cartera mayorista | K21: =+(SUMIFS('Cartera_Viva-Otros'!AM:AM,'Cartera_Viva-Otros'!P:P,"J")+SUMIFS(Saldos_No_Util!G:G,Saldos_No_Util!P:P,"J")+SUM('Cartera_Viva-Calls'!AC7:AC8))/$E$4 -> 927.99418 | M21: Tarjetas_de_Crédito | N21: =+SUMIFS('Cartera_Viva-Otros'!AN:AN,'Cartera_Viva-Otros'!AL:AL,"1",'Cartera_Viva-Otros'!P:P,"J",'Cartera_Viva-Otros'!AO:AO,'Resumen PE'!M21)/$E$4 -> 0 | O21: =IFERROR(AVERAGEIFS('Cartera_Viva-Otros'!AJ:AJ,'Cartera_Viva-Otros'!AL:AL,"1",'Cartera_Viva-Otros'!P:P,"J",'Cartera_Viva-Otros'!AO:AO,'Resumen PE'!M21),"-") -> - | P21: =IFERROR(AVERAGEIFS('Cartera_Viva-Otros'!AK:AK,'Cartera_Viva-Otros'!AL:AL,"1",'Cartera_Viva-Otros'!P:P,"J",'Cartera_Viva-Otros'!AO:AO,'Resumen PE'!M21),"-") -> - | Q21: =+SUMIFS('Cartera_Viva-Otros'!AM:AM,'Cartera_Viva-Otros'!AL:AL,"1",'Cartera_Viva-Otros'!P:P,"J",'Cartera_Viva-Otros'!AO:AO,'Resumen PE'!M12)/$E$4 -> 0
J22: Tarjetas_de_Crédito | K22: =+SUMIFS('Cartera_Viva-Otros'!AM:AM,'Cartera_Viva-Otros'!AO:AO,'Resumen PE'!J22,'Cartera_Viva-Otros'!P:P,"J")/$E$4 -> 0 | M22: Prestamos Personales | N22: =+SUMIFS('Cartera_Viva-Otros'!AN:AN,'Cartera_Viva-Otros'!AL:AL,"1",'Cartera_Viva-Otros'!P:P,"J",'Cartera_Viva-Otros'!AO:AO,'Resumen PE'!M22)/$E$4 -> 0 | O22: =IFERROR(AVERAGEIFS('Cartera_Viva-Otros'!AJ:AJ,'Cartera_Viva-Otros'!AL:AL,"1",'Cartera_Viva-Otros'!P:P,"J",'Cartera_Viva-Otros'!AO:AO,'Resumen PE'!M22),"-") -> - | P22: =IFERROR(AVERAGEIFS('Cartera_Viva-Otros'!AK:AK,'Cartera_Viva-Otros'!AL:AL,"1",'Cartera_Viva-Otros'!P:P,"J",'Cartera_Viva-Otros'!AO:AO,'Resumen PE'!M22),"-") -> - | Q22: =+SUMIFS('Cartera_Viva-Otros'!AM:AM,'Cartera_Viva-Otros'!AL:AL,"1",'Cartera_Viva-Otros'!P:P,"J",'Cartera_Viva-Otros'!AO:AO,'Resumen PE'!M13)/$E$4 -> 0
J23: Prestamos Personales | K23: =+SUMIFS('Cartera_Viva-Otros'!AM:AM,'Cartera_Viva-Otros'!AO:AO,'Resumen PE'!J23,'Cartera_Viva-Otros'!P:P,"J")/$E$4 -> 0 | M23: Prestamos a Sola Firma | N23: =+SUMIFS('Cartera_Viva-Otros'!AN:AN,'Cartera_Viva-Otros'!AL:AL,"1",'Cartera_Viva-Otros'!P:P,"J",'Cartera_Viva-Otros'!AO:AO,'Resumen PE'!M23)/$E$4 -> 0 | O23: =IFERROR(AVERAGEIFS('Cartera_Viva-Otros'!AJ:AJ,'Cartera_Viva-Otros'!AL:AL,"1",'Cartera_Viva-Otros'!P:P,"J",'Cartera_Viva-Otros'!AO:AO,'Resumen PE'!M23),"-") -> - | P23: =IFERROR(AVERAGEIFS('Cartera_Viva-Otros'!AK:AK,'Cartera_Viva-Otros'!AL:AL,"1",'Cartera_Viva-Otros'!P:P,"J",'Cartera_Viva-Otros'!AO:AO,'Resumen PE'!M23),"-") -> - | Q23: =+SUMIFS('Cartera_Viva-Otros'!AM:AM,'Cartera_Viva-Otros'!AL:AL,"1",'Cartera_Viva-Otros'!P:P,"J",'Cartera_Viva-Otros'!AO:AO,'Resumen PE'!M14)/$E$4 -> 0
J24: Prestamos a Sola Firma | K24: =+SUMIFS('Cartera_Viva-Otros'!AM:AM,'Cartera_Viva-Otros'!AO:AO,'Resumen PE'!J24,'Cartera_Viva-Otros'!P:P,"J")/$E$4 -> 0 | M24: ACC | N24: =+SUMIFS('Cartera_Viva-Otros'!AN:AN,'Cartera_Viva-Otros'!AL:AL,"1",'Cartera_Viva-Otros'!P:P,"J",'Cartera_Viva-Otros'!AO:AO,'Resumen PE'!M24)/$E$4 -> 0 | O24: =IFERROR(AVERAGEIFS('Cartera_Viva-Otros'!AJ:AJ,'Cartera_Viva-Otros'!AL:AL,"1",'Cartera_Viva-Otros'!P:P,"J",'Cartera_Viva-Otros'!AO:AO,'Resumen PE'!M24),"-") -> - | P24: =IFERROR(AVERAGEIFS('Cartera_Viva-Otros'!AK:AK,'Cartera_Viva-Otros'!AL:AL,"1",'Cartera_Viva-Otros'!P:P,"J",'Cartera_Viva-Otros'!AO:AO,'Resumen PE'!M24),"-") -> - | Q24: =+SUMIFS('Cartera_Viva-Otros'!AM:AM,'Cartera_Viva-Otros'!AL:AL,"1",'Cartera_Viva-Otros'!P:P,"J",'Cartera_Viva-Otros'!AO:AO,'Resumen PE'!M15)/$E$4 -> 0
J25: ACC | K25: =+SUMIFS('Cartera_Viva-Otros'!AM:AM,'Cartera_Viva-Otros'!AO:AO,'Resumen PE'!J25,'Cartera_Viva-Otros'!P:P,"J")/$E$4 -> 0 | M25: Documentos descontados | N25: =+SUMIFS('Cartera_Viva-Otros'!AN:AN,'Cartera_Viva-Otros'!AL:AL,"1",'Cartera_Viva-Otros'!P:P,"J",'Cartera_Viva-Otros'!AO:AO,'Resumen PE'!M25)/$E$4 -> 0 | O25: =IFERROR(AVERAGEIFS('Cartera_Viva-Otros'!AJ:AJ,'Cartera_Viva-Otros'!AL:AL,"1",'Cartera_Viva-Otros'!P:P,"J",'Cartera_Viva-Otros'!AO:AO,'Resumen PE'!M25),"-") -> - | P25: =IFERROR(AVERAGEIFS('Cartera_Viva-Otros'!AK:AK,'Cartera_Viva-Otros'!AL:AL,"1",'Cartera_Viva-Otros'!P:P,"J",'Cartera_Viva-Otros'!AO:AO,'Resumen PE'!M25),"-") -> - | Q25: =+SUMIFS('Cartera_Viva-Otros'!AM:AM,'Cartera_Viva-Otros'!AL:AL,"1",'Cartera_Viva-Otros'!P:P,"J",'Cartera_Viva-Otros'!AO:AO,'Resumen PE'!M16)/$E$4 -> 0
J26: Documentos descontados | K26: =+SUMIFS('Cartera_Viva-Otros'!AM:AM,'Cartera_Viva-Otros'!AO:AO,'Resumen PE'!J26,'Cartera_Viva-Otros'!P:P,"J")/$E$4 -> 0 | M26: Saldo no utilizado TC | N26: =+SUMIFS(Saldos_No_Util!O:O,Saldos_No_Util!K:K,"1",Saldos_No_Util!P:P,"J",Saldos_No_Util!Q:Q,'Resumen PE'!M26)/$E$4 -> 0.085311825 | O26: =IFERROR(AVERAGEIFS(Saldos_No_Util!L:L,Saldos_No_Util!K:K,"1",Saldos_No_Util!P:P,"J",Saldos_No_Util!Q:Q,'Resumen PE'!M26),0) -> 0.015 | P26: =IFERROR(AVERAGEIFS(Saldos_No_Util!M:M,Saldos_No_Util!K:K,"1",Saldos_No_Util!P:P,"J",Saldos_No_Util!Q:Q,'Resumen PE'!M26),0) -> 0.66499986 | Q26: =+SUMIFS(Saldos_No_Util!G:G,Saldos_No_Util!K:K,"1",Saldos_No_Util!P:P,"J",Saldos_No_Util!Q:Q,'Resumen PE'!M26)/$E$4 -> 16.042228
J27: Saldo no utilizado TC | K27: =+SUMIFS(Saldos_No_Util!G:G,Saldos_No_Util!P:P,"J",Saldos_No_Util!Q:Q,J27)/$E$4 -> 16.042228 | M27: Saldo no utilizado ACC | N27: =+SUMIFS(Saldos_No_Util!O:O,Saldos_No_Util!K:K,"1",Saldos_No_Util!P:P,"J",Saldos_No_Util!Q:Q,'Resumen PE'!M27)/$E$4 -> 0.069973463 | O27: =IFERROR(AVERAGEIFS(Saldos_No_Util!L:L,Saldos_No_Util!K:K,"1",Saldos_No_Util!P:P,"J",Saldos_No_Util!Q:Q,'Resumen PE'!M27),"-") -> 0.015 | P27: =IFERROR(AVERAGEIFS(Saldos_No_Util!M:M,Saldos_No_Util!K:K,"1",Saldos_No_Util!P:P,"J",Saldos_No_Util!Q:Q,'Resumen PE'!M27),"-") -> 0.66499986 | Q27: =+SUMIFS(Saldos_No_Util!G:G,Saldos_No_Util!K:K,"1",Saldos_No_Util!P:P,"J",Saldos_No_Util!Q:Q,'Resumen PE'!M27)/$E$4 -> 11.526606
J28: Saldo no utilizado ACC | K28: =+SUMIFS(Saldos_No_Util!G:G,Saldos_No_Util!P:P,"J",Saldos_No_Util!Q:Q,J28)/$E$4 -> 11.526606 | M28: Call Financiero | N28: =+SUM('Cartera_Viva-Calls'!AJ:AJ)/1000000 -> 0.033128766 | O28: ='Cartera_Viva-Calls'!AH7 -> 5.5326856e-05 | P28: =+'Cartera_Viva-Calls'!AI7 -> 0.66499986 | Q28: =+SUM('Cartera_Viva-Calls'!AC:AC)/1000000 -> 900.42534
J29: Call Financiero | K29: =+SUM('Cartera_Viva-Calls'!AC7:AC8)/'Resumen PE'!$E$4 -> 900.42534 | M29: Otros | N29: =+SUMIFS('Cartera_Viva-Otros'!AN:AN,'Cartera_Viva-Otros'!AL:AL,"1",'Cartera_Viva-Otros'!P:P,"J",'Cartera_Viva-Otros'!AO:AO,"IVA Debito Fiscal no Cobrados")/$E$4 -> 0 | O29: =IFERROR(AVERAGEIFS('Cartera_Viva-Otros'!AJ:AJ,'Cartera_Viva-Otros'!AL:AL,"1",'Cartera_Viva-Otros'!P:P,"J",'Cartera_Viva-Otros'!AO:AO,"IVA Debito Fiscal no Cobrados"),"-") -> - | P29: =IFERROR(AVERAGEIFS('Cartera_Viva-Otros'!AK:AK,'Cartera_Viva-Otros'!AL:AL,"1",'Cartera_Viva-Otros'!P:P,"J",'Cartera_Viva-Otros'!AO:AO,"IVA Debito Fiscal no Cobrados"),"-") -> - | Q29: =+SUMIFS('Cartera_Viva-Otros'!AM:AM,'Cartera_Viva-Otros'!AL:AL,"1",'Cartera_Viva-Otros'!P:P,"J",'Cartera_Viva-Otros'!AO:AO,"IVA Debito Fiscal no Cobrados")/$E$4 -> 0
J30: Otros | K30: =+SUMIFS('Cartera_Viva-Otros'!AM:AM,'Cartera_Viva-Otros'!AO:AO,"IVA Debito Fiscal no Cobrados",'Cartera_Viva-Otros'!P:P,"J")/$E$4 -> 0 | M30: Stage 2
J31: PCE Total | K31: =+K10+K20 -> 1.3484299 | M31: Cartera Minorista | N31: =+(SUMIFS('Cartera_Viva-Otros'!AN:AN,'Cartera_Viva-Otros'!AL:AL,"2",'Cartera_Viva-Otros'!P:P,"F")+SUMIFS(Saldos_No_Util!O:O,Saldos_No_Util!K:K,"2",Saldos_No_Util!P:P,"F"))/$E$4 -> 0 | O31: =IFERROR(AVERAGEIFS('Cartera_Viva-Otros'!AJ:AJ,'Cartera_Viva-Otros'!AL:AL,"2",'Cartera_Viva-Otros'!P:P,"F"),0) -> 0 | P31: =IFERROR(AVERAGEIFS('Cartera_Viva-Otros'!AK:AK,'Cartera_Viva-Otros'!AL:AL,"2",'Cartera_Viva-Otros'!P:P,"F"),0) -> 0 | Q31: =+(SUMIFS('Cartera_Viva-Otros'!AM:AM,'Cartera_Viva-Otros'!AL:AL,"2",'Cartera_Viva-Otros'!P:P,"F")+SUMIFS(Saldos_No_Util!G:G,Saldos_No_Util!K:K,"2",Saldos_No_Util!P:P,"F"))/$E$4 -> 0
J32: EAD Total | K32: =+K11+K21 -> 1080.9938 | M32: Tarjetas_de_Crédito | N32: =+SUMIFS('Cartera_Viva-Otros'!AN:AN,'Cartera_Viva-Otros'!AL:AL,"2",'Cartera_Viva-Otros'!P:P,"F",'Cartera_Viva-Otros'!AO:AO,'Resumen PE'!M32)/$E$4 -> 0 | O32: =IFERROR(AVERAGEIFS('Cartera_Viva-Otros'!AJ:AJ,'Cartera_Viva-Otros'!AL:AL,"2",'Cartera_Viva-Otros'!P:P,"F",'Cartera_Viva-Otros'!AO:AO,'Resumen PE'!M32),"-") -> - | P32: =IFERROR(AVERAGEIFS('Cartera_Viva-Otros'!AK:AK,'Cartera_Viva-Otros'!AL:AL,"2",'Cartera_Viva-Otros'!P:P,"F",'Cartera_Viva-Otros'!AO:AO,'Resumen PE'!M32),"-") -> - | Q32: =+SUMIFS('Cartera_Viva-Otros'!AM:AM,'Cartera_Viva-Otros'!AL:AL,"2",'Cartera_Viva-Otros'!P:P,"F",'Cartera_Viva-Otros'!AO:AO,'Resumen PE'!M32)/$E$4 -> 0
M33: Prestamos Personales | N33: =+SUMIFS('Cartera_Viva-Otros'!AN:AN,'Cartera_Viva-Otros'!AL:AL,"2",'Cartera_Viva-Otros'!P:P,"F",'Cartera_Viva-Otros'!AO:AO,'Resumen PE'!M33)/$E$4 -> 0 | O33: =IFERROR(AVERAGEIFS('Cartera_Viva-Otros'!AJ:AJ,'Cartera_Viva-Otros'!AL:AL,"2",'Cartera_Viva-Otros'!P:P,"F",'Cartera_Viva-Otros'!AO:AO,'Resumen PE'!M33),"-") -> - | P33: =IFERROR(AVERAGEIFS('Cartera_Viva-Otros'!AK:AK,'Cartera_Viva-Otros'!AL:AL,"2",'Cartera_Viva-Otros'!P:P,"F",'Cartera_Viva-Otros'!AO:AO,'Resumen PE'!M33),"-") -> - | Q33: =+SUMIFS('Cartera_Viva-Otros'!AM:AM,'Cartera_Viva-Otros'!AL:AL,"2",'Cartera_Viva-Otros'!P:P,"F",'Cartera_Viva-Otros'!AO:AO,'Resumen PE'!M33)/$E$4 -> 0
M34: Prestamos a Sola Firma | N34: =+SUMIFS('Cartera_Viva-Otros'!AN:AN,'Cartera_Viva-Otros'!AL:AL,"2",'Cartera_Viva-Otros'!P:P,"F",'Cartera_Viva-Otros'!AO:AO,'Resumen PE'!M34)/$E$4 -> 0 | O34: =IFERROR(AVERAGEIFS('Cartera_Viva-Otros'!AJ:AJ,'Cartera_Viva-Otros'!AL:AL,"2",'Cartera_Viva-Otros'!P:P,"F",'Cartera_Viva-Otros'!AO:AO,'Resumen PE'!M34),"-") -> - | P34: =IFERROR(AVERAGEIFS('Cartera_Viva-Otros'!AK:AK,'Cartera_Viva-Otros'!AL:AL,"2",'Cartera_Viva-Otros'!P:P,"F",'Cartera_Viva-Otros'!AO:AO,'Resumen PE'!M34),"-") -> - | Q34: =+SUMIFS('Cartera_Viva-Otros'!AM:AM,'Cartera_Viva-Otros'!AL:AL,"2",'Cartera_Viva-Otros'!P:P,"F",'Cartera_Viva-Otros'!AO:AO,'Resumen PE'!M34)/$E$4 -> 0
M35: ACC | N35: =+SUMIFS('Cartera_Viva-Otros'!AN:AN,'Cartera_Viva-Otros'!AL:AL,"2",'Cartera_Viva-Otros'!P:P,"F",'Cartera_Viva-Otros'!AO:AO,'Resumen PE'!M35)/$E$4 -> 0 | O35: =IFERROR(AVERAGEIFS('Cartera_Viva-Otros'!AJ:AJ,'Cartera_Viva-Otros'!AL:AL,"2",'Cartera_Viva-Otros'!P:P,"F",'Cartera_Viva-Otros'!AO:AO,'Resumen PE'!M35),"-") -> - | P35: =IFERROR(AVERAGEIFS('Cartera_Viva-Otros'!AK:AK,'Cartera_Viva-Otros'!AL:AL,"2",'Cartera_Viva-Otros'!P:P,"F",'Cartera_Viva-Otros'!AO:AO,'Resumen PE'!M35),"-") -> - | Q35: =+SUMIFS('Cartera_Viva-Otros'!AM:AM,'Cartera_Viva-Otros'!AL:AL,"2",'Cartera_Viva-Otros'!P:P,"F",'Cartera_Viva-Otros'!AO:AO,'Resumen PE'!M35)/$E$4 -> 0
M36: Documentos descontados | N36: =+SUMIFS('Cartera_Viva-Otros'!AN:AN,'Cartera_Viva-Otros'!AL:AL,"2",'Cartera_Viva-Otros'!P:P,"F",'Cartera_Viva-Otros'!AO:AO,'Resumen PE'!M36)/$E$4 -> 0 | O36: =IFERROR(AVERAGEIFS('Cartera_Viva-Otros'!AJ:AJ,'Cartera_Viva-Otros'!AL:AL,"2",'Cartera_Viva-Otros'!P:P,"F",'Cartera_Viva-Otros'!AO:AO,'Resumen PE'!M36),"-") -> - | P36: =IFERROR(AVERAGEIFS('Cartera_Viva-Otros'!AK:AK,'Cartera_Viva-Otros'!AL:AL,"2",'Cartera_Viva-Otros'!P:P,"F",'Cartera_Viva-Otros'!AO:AO,'Resumen PE'!M36),"-") -> - | Q36: =+SUMIFS('Cartera_Viva-Otros'!AM:AM,'Cartera_Viva-Otros'!AL:AL,"2",'Cartera_Viva-Otros'!P:P,"F",'Cartera_Viva-Otros'!AO:AO,'Resumen PE'!M36)/$E$4 -> 0
M37: Saldo no utilizado TC | N37: =+SUMIFS(Saldos_No_Util!O:O,Saldos_No_Util!K:K,"2",Saldos_No_Util!P:P,"F",Saldos_No_Util!Q:Q,'Resumen PE'!M37)/$E$4 -> 0 | O37: =IFERROR(AVERAGEIFS(Saldos_No_Util!L:L,Saldos_No_Util!K:K,"2",Saldos_No_Util!P:P,"F",Saldos_No_Util!Q:Q,'Resumen PE'!M37),0) -> 0 | P37: =IFERROR(AVERAGEIFS(Saldos_No_Util!M:M,Saldos_No_Util!K:K,"2",Saldos_No_Util!P:P,"F",Saldos_No_Util!Q:Q,'Resumen PE'!M37),0) -> 0 | Q37: =+SUMIFS(Saldos_No_Util!G:G,Saldos_No_Util!K:K,"2",Saldos_No_Util!P:P,"F",Saldos_No_Util!Q:Q,'Resumen PE'!M37)/$E$4 -> 0
M38: Saldo no utilizado ACC | N38: =+SUMIFS(Saldos_No_Util!O:O,Saldos_No_Util!K:K,"2",Saldos_No_Util!P:P,"F",Saldos_No_Util!Q:Q,'Resumen PE'!M38)/$E$4 -> 0 | O38: =IFERROR(AVERAGEIFS(Saldos_No_Util!L:L,Saldos_No_Util!K:K,"2",Saldos_No_Util!P:P,"F",Saldos_No_Util!Q:Q,'Resumen PE'!M38),"-") -> - | P38: =IFERROR(AVERAGEIFS(Saldos_No_Util!M:M,Saldos_No_Util!K:K,"2",Saldos_No_Util!P:P,"F",Saldos_No_Util!Q:Q,'Resumen PE'!M38),"-") -> - | Q38: =+SUMIFS(Saldos_No_Util!G:G,Saldos_No_Util!K:K,"2",Saldos_No_Util!P:P,"F",Saldos_No_Util!Q:Q,'Resumen PE'!M38)/$E$4 -> 0
M39: Otros | N39: =+SUMIFS('Cartera_Viva-Otros'!AN:AN,'Cartera_Viva-Otros'!AL:AL,"2",'Cartera_Viva-Otros'!P:P,"F",'Cartera_Viva-Otros'!AO:AO,'Resumen PE'!M39)/$E$4 -> 0 | O39: =IFERROR(AVERAGEIFS('Cartera_Viva-Otros'!AJ:AJ,'Cartera_Viva-Otros'!AL:AL,"2",'Cartera_Viva-Otros'!P:P,"F",'Cartera_Viva-Otros'!AO:AO,"IVA Debito Fiscal no Cobrados"),"-") -> - | P39: =IFERROR(AVERAGEIFS('Cartera_Viva-Otros'!AK:AK,'Cartera_Viva-Otros'!AL:AL,"2",'Cartera_Viva-Otros'!P:P,"F",'Cartera_Viva-Otros'!AO:AO,"IVA Debito Fiscal no Cobrados"),"-") -> - | Q39: =+SUMIFS('Cartera_Viva-Otros'!AM:AM,'Cartera_Viva-Otros'!AL:AL,"2",'Cartera_Viva-Otros'!P:P,"F",'Cartera_Viva-Otros'!AO:AO,"IVA Debito Fiscal no Cobrados")/$E$4 -> 0
M40: Cartera Mayorista | N40: =+(SUMIFS('Cartera_Viva-Otros'!AN:AN,'Cartera_Viva-Otros'!AL:AL,"2",'Cartera_Viva-Otros'!P:P,"J")+SUMIFS(Saldos_No_Util!O:O,Saldos_No_Util!P:P,"J",Saldos_No_Util!K:K,"2")+SUMIF('Cartera_Viva-Calls'!AF7,"2",'Cartera_Viva-Calls'!AJ7))/$E$4 -> 0 | O40: =IFERROR(AVERAGEIFS('Cartera_Viva-Otros'!AJ:AJ,'Cartera_Viva-Otros'!AL:AL,"2",'Cartera_Viva-Otros'!P:P,"J"),"-") -> - | P40: =IFERROR(AVERAGEIFS('Cartera_Viva-Otros'!AK:AK,'Cartera_Viva-Otros'!AL:AL,"2",'Cartera_Viva-Otros'!P:P,"J"),"-") -> - | Q40: =+(SUMIFS('Cartera_Viva-Otros'!AM:AM,'Cartera_Viva-Otros'!AL:AL,"2",'Cartera_Viva-Otros'!P:P,"J")+SUMIFS(Saldos_No_Util!G:G,Saldos_No_Util!P:P,"J",Saldos_No_Util!K:K,"2")+SUMIF('Cartera_Viva-Calls'!AF7,"2",'Cartera_Viva-Calls'!AC7))/$E$4 -> 0
M41: Tarjetas_de_Crédito | N41: =+SUMIFS('Cartera_Viva-Otros'!AN:AN,'Cartera_Viva-Otros'!AL:AL,"2",'Cartera_Viva-Otros'!P:P,"J",'Cartera_Viva-Otros'!AO:AO,'Resumen PE'!M41)/$E$4 -> 0 | O41: =IFERROR(AVERAGEIFS('Cartera_Viva-Otros'!AJ:AJ,'Cartera_Viva-Otros'!AL:AL,"2",'Cartera_Viva-Otros'!P:P,"J",'Cartera_Viva-Otros'!AO:AO,'Resumen PE'!M41),"-") -> - | P41: =IFERROR(AVERAGEIFS('Cartera_Viva-Otros'!AK:AK,'Cartera_Viva-Otros'!AL:AL,"2",'Cartera_Viva-Otros'!P:P,"J",'Cartera_Viva-Otros'!AO:AO,'Resumen PE'!M41),"-") -> - | Q41: =+SUMIFS('Cartera_Viva-Otros'!AM:AM,'Cartera_Viva-Otros'!AL:AL,"2",'Cartera_Viva-Otros'!P:P,"J",'Cartera_Viva-Otros'!AO:AO,'Resumen PE'!M32)/$E$4 -> 0
M42: Prestamos Personales | N42: =+SUMIFS('Cartera_Viva-Otros'!AN:AN,'Cartera_Viva-Otros'!AL:AL,"2",'Cartera_Viva-Otros'!P:P,"J",'Cartera_Viva-Otros'!AO:AO,'Resumen PE'!M42)/$E$4 -> 0 | O42: =IFERROR(AVERAGEIFS('Cartera_Viva-Otros'!AJ:AJ,'Cartera_Viva-Otros'!AL:AL,"2",'Cartera_Viva-Otros'!P:P,"J",'Cartera_Viva-Otros'!AO:AO,'Resumen PE'!M42),"-") -> - | P42: =IFERROR(AVERAGEIFS('Cartera_Viva-Otros'!AK:AK,'Cartera_Viva-Otros'!AL:AL,"2",'Cartera_Viva-Otros'!P:P,"J",'Cartera_Viva-Otros'!AO:AO,'Resumen PE'!M42),"-") -> - | Q42: =+SUMIFS('Cartera_Viva-Otros'!AM:AM,'Cartera_Viva-Otros'!AL:AL,"2",'Cartera_Viva-Otros'!P:P,"J",'Cartera_Viva-Otros'!AO:AO,'Resumen PE'!M33)/$E$4 -> 0
M43: Prestamos a Sola Firma | N43: =+SUMIFS('Cartera_Viva-Otros'!AN:AN,'Cartera_Viva-Otros'!AL:AL,"2",'Cartera_Viva-Otros'!P:P,"J",'Cartera_Viva-Otros'!AO:AO,'Resumen PE'!M43)/$E$4 -> 0 | O43: =IFERROR(AVERAGEIFS('Cartera_Viva-Otros'!AJ:AJ,'Cartera_Viva-Otros'!AL:AL,"2",'Cartera_Viva-Otros'!P:P,"J",'Cartera_Viva-Otros'!AO:AO,'Resumen PE'!M43),"-") -> - | P43: =IFERROR(AVERAGEIFS('Cartera_Viva-Otros'!AK:AK,'Cartera_Viva-Otros'!AL:AL,"2",'Cartera_Viva-Otros'!P:P,"J",'Cartera_Viva-Otros'!AO:AO,'Resumen PE'!M43),"-") -> - | Q43: =+SUMIFS('Cartera_Viva-Otros'!AM:AM,'Cartera_Viva-Otros'!AL:AL,"2",'Cartera_Viva-Otros'!P:P,"J",'Cartera_Viva-Otros'!AO:AO,'Resumen PE'!M34)/$E$4 -> 0
M44: ACC | N44: =+SUMIFS('Cartera_Viva-Otros'!AN:AN,'Cartera_Viva-Otros'!AL:AL,"2",'Cartera_Viva-Otros'!P:P,"J",'Cartera_Viva-Otros'!AO:AO,'Resumen PE'!M44)/$E$4 -> 0 | O44: =IFERROR(AVERAGEIFS('Cartera_Viva-Otros'!AJ:AJ,'Cartera_Viva-Otros'!AL:AL,"2",'Cartera_Viva-Otros'!P:P,"J",'Cartera_Viva-Otros'!AO:AO,'Resumen PE'!M44),"-") -> - | P44: =IFERROR(AVERAGEIFS('Cartera_Viva-Otros'!AK:AK,'Cartera_Viva-Otros'!AL:AL,"2",'Cartera_Viva-Otros'!P:P,"J",'Cartera_Viva-Otros'!AO:AO,'Resumen PE'!M44),"-") -> - | Q44: =+SUMIFS('Cartera_Viva-Otros'!AM:AM,'Cartera_Viva-Otros'!AL:AL,"2",'Cartera_Viva-Otros'!P:P,"J",'Cartera_Viva-Otros'!AO:AO,'Resumen PE'!M35)/$E$4 -> 0
M45: Documentos descontados | N45: =+SUMIFS('Cartera_Viva-Otros'!AN:AN,'Cartera_Viva-Otros'!AL:AL,"2",'Cartera_Viva-Otros'!P:P,"J",'Cartera_Viva-Otros'!AO:AO,'Resumen PE'!M45)/$E$4 -> 0 | O45: =IFERROR(AVERAGEIFS('Cartera_Viva-Otros'!AJ:AJ,'Cartera_Viva-Otros'!AL:AL,"2",'Cartera_Viva-Otros'!P:P,"J",'Cartera_Viva-Otros'!AO:AO,'Resumen PE'!M45),"-") -> - | P45: =IFERROR(AVERAGEIFS('Cartera_Viva-Otros'!AK:AK,'Cartera_Viva-Otros'!AL:AL,"2",'Cartera_Viva-Otros'!P:P,"J",'Cartera_Viva-Otros'!AO:AO,'Resumen PE'!M45),"-") -> - | Q45: =+SUMIFS('Cartera_Viva-Otros'!AM:AM,'Cartera_Viva-Otros'!AL:AL,"2",'Cartera_Viva-Otros'!P:P,"J",'Cartera_Viva-Otros'!AO:AO,'Resumen PE'!M36)/$E$4 -> 0
M46: Saldo no utilizado TC | N46: =+SUMIFS(Saldos_No_Util!O:O,Saldos_No_Util!K:K,"2",Saldos_No_Util!P:P,"J",Saldos_No_Util!Q:Q,'Resumen PE'!M46)/$E$4 -> 0 | O46: =IFERROR(AVERAGEIFS(Saldos_No_Util!L:L,Saldos_No_Util!K:K,"2",Saldos_No_Util!P:P,"J",Saldos_No_Util!Q:Q,'Resumen PE'!M46),0) -> 0 | P46: =IFERROR(AVERAGEIFS(Saldos_No_Util!M:M,Saldos_No_Util!K:K,"2",Saldos_No_Util!P:P,"J",Saldos_No_Util!Q:Q,'Resumen PE'!M46),0) -> 0 | Q46: =+SUMIFS(Saldos_No_Util!G:G,Saldos_No_Util!K:K,"2",Saldos_No_Util!P:P,"J",Saldos_No_Util!Q:Q,'Resumen PE'!M46)/$E$4 -> 0
M47: Saldo no utilizado ACC | N47: =+SUMIFS(Saldos_No_Util!O:O,Saldos_No_Util!K:K,"2",Saldos_No_Util!P:P,"J",Saldos_No_Util!Q:Q,'Resumen PE'!M47)/$E$4 -> 0 | O47: =IFERROR(AVERAGEIFS(Saldos_No_Util!L:L,Saldos_No_Util!K:K,"2",Saldos_No_Util!P:P,"J",Saldos_No_Util!Q:Q,'Resumen PE'!M47),"-") -> - | P47: =IFERROR(AVERAGEIFS(Saldos_No_Util!M:M,Saldos_No_Util!K:K,"2",Saldos_No_Util!P:P,"J",Saldos_No_Util!Q:Q,'Resumen PE'!M47),"-") -> - | Q47: =+SUMIFS(Saldos_No_Util!G:G,Saldos_No_Util!K:K,"2",Saldos_No_Util!P:P,"J",Saldos_No_Util!Q:Q,'Resumen PE'!M47)/$E$4 -> 0
M48: Call Financiero | N48: =+'Cartera_Viva-Calls'!AJ22/1000000 -> 0 | O48: =+'Cartera_Viva-Calls'!AH22 -> 0 | P48: =+'Cartera_Viva-Calls'!AI22 -> 0 | Q48: =+'Cartera_Viva-Calls'!AC22/1000000 -> 0
M49: Otros | N49: =+SUMIFS('Cartera_Viva-Otros'!AN:AN,'Cartera_Viva-Otros'!AL:AL,"2",'Cartera_Viva-Otros'!P:P,"J",'Cartera_Viva-Otros'!AO:AO,"IVA Debito Fiscal no Cobrados")/$E$4 -> 0 | O49: =IFERROR(AVERAGEIFS('Cartera_Viva-Otros'!AJ:AJ,'Cartera_Viva-Otros'!AL:AL,"2",'Cartera_Viva-Otros'!P:P,"J",'Cartera_Viva-Otros'!AO:AO,"IVA Debito Fiscal no Cobrados"),"-") -> - | P49: =IFERROR(AVERAGEIFS('Cartera_Viva-Otros'!AK:AK,'Cartera_Viva-Otros'!AL:AL,"2",'Cartera_Viva-Otros'!P:P,"J",'Cartera_Viva-Otros'!AO:AO,"IVA Debito Fiscal no Cobrados"),"-") -> - | Q49: =+SUMIFS('Cartera_Viva-Otros'!AM:AM,'Cartera_Viva-Otros'!AL:AL,"2",'Cartera_Viva-Otros'!P:P,"J",'Cartera_Viva-Otros'!AO:AO,"IVA Debito Fiscal no Cobrados")/$E$4 -> 0
M50: Stage 3
M51: Cartera Minorista | N51: =+(SUMIFS('Cartera_Viva-Otros'!AN:AN,'Cartera_Viva-Otros'!AL:AL,"3",'Cartera_Viva-Otros'!P:P,"F")+SUMIFS(Saldos_No_Util!O:O,Saldos_No_Util!K:K,"3",Saldos_No_Util!P:P,"F"))/$E$4 -> 0.35015728 | O51: =AVERAGEIFS('Cartera_Viva-Otros'!AJ:AJ,'Cartera_Viva-Otros'!AL:AL,"3",'Cartera_Viva-Otros'!P:P,"F") -> #DIV/0! | P51: =AVERAGEIFS('Cartera_Viva-Otros'!AK:AK,'Cartera_Viva-Otros'!AL:AL,"3",'Cartera_Viva-Otros'!P:P,"F") -> #DIV/0! | Q51: =+(SUMIFS('Cartera_Viva-Otros'!AM:AM,'Cartera_Viva-Otros'!AL:AL,"3",'Cartera_Viva-Otros'!P:P,"F")+SUMIFS(Saldos_No_Util!G:G,Saldos_No_Util!K:K,"3",Saldos_No_Util!P:P,"F"))/$E$4 -> 0.7119747
M52: Tarjetas_de_Crédito | N52: =+SUMIFS('Cartera_Viva-Otros'!AN:AN,'Cartera_Viva-Otros'!AL:AL,"3",'Cartera_Viva-Otros'!P:P,"F",'Cartera_Viva-Otros'!AO:AO,'Resumen PE'!M52)/$E$4 -> 0 | O52: =IFERROR(AVERAGEIFS('Cartera_Viva-Otros'!AJ:AJ,'Cartera_Viva-Otros'!AL:AL,"3",'Cartera_Viva-Otros'!P:P,"F",'Cartera_Viva-Otros'!AO:AO,'Resumen PE'!M52),"-") -> - | P52: =IFERROR(AVERAGEIFS('Cartera_Viva-Otros'!AK:AK,'Cartera_Viva-Otros'!AL:AL,"3",'Cartera_Viva-Otros'!P:P,"F",'Cartera_Viva-Otros'!AO:AO,'Resumen PE'!M52),"-") -> - | Q52: =+SUMIFS('Cartera_Viva-Otros'!AM:AM,'Cartera_Viva-Otros'!AL:AL,"3",'Cartera_Viva-Otros'!P:P,"F",'Cartera_Viva-Otros'!AO:AO,'Resumen PE'!M52)/$E$4 -> 0
M53: Prestamos Personales | N53: =+SUMIFS('Cartera_Viva-Otros'!AN:AN,'Cartera_Viva-Otros'!AL:AL,"3",'Cartera_Viva-Otros'!P:P,"F",'Cartera_Viva-Otros'!AO:AO,'Resumen PE'!M53)/$E$4 -> 0 | O53: =IFERROR(AVERAGEIFS('Cartera_Viva-Otros'!AJ:AJ,'Cartera_Viva-Otros'!AL:AL,"3",'Cartera_Viva-Otros'!P:P,"F",'Cartera_Viva-Otros'!AO:AO,'Resumen PE'!M53),"-") -> - | P53: =IFERROR(AVERAGEIFS('Cartera_Viva-Otros'!AK:AK,'Cartera_Viva-Otros'!AL:AL,"3",'Cartera_Viva-Otros'!P:P,"F",'Cartera_Viva-Otros'!AO:AO,'Resumen PE'!M53),"-") -> - | Q53: =+SUMIFS('Cartera_Viva-Otros'!AM:AM,'Cartera_Viva-Otros'!AL:AL,"3",'Cartera_Viva-Otros'!P:P,"F",'Cartera_Viva-Otros'!AO:AO,'Resumen PE'!M53)/$E$4 -> 0
M54: Prestamos a Sola Firma | N54: =+SUMIFS('Cartera_Viva-Otros'!AN:AN,'Cartera_Viva-Otros'!AL:AL,"3",'Cartera_Viva-Otros'!P:P,"F",'Cartera_Viva-Otros'!AO:AO,'Resumen PE'!M54)/$E$4 -> 0 | O54: =IFERROR(AVERAGEIFS('Cartera_Viva-Otros'!AJ:AJ,'Cartera_Viva-Otros'!AL:AL,"3",'Cartera_Viva-Otros'!P:P,"F",'Cartera_Viva-Otros'!AO:AO,'Resumen PE'!M54),"-") -> - | P54: =IFERROR(AVERAGEIFS('Cartera_Viva-Otros'!AK:AK,'Cartera_Viva-Otros'!AL:AL,"3",'Cartera_Viva-Otros'!P:P,"F",'Cartera_Viva-Otros'!AO:AO,'Resumen PE'!M54),"-") -> - | Q54: =+SUMIFS('Cartera_Viva-Otros'!AM:AM,'Cartera_Viva-Otros'!AL:AL,"3",'Cartera_Viva-Otros'!P:P,"F",'Cartera_Viva-Otros'!AO:AO,'Resumen PE'!M54)/$E$4 -> 0
M55: ACC | N55: =+SUMIFS('Cartera_Viva-Otros'!AN:AN,'Cartera_Viva-Otros'!AL:AL,"3",'Cartera_Viva-Otros'!P:P,"F",'Cartera_Viva-Otros'!AO:AO,'Resumen PE'!M55)/$E$4 -> 0 | O55: =IFERROR(AVERAGEIFS('Cartera_Viva-Otros'!AJ:AJ,'Cartera_Viva-Otros'!AL:AL,"3",'Cartera_Viva-Otros'!P:P,"F",'Cartera_Viva-Otros'!AO:AO,'Resumen PE'!M55),"-") -> - | P55: =IFERROR(AVERAGEIFS('Cartera_Viva-Otros'!AK:AK,'Cartera_Viva-Otros'!AL:AL,"3",'Cartera_Viva-Otros'!P:P,"F",'Cartera_Viva-Otros'!AO:AO,'Resumen PE'!M55),"-") -> - | Q55: =+SUMIFS('Cartera_Viva-Otros'!AM:AM,'Cartera_Viva-Otros'!AL:AL,"3",'Cartera_Viva-Otros'!P:P,"F",'Cartera_Viva-Otros'!AO:AO,'Resumen PE'!M55)/$E$4 -> 0
M56: Documentos descontados | N56: =+SUMIFS('Cartera_Viva-Otros'!AN:AN,'Cartera_Viva-Otros'!AL:AL,"3",'Cartera_Viva-Otros'!P:P,"F",'Cartera_Viva-Otros'!AO:AO,'Resumen PE'!M56)/$E$4 -> 0 | O56: =IFERROR(AVERAGEIFS('Cartera_Viva-Otros'!AJ:AJ,'Cartera_Viva-Otros'!AL:AL,"3",'Cartera_Viva-Otros'!P:P,"F",'Cartera_Viva-Otros'!AO:AO,'Resumen PE'!M56),"-") -> - | P56: =IFERROR(AVERAGEIFS('Cartera_Viva-Otros'!AK:AK,'Cartera_Viva-Otros'!AL:AL,"3",'Cartera_Viva-Otros'!P:P,"F",'Cartera_Viva-Otros'!AO:AO,'Resumen PE'!M56),"-") -> - | Q56: =+SUMIFS('Cartera_Viva-Otros'!AM:AM,'Cartera_Viva-Otros'!AL:AL,"3",'Cartera_Viva-Otros'!P:P,"F",'Cartera_Viva-Otros'!AO:AO,'Resumen PE'!M56)/$E$4 -> 0
M57: Saldo no utilizado TC | N57: =+SUMIFS(Saldos_No_Util!O:O,Saldos_No_Util!K:K,"3",Saldos_No_Util!P:P,"F",Saldos_No_Util!Q:Q,'Resumen PE'!M57)/$E$4 -> 0.35015728 | O57: =IFERROR(AVERAGEIFS(Saldos_No_Util!L:L,Saldos_No_Util!K:K,"3",Saldos_No_Util!P:P,"F",Saldos_No_Util!Q:Q,'Resumen PE'!M57),0) -> 1 | P57: =IFERROR(AVERAGEIFS(Saldos_No_Util!M:M,Saldos_No_Util!K:K,"3",Saldos_No_Util!P:P,"F",Saldos_No_Util!Q:Q,'Resumen PE'!M57),0) -> 0.92250106 | Q57: =+SUMIFS(Saldos_No_Util!G:G,Saldos_No_Util!K:K,"3",Saldos_No_Util!P:P,"F",Saldos_No_Util!Q:Q,'Resumen PE'!M57)/$E$4 -> 0.7119747
M58: Saldo no utilizado ACC | N58: =+SUMIFS('Cartera_Viva-Otros'!AN:AN,'Cartera_Viva-Otros'!AL:AL,"3",'Cartera_Viva-Otros'!P:P,"F",'Cartera_Viva-Otros'!AO:AO,'Resumen PE'!M58)/$E$4 -> 0 | O58: =IFERROR(AVERAGEIFS(Saldos_No_Util!L:L,Saldos_No_Util!K:K,"3",Saldos_No_Util!P:P,"F",Saldos_No_Util!Q:Q,'Resumen PE'!M58),"-") -> - | P58: =IFERROR(AVERAGEIFS(Saldos_No_Util!M:M,Saldos_No_Util!K:K,"3",Saldos_No_Util!P:P,"F",Saldos_No_Util!Q:Q,'Resumen PE'!M58),"-") -> - | Q58: =+SUMIFS('Cartera_Viva-Otros'!AM:AM,'Cartera_Viva-Otros'!AL:AL,"3",'Cartera_Viva-Otros'!P:P,"F",'Cartera_Viva-Otros'!AO:AO,'Resumen PE'!M58)/$E$4 -> 0
M59: Otros | N59: =+SUMIFS('Cartera_Viva-Otros'!AN:AN,'Cartera_Viva-Otros'!AL:AL,"3",'Cartera_Viva-Otros'!P:P,"F",'Cartera_Viva-Otros'!AO:AO,'Resumen PE'!M59)/$E$4 -> 0 | O59: =IFERROR(AVERAGEIFS('Cartera_Viva-Otros'!AJ:AJ,'Cartera_Viva-Otros'!AL:AL,"3",'Cartera_Viva-Otros'!P:P,"F",'Cartera_Viva-Otros'!AO:AO,"IVA Debito Fiscal no Cobrados"),"-") -> - | P59: =IFERROR(AVERAGEIFS('Cartera_Viva-Otros'!AK:AK,'Cartera_Viva-Otros'!AL:AL,"3",'Cartera_Viva-Otros'!P:P,"F",'Cartera_Viva-Otros'!AO:AO,"IVA Debito Fiscal no Cobrados"),"-") -> - | Q59: =+SUMIFS('Cartera_Viva-Otros'!AM:AM,'Cartera_Viva-Otros'!AL:AL,"3",'Cartera_Viva-Otros'!P:P,"F",'Cartera_Viva-Otros'!AO:AO,"IVA Debito Fiscal no Cobrados")/$E$4 -> 0
M60: Cartera Mayorista | N60: =+(SUMIFS('Cartera_Viva-Otros'!AN:AN,'Cartera_Viva-Otros'!AL:AL,"3",'Cartera_Viva-Otros'!P:P,"J")+SUMIFS(Saldos_No_Util!O:O,Saldos_No_Util!P:P,"J",Saldos_No_Util!K:K,"3")+SUMIF('Cartera_Viva-Calls'!AF7,"3",'Cartera_Viva-Calls'!AJ7))/$E$4 -> 0 | O60: =IFERROR(AVERAGEIFS('Cartera_Viva-Otros'!AJ:AJ,'Cartera_Viva-Otros'!AL:AL,"3",'Cartera_Viva-Otros'!P:P,"J"),"-") -> - | P60: =IFERROR(AVERAGEIFS('Cartera_Viva-Otros'!AK:AK,'Cartera_Viva-Otros'!AL:AL,"3",'Cartera_Viva-Otros'!P:P,"J"),"-") -> - | Q60: =+(SUMIFS('Cartera_Viva-Otros'!AM:AM,'Cartera_Viva-Otros'!AL:AL,"3",'Cartera_Viva-Otros'!P:P,"J")+SUMIFS(Saldos_No_Util!G:G,Saldos_No_Util!P:P,"J",Saldos_No_Util!K:K,"3")+SUMIF('Cartera_Viva-Calls'!AF7,"3",'Cartera_Viva-Calls'!AC7))/$E$4 -> 0
M61: Tarjetas_de_Crédito | N61: =+SUMIFS('Cartera_Viva-Otros'!AN:AN,'Cartera_Viva-Otros'!AL:AL,"3",'Cartera_Viva-Otros'!P:P,"J",'Cartera_Viva-Otros'!AO:AO,'Resumen PE'!M61)/$E$4 -> 0 | O61: =IFERROR(AVERAGEIFS('Cartera_Viva-Otros'!AJ:AJ,'Cartera_Viva-Otros'!AL:AL,"3",'Cartera_Viva-Otros'!P:P,"J",'Cartera_Viva-Otros'!AO:AO,'Resumen PE'!M61),"-") -> - | P61: =IFERROR(AVERAGEIFS('Cartera_Viva-Otros'!AK:AK,'Cartera_Viva-Otros'!AL:AL,"3",'Cartera_Viva-Otros'!P:P,"J",'Cartera_Viva-Otros'!AO:AO,'Resumen PE'!M61),"-") -> - | Q61: =+SUMIFS('Cartera_Viva-Otros'!AM:AM,'Cartera_Viva-Otros'!AL:AL,"3",'Cartera_Viva-Otros'!P:P,"J",'Cartera_Viva-Otros'!AO:AO,'Resumen PE'!M52)/$E$4 -> 0
M62: Prestamos Personales | N62: =+SUMIFS('Cartera_Viva-Otros'!AN:AN,'Cartera_Viva-Otros'!AL:AL,"3",'Cartera_Viva-Otros'!P:P,"J",'Cartera_Viva-Otros'!AO:AO,'Resumen PE'!M62)/$E$4 -> 0 | O62: =IFERROR(AVERAGEIFS('Cartera_Viva-Otros'!AJ:AJ,'Cartera_Viva-Otros'!AL:AL,"3",'Cartera_Viva-Otros'!P:P,"J",'Cartera_Viva-Otros'!AO:AO,'Resumen PE'!M62),"-") -> - | P62: =IFERROR(AVERAGEIFS('Cartera_Viva-Otros'!AK:AK,'Cartera_Viva-Otros'!AL:AL,"3",'Cartera_Viva-Otros'!P:P,"J",'Cartera_Viva-Otros'!AO:AO,'Resumen PE'!M62),"-") -> - | Q62: =+SUMIFS('Cartera_Viva-Otros'!AM:AM,'Cartera_Viva-Otros'!AL:AL,"3",'Cartera_Viva-Otros'!P:P,"J",'Cartera_Viva-Otros'!AO:AO,'Resumen PE'!M53)/$E$4 -> 0
M63: Prestamos a Sola Firma | N63: =+SUMIFS('Cartera_Viva-Otros'!AN:AN,'Cartera_Viva-Otros'!AL:AL,"3",'Cartera_Viva-Otros'!P:P,"J",'Cartera_Viva-Otros'!AO:AO,'Resumen PE'!M63)/$E$4 -> 0 | O63: =IFERROR(AVERAGEIFS('Cartera_Viva-Otros'!AJ:AJ,'Cartera_Viva-Otros'!AL:AL,"3",'Cartera_Viva-Otros'!P:P,"J",'Cartera_Viva-Otros'!AO:AO,'Resumen PE'!M63),"-") -> - | P63: =IFERROR(AVERAGEIFS('Cartera_Viva-Otros'!AK:AK,'Cartera_Viva-Otros'!AL:AL,"3",'Cartera_Viva-Otros'!P:P,"J",'Cartera_Viva-Otros'!AO:AO,'Resumen PE'!M63),"-") -> - | Q63: =+SUMIFS('Cartera_Viva-Otros'!AM:AM,'Cartera_Viva-Otros'!AL:AL,"3",'Cartera_Viva-Otros'!P:P,"J",'Cartera_Viva-Otros'!AO:AO,'Resumen PE'!M54)/$E$4 -> 0
M64: ACC | N64: =+SUMIFS('Cartera_Viva-Otros'!AN:AN,'Cartera_Viva-Otros'!AL:AL,"3",'Cartera_Viva-Otros'!P:P,"J",'Cartera_Viva-Otros'!AO:AO,'Resumen PE'!M64)/$E$4 -> 0 | O64: =IFERROR(AVERAGEIFS('Cartera_Viva-Otros'!AJ:AJ,'Cartera_Viva-Otros'!AL:AL,"3",'Cartera_Viva-Otros'!P:P,"J",'Cartera_Viva-Otros'!AO:AO,'Resumen PE'!M64),"-") -> - | P64: =IFERROR(AVERAGEIFS('Cartera_Viva-Otros'!AK:AK,'Cartera_Viva-Otros'!AL:AL,"3",'Cartera_Viva-Otros'!P:P,"J",'Cartera_Viva-Otros'!AO:AO,'Resumen PE'!M64),"-") -> - | Q64: =+SUMIFS('Cartera_Viva-Otros'!AM:AM,'Cartera_Viva-Otros'!AL:AL,"3",'Cartera_Viva-Otros'!P:P,"J",'Cartera_Viva-Otros'!AO:AO,'Resumen PE'!M55)/$E$4 -> 0
M65: Documentos descontados | N65: =+SUMIFS('Cartera_Viva-Otros'!AN:AN,'Cartera_Viva-Otros'!AL:AL,"3",'Cartera_Viva-Otros'!P:P,"J",'Cartera_Viva-Otros'!AO:AO,'Resumen PE'!M65)/$E$4 -> 0 | O65: =IFERROR(AVERAGEIFS('Cartera_Viva-Otros'!AJ:AJ,'Cartera_Viva-Otros'!AL:AL,"3",'Cartera_Viva-Otros'!P:P,"J",'Cartera_Viva-Otros'!AO:AO,'Resumen PE'!M65),"-") -> - | P65: =IFERROR(AVERAGEIFS('Cartera_Viva-Otros'!AK:AK,'Cartera_Viva-Otros'!AL:AL,"3",'Cartera_Viva-Otros'!P:P,"J",'Cartera_Viva-Otros'!AO:AO,'Resumen PE'!M65),"-") -> - | Q65: =+SUMIFS('Cartera_Viva-Otros'!AM:AM,'Cartera_Viva-Otros'!AL:AL,"3",'Cartera_Viva-Otros'!P:P,"J",'Cartera_Viva-Otros'!AO:AO,'Resumen PE'!M56)/$E$4 -> 0
M66: Saldo no utilizado TC | N66: =+SUMIFS(Saldos_No_Util!O:O,Saldos_No_Util!K:K,"3",Saldos_No_Util!P:P,"J",Saldos_No_Util!Q:Q,'Resumen PE'!M66)/$E$4 -> 0 | O66: =IFERROR(AVERAGEIFS(Saldos_No_Util!L:L,Saldos_No_Util!K:K,"3",Saldos_No_Util!P:P,"J",Saldos_No_Util!Q:Q,'Resumen PE'!M66),0) -> 0 | P66: =IFERROR(AVERAGEIFS(Saldos_No_Util!M:M,Saldos_No_Util!K:K,"3",Saldos_No_Util!P:P,"J",Saldos_No_Util!Q:Q,'Resumen PE'!M66),0) -> 0 | Q66: =+SUMIFS(Saldos_No_Util!G:G,Saldos_No_Util!K:K,"3",Saldos_No_Util!P:P,"J",Saldos_No_Util!Q:Q,'Resumen PE'!M66)/$E$4 -> 0
M67: Saldo no utilizado ACC | N67: =+SUMIFS('Cartera_Viva-Otros'!AN:AN,'Cartera_Viva-Otros'!AL:AL,"3",'Cartera_Viva-Otros'!P:P,"J",'Cartera_Viva-Otros'!AO:AO,'Resumen PE'!M67)/$E$4 -> 0 | O67: =IFERROR(AVERAGEIFS(Saldos_No_Util!L:L,Saldos_No_Util!K:K,"3",Saldos_No_Util!P:P,"J",Saldos_No_Util!Q:Q,'Resumen PE'!M67),"-") -> - | P67: =IFERROR(AVERAGEIFS(Saldos_No_Util!M:M,Saldos_No_Util!K:K,"3",Saldos_No_Util!P:P,"J",Saldos_No_Util!Q:Q,'Resumen PE'!M67),"-") -> - | Q67: =+SUMIFS('Cartera_Viva-Otros'!AM:AM,'Cartera_Viva-Otros'!AL:AL,"3",'Cartera_Viva-Otros'!P:P,"J",'Cartera_Viva-Otros'!AO:AO,'Resumen PE'!M67)/$E$4 -> 0
M68: Call Financiero | N68: =+'Cartera_Viva-Calls'!AJ42/1000000 -> 0 | O68: =+'Cartera_Viva-Calls'!AH42 -> 0 | P68: =+'Cartera_Viva-Calls'!AI42 -> 0 | Q68: =+'Cartera_Viva-Calls'!AC42/1000000 -> 0
M69: Otros | N69: =+SUMIFS('Cartera_Viva-Otros'!AN:AN,'Cartera_Viva-Otros'!AL:AL,"3",'Cartera_Viva-Otros'!P:P,"J",'Cartera_Viva-Otros'!AO:AO,"IVA Debito Fiscal no Cobrados")/$E$4 -> 0 | O69: =IFERROR(AVERAGEIFS('Cartera_Viva-Otros'!AJ:AJ,'Cartera_Viva-Otros'!AL:AL,"3",'Cartera_Viva-Otros'!P:P,"J",'Cartera_Viva-Otros'!AO:AO,"IVA Debito Fiscal no Cobrados"),"-") -> - | P69: =IFERROR(AVERAGEIFS('Cartera_Viva-Otros'!AK:AK,'Cartera_Viva-Otros'!AL:AL,"3",'Cartera_Viva-Otros'!P:P,"J",'Cartera_Viva-Otros'!AO:AO,"IVA Debito Fiscal no Cobrados"),"-") -> - | Q69: =+SUMIFS('Cartera_Viva-Otros'!AM:AM,'Cartera_Viva-Otros'!AL:AL,"3",'Cartera_Viva-Otros'!P:P,"J",'Cartera_Viva-Otros'!AO:AO,"IVA Debito Fiscal no Cobrados")/$E$4 -> 0

Sheet Cartera_Viva-Otros
A1: BCRubr | B1: BCMda | C1: BCCta | D1: BCOper | E1: BCSbOp | F1: BCFech | G1: BCFVto | H1: BCFVal | I1: BCPlaz | J1: BCTTasa | K1: BCTasa | L1: BCTDia | M1: BCTAno | N1: BCResi | O1: BCCate | P1: BCActi | Q1: BCTiCu | R1: BCFAtr | S1: BCSdOr | T1: BCSdMN | U1: BCSdUS | V1: BCSdMO | W1: BCInt | X1: BCPrev | Y1: BCCate sin esp | Z1: Situación BCRA | AA1: rubros_considerados | AB1: rubros_considerados_2 | AC1: Deuda+int | AD1: PD | AE1: PD_diaria | AF1: Plazo1 | AG1: Plazo2 | AH1: Min(Plazo;365) | AI1: Plazo Prom | AJ1: PD o 100% | AK1: LGD | AL1: Stage | AM1: EAD | AN1: PE | AO1: Producto | AQ1: FECHA DE CALCULO | AR1: =$F$2 -> 46142
A2: 131709001 | B2: 80 | C2: 6206 | D2: 3563 | E2: 0 | F2: 46142 | G2: 46417 | H2: 46052 | I2: 365 | J2: 2 | K2: 73 | L2: 0 | M2: 0 | N2: S | O2: Sit.Normal | P2: 466 | Q2: J | R2: 46136 | S2: 0 | T2: -22482.8 | U2: -16.28 | V2: -22482.8 | W2: 0 | X2: 224.83 | Y2: =TRIM(O2) -> Sit.Normal | Z2: =IF(Y2="Sit.Normal",1,IF(Y2="Riesgo potencia",2,IF(Y2="Con Problemas",3,IF(Y2="Alto Riesgo",4,IF(Y2="Irrecuperable",5,IF(Y2="Irrec Disp Tecn",6,IF(Y2="Sin identificación",0,""))))))) -> 1 | AB2: =VLOOKUP(A2,rubros_a_considerar!$A$2:$A$13,1,FALSE) -> 131709001 | AC2: =T2+W2 -> -22482.8 | AD2: =IF(Z2<=1,Diccionario!$M$2,Diccionario!$M$3) -> 0.015 | AE2: =1-(1-AD2)^(1/365) -> 4.140637e-05 | AF2: =+IFERROR(G2-$AR$1,0) -> 275 | AG2: =+IF(AF2<=0,10*365,AF2) -> 275 | AH2: =+IF(Z2<=1,MIN(AG2,365),AG2) -> 275 | AI2: =+(1-(AG2+1)*(1-AE2)^AG2+AG2*(1-AE2)^(AG2+1))/((1-(1-AE2)^AG2)*AE2)-0.5 -> 137.23905 | AJ2: =+IF(Z2<3,AD2,1) -> 0.015 | AK2: =IF(Z2<=3,Diccionario!$O$2,IF(Z2=4,Diccionario!$O$5,Diccionario!$O$6)) -> 0.66499986 | AL2: =+IF(Z2<=1,1,IF(Z2=2,2,3)) -> 1 | AM2: =+IF(AC2<0,-AC2,0) -> 22482.8 | AN2: =MIN(AJ2*AK2*AM2*(1+'[2]Pesos escenarios'!$F$8/2),AM2) -> 298.90621 | AO2: =IFERROR(VLOOKUP(A2,Diccionario!$C$2:$E$65,3,FALSE),"no") -> ACC
A3: 131709001 | B3: 80 | C3: 85455 | D3: 3560 | E3: 0 | F3: 46142 | G3: 46302 | H3: 45937 | I3: 365 | J3: 2 | K3: 73 | L3: 0 | M3: 0 | N3: S | O3: Sit.Normal | P3: 620 | Q3: J | R3: 46142 | S3: 0 | T3: -103456.1 | U3: -74.91 | V3: -103456.1 | W3: 0 | X3: 1034.56 | Y3: =TRIM(O3) -> Sit.Normal | Z3: =IF(Y3="Sit.Normal",1,IF(Y3="Riesgo potencia",2,IF(Y3="Con Problemas",3,IF(Y3="Alto Riesgo",4,IF(Y3="Irrecuperable",5,IF(Y3="Irrec Disp Tecn",6,IF(Y3="Sin identificación",0,""))))))) -> 1 | AB3: =VLOOKUP(A3,rubros_a_considerar!$A$2:$A$13,1,FALSE) -> 131709001 | AC3: =T3+W3 -> -103456.1 | AD3: =IF(Z3<=1,Diccionario!$M$2,Diccionario!$M$3) -> 0.015 | AE3: =1-(1-AD3)^(1/365) -> 4.140637e-05 | AF3: =+IFERROR(G3-$AR$1,0) -> 160 | AG3: =+IF(AF3<=0,10*365,AF3) -> 160 | AH3: =+IF(Z3<=1,MIN(AG3,365),AG3) -> 160 | AI3: =+(1-(AG3+1)*(1-AE3)^AG3+AG3*(1-AE3)^(AG3+1))/((1-(1-AE3)^AG3)*AE3)-0.5 -> 79.911668 | AJ3: =+IF(Z3<3,AD3,1) -> 0.015 | AK3: =IF(Z3<=3,Diccionario!$O$2,IF(Z3=4,Diccionario!$O$5,Diccionario!$O$6)) -> 0.66499986 | AL3: =+IF(Z3<=1,1,IF(Z3=2,2,3)) -> 1 | AM3: =+IF(AC3<0,-AC3,0) -> 103456.1 | AN3: =MIN(AJ3*AK3*AM3*(1+'[2]Pesos escenarios'!$F$8/2),AM3) -> 1375.4368 | AO3: =IFERROR(VLOOKUP(A3,Diccionario!$C$2:$E$65,3,FALSE),"no") -> ACC
A4: 131709001 | B4: 80 | C4: 59750 | D4: 3553 | E4: 0 | F4: 46142 | G4: 46235 | H4: 45870 | I4: 365 | J4: 2 | K4: 52 | L4: 0 | M4: 0 | N4: S | O4: Sit.Normal | P4: 103 | Q4: J | R4: 45797 | S4: 0 | T4: -7347455.2 | U4: -5320.02 | V4: -7347455.2 | W4: 0 | X4: 73474.55 | Y4: =TRIM(O4) -> Sit.Normal | Z4: =IF(Y4="Sit.Normal",1,IF(Y4="Riesgo potencia",2,IF(Y4="Con Problemas",3,IF(Y4="Alto Riesgo",4,IF(Y4="Irrecuperable",5,IF(Y4="Irrec Disp Tecn",6,IF(Y4="Sin identificación",0,""))))))) -> 1 | AB4: =VLOOKUP(A4,rubros_a_considerar!$A$2:$A$13,1,FALSE) -> 131709001 | AC4: =T4+W4 -> -7347455.2 | AD4: =IF(Z4<=1,Diccionario!$M$2,Diccionario!$M$3) -> 0.015 | AE4: =1-(1-AD4)^(1/365) -> 4.140637e-05 | AF4: =+IFERROR(G4-$AR$1,0) -> 93 | AG4: =+IF(AF4<=0,10*365,AF4) -> 93 | AH4: =+IF(Z4<=1,MIN(AG4,365),AG4) -> 93 | AI4: =+(1-(AG4+1)*(1-AE4)^AG4+AG4*(1-AE4)^(AG4+1))/((1-(1-AE4)^AG4)*AE4)-0.5 -> 46.470159 | AJ4: =+IF(Z4<3,AD4,1) -> 0.015 | AK4: =IF(Z4<=3,Diccionario!$O$2,IF(Z4=4,Diccionario!$O$5,Diccionario!$O$6)) -> 0.66499986 | AL4: =+IF(Z4<=1,1,IF(Z4=2,2,3)) -> 1 | AM4: =+IF(AC4<0,-AC4,0) -> 7347455.2 | AN4: =MIN(AJ4*AK4*AM4*(1+'[2]Pesos escenarios'!$F$8/2),AM4) -> 97683.562 | AO4: =IFERROR(VLOOKUP(A4,Diccionario!$C$2:$E$65,3,FALSE),"no") -> ACC
A5: 141154001 | B5: 80 | C5: 86152 | D5: 42805 | E5: 0 | F5: 46142 | G5: 1753-01-01 | H5: 46142 | I5: 0 | J5: 0 | K5: 0 | L5: 0 | M5: 0 | N5: S | O5: Sit.Normal | P5: 999 | Q5: F | R5: 46142 | S5: 0 | T5: -707.32 | U5: -0.51 | V5: -707.32 | W5: 0 | X5: 7.07 | Y5: =TRIM(O5) -> Sit.Normal | Z5: =IF(Y5="Sit.Normal",1,IF(Y5="Riesgo potencia",2,IF(Y5="Con Problemas",3,IF(Y5="Alto Riesgo",4,IF(Y5="Irrecuperable",5,IF(Y5="Irrec Disp Tecn",6,IF(Y5="Sin identificación",0,""))))))) -> 1 | AB5: =VLOOKUP(A5,rubros_a_considerar!$A$2:$A$13,1,FALSE) -> 141154001 | AC5: =T5+W5 -> -707.32 | AD5: =IF(Z5<=1,Diccionario!$M$2,Diccionario!$M$3) -> 0.015 | AE5: =1-(1-AD5)^(1/365) -> 4.140637e-05 | AF5: =+IFERROR(G5-$AR$1,0) -> 0 | AG5: =+IF(AF5<=0,10*365,AF5) -> 3650 | AH5: =+IF(Z5<=1,MIN(AG5,365),AG5) -> 365 | AI5: =+(1-(AG5+1)*(1-AE5)^AG5+AG5*(1-AE5)^(AG5+1))/((1-(1-AE5)^AG5)*AE5)-0.5 -> 1779.0468 | AJ5: =+IF(Z5<3,AD5,1) -> 0.015 | AK5: =IF(Z5<=3,Diccionario!$O$2,IF(Z5=4,Diccionario!$O$5,Diccionario!$O$6)) -> 0.66499986 | AL5: =+IF(Z5<=1,1,IF(Z5=2,2,3)) -> 1 | AM5: =+IF(AC5<0,-AC5,0) -> 707.32 | AN5: =MIN(AJ5*AK5*AM5*(1+'[2]Pesos escenarios'!$F$8/2),AM5) -> 9.4037372 | AO5: =IFERROR(VLOOKUP(A5,Diccionario!$C$2:$E$65,3,FALSE),"no") -> IVA Debito Fiscal no Cobrados
A6: 141154001 | B6: 80 | C6: 86563 | D6: 42806 | E6: 0 | F6: 46142 | G6: 1753-01-01 | H6: 46142 | I6: 0 | J6: 0 | K6: 0 | L6: 0 | M6: 0 | N6: S | O6: Sit.Normal | P6: 999 | Q6: F | R6: 46142 | S6: 0 | T6: -1108.73 | U6: -0.8 | V6: -1108.73 | W6: 0 | X6: 11.09 | Y6: =TRIM(O6) -> Sit.Normal | Z6: =IF(Y6="Sit.Normal",1,IF(Y6="Riesgo potencia",2,IF(Y6="Con Problemas",3,IF(Y6="Alto Riesgo",4,IF(Y6="Irrecuperable",5,IF(Y6="Irrec Disp Tecn",6,IF(Y6="Sin identificación",0,""))))))) -> 1 | AB6: =VLOOKUP(A6,rubros_a_considerar!$A$2:$A$13,1,FALSE) -> 141154001 | AC6: =T6+W6 -> -1108.73 | AD6: =IF(Z6<=1,Diccionario!$M$2,Diccionario!$M$3) -> 0.015 | AE6: =1-(1-AD6)^(1/365) -> 4.140637e-05 | AF6: =+IFERROR(G6-$AR$1,0) -> 0 | AG6: =+IF(AF6<=0,10*365,AF6) -> 3650 | AH6: =+IF(Z6<=1,MIN(AG6,365),AG6) -> 365 | AI6: =+(1-(AG6+1)*(1-AE6)^AG6+AG6*(1-AE6)^(AG6+1))/((1-(1-AE6)^AG6)*AE6)-0.5 -> 1779.0468 | AJ6: =+IF(Z6<3,AD6,1) -> 0.015 | AK6: =IF(Z6<=3,Diccionario!$O$2,IF(Z6=4,Diccionario!$O$5,Diccionario!$O$6)) -> 0.66499986 | AL6: =+IF(Z6<=1,1,IF(Z6=2,2,3)) -> 1 | AM6: =+IF(AC6<0,-AC6,0) -> 1108.73 | AN6: =MIN(AJ6*AK6*AM6*(1+'[2]Pesos escenarios'!$F$8/2),AM6) -> 14.740437 | AO6: =IFERROR(VLOOKUP(A6,Diccionario!$C$2:$E$65,3,FALSE),"no") -> IVA Debito Fiscal no Cobrados
A7: 141154001 | B7: 80 | C7: 57649 | D7: 42906 | E7: 0 | F7: 46142 | G7: 1753-01-01 | H7: 46142 | I7: 0 | J7: 0 | K7: 0 | L7: 0 | M7: 0 | N7: S | O7: Sit.Normal | P7: 999 | Q7: F | R7: 46142 | S7: 0 | T7: -2625.33 | U7: -1.9 | V7: -2625.33 | W7: 0 | X7: 26.25 | Y7: =TRIM(O7) -> Sit.Normal | Z7: =IF(Y7="Sit.Normal",1,IF(Y7="Riesgo potencia",2,IF(Y7="Con Problemas",3,IF(Y7="Alto Riesgo",4,IF(Y7="Irrecuperable",5,IF(Y7="Irrec Disp Tecn",6,IF(Y7="Sin identificación",0,""))))))) -> 1 | AB7: =VLOOKUP(A7,rubros_a_considerar!$A$2:$A$13,1,FALSE) -> 141154001 | AC7: =T7+W7 -> -2625.33 | AD7: =IF(Z7<=1,Diccionario!$M$2,Diccionario!$M$3) -> 0.015 | AE7: =1-(1-AD7)^(1/365) -> 4.140637e-05 | AF7: =+IFERROR(G7-$AR$1,0) -> 0 | AG7: =+IF(AF7<=0,10*365,AF7) -> 3650 | AH7: =+IF(Z7<=1,MIN(AG7,365),AG7) -> 365 | AI7: =+(1-(AG7+1)*(1-AE7)^AG7+AG7*(1-AE7)^(AG7+1))/((1-(1-AE7)^AG7)*AE7)-0.5 -> 1779.0468 | AJ7: =+IF(Z7<3,AD7,1) -> 0.015 | AK7: =IF(Z7<=3,Diccionario!$O$2,IF(Z7=4,Diccionario!$O$5,Diccionario!$O$6)) -> 0.66499986 | AL7: =+IF(Z7<=1,1,IF(Z7=2,2,3)) -> 1 | AM7: =+IF(AC7<0,-AC7,0) -> 2625.33 | AN7: =MIN(AJ7*AK7*AM7*(1+'[2]Pesos escenarios'!$F$8/2),AM7) -> 34.903457 | AO7: =IFERROR(VLOOKUP(A7,Diccionario!$C$2:$E$65,3,FALSE),"no") -> IVA Debito Fiscal no Cobrados
A8: 141154001 | B8: 80 | C8: 56956 | D8: 42856 | E8: 0 | F8: 46142 | G8: 1753-01-01 | H8: 46142 | I8: 0 | J8: 0 | K8: 0 | L8: 0 | M8: 0 | N8: S | O8: Sit.Normal | P8: 999 | Q8: F | R8: 46142 | S8: 0 | T8: -2691.65 | U8: -1.95 | V8: -2691.65 | W8: 0 | X8: 26.92 | Y8: =TRIM(O8) -> Sit.Normal | Z8: =IF(Y8="Sit.Normal",1,IF(Y8="Riesgo potencia",2,IF(Y8="Con Problemas",3,IF(Y8="Alto Riesgo",4,IF(Y8="Irrecuperable",5,IF(Y8="Irrec Disp Tecn",6,IF(Y8="Sin identificación",0,""))))))) -> 1 | AB8: =VLOOKUP(A8,rubros_a_considerar!$A$2:$A$13,1,FALSE) -> 141154001 | AC8: =T8+W8 -> -2691.65 | AD8: =IF(Z8<=1,Diccionario!$M$2,Diccionario!$M$3) -> 0.015 | AE8: =1-(1-AD8)^(1/365) -> 4.140637e-05 | AF8: =+IFERROR(G8-$AR$1,0) -> 0 | AG8: =+IF(AF8<=0,10*365,AF8) -> 3650 | AH8: =+IF(Z8<=1,MIN(AG8,365),AG8) -> 365 | AI8: =+(1-(AG8+1)*(1-AE8)^AG8+AG8*(1-AE8)^(AG8+1))/((1-(1-AE8)^AG8)*AE8)-0.5 -> 1779.0468 | AJ8: =+IF(Z8<3,AD8,1) -> 0.015 | AK8: =IF(Z8<=3,Diccionario!$O$2,IF(Z8=4,Diccionario!$O$5,Diccionario!$O$6)) -> 0.66499986 | AL8: =+IF(Z8<=1,1,IF(Z8=2,2,3)) -> 1 | AM8: =+IF(AC8<0,-AC8,0) -> 2691.65 | AN8: =MIN(AJ8*AK8*AM8*(1+'[2]Pesos escenarios'!$F$8/2),AM8) -> 35.785174 | AO8: =IFERROR(VLOOKUP(A8,Diccionario!$C$2:$E$65,3,FALSE),"no") -> IVA Debito Fiscal no Cobrados
A9: 141154001 | B9: 80 | C9: 57332 | D9: 42861 | E9: 0 | F9: 46142 | G9: 1753-01-01 | H9: 46142 | I9: 0 | J9: 0 | K9: 0 | L9: 0 | M9: 0 | N9: S | O9: Sit.Normal | P9: 999 | Q9: F | R9: 46142 | S9: 0 | T9: -3217.07 | U9: -2.33 | V9: -3217.07 | W9: 0 | X9: 32.17 | Y9: =TRIM(O9) -> Sit.Normal | Z9: =IF(Y9="Sit.Normal",1,IF(Y9="Riesgo potencia",2,IF(Y9="Con Problemas",3,IF(Y9="Alto Riesgo",4,IF(Y9="Irrecuperable",5,IF(Y9="Irrec Disp Tecn",6,IF(Y9="Sin identificación",0,""))))))) -> 1 | AB9: =VLOOKUP(A9,rubros_a_considerar!$A$2:$A$13,1,FALSE) -> 141154001 | AC9: =T9+W9 -> -3217.07 | AD9: =IF(Z9<=1,Diccionario!$M$2,Diccionario!$M$3) -> 0.015 | AE9: =1-(1-AD9)^(1/365) -> 4.140637e-05 | AF9: =+IFERROR(G9-$AR$1,0) -> 0 | AG9: =+IF(AF9<=0,10*365,AF9) -> 3650 | AH9: =+IF(Z9<=1,MIN(AG9,365),AG9) -> 365 | AI9: =+(1-(AG9+1)*(1-AE9)^AG9+AG9*(1-AE9)^(AG9+1))/((1-(1-AE9)^AG9)*AE9)-0.5 -> 1779.0468 | AJ9: =+IF(Z9<3,AD9,1) -> 0.015 | AK9: =IF(Z9<=3,Diccionario!$O$2,IF(Z9=4,Diccionario!$O$5,Diccionario!$O$6)) -> 0.66499986 | AL9: =+IF(Z9<=1,1,IF(Z9=2,2,3)) -> 1 | AM9: =+IF(AC9<0,-AC9,0) -> 3217.07 | AN9: =MIN(AJ9*AK9*AM9*(1+'[2]Pesos escenarios'!$F$8/2),AM9) -> 42.770572 | AO9: =IFERROR(VLOOKUP(A9,Diccionario!$C$2:$E$65,3,FALSE),"no") -> IVA Debito Fiscal no Cobrados
A10: 141154001 | B10: 80 | C10: 55476 | D10: 42932 | E10: 0 | F10: 46142 | G10: 1753-01-01 | H10: 46142 | I10: 0 | J10: 0 | K10: 0 | L10: 0 | M10: 0 | N10: S | O10: Sit.Normal | P10: 999 | Q10: F | R10: 46142 | S10: 0 | T10: -3428.21 | U10: -2.48 | V10: -3428.21 | W10: 0 | X10: 34.28 | Y10: =TRIM(O10) -> Sit.Normal | Z10: =IF(Y10="Sit.Normal",1,IF(Y10="Riesgo potencia",2,IF(Y10="Con Problemas",3,IF(Y10="Alto Riesgo",4,IF(Y10="Irrecuperable",5,IF(Y10="Irrec Disp Tecn",6,IF(Y10="Sin identificación",0,""))))))) -> 1 | AB10: =VLOOKUP(A10,rubros_a_considerar!$A$2:$A$13,1,FALSE) -> 141154001 | AC10: =T10+W10 -> -3428.21 | AD10: =IF(Z10<=1,Diccionario!$M$2,Diccionario!$M$3) -> 0.015 | AE10: =1-(1-AD10)^(1/365) -> 4.140637e-05 | AF10: =+IFERROR(G10-$AR$1,0) -> 0 | AG10: =+IF(AF10<=0,10*365,AF10) -> 3650 | AH10: =+IF(Z10<=1,MIN(AG10,365),AG10) -> 365 | AI10: =+(1-(AG10+1)*(1-AE10)^AG10+AG10*(1-AE10)^(AG10+1))/((1-(1-AE10)^AG10)*AE10)-0.5 -> 1779.0468 | AJ10: =+IF(Z10<3,AD10,1) -> 0.015 | AK10: =IF(Z10<=3,Diccionario!$O$2,IF(Z10=4,Diccionario!$O$5,Diccionario!$O$6)) -> 0.66499986 | AL10: =+IF(Z10<=1,1,IF(Z10=2,2,3)) -> 1 | AM10: =+IF(AC10<0,-AC10,0) -> 3428.21 | AN10: =MIN(AJ10*AK10*AM10*(1+'[2]Pesos escenarios'!$F$8/2),AM10) -> 45.577654 | AO10: =IFERROR(VLOOKUP(A10,Diccionario!$C$2:$E$65,3,FALSE),"no") -> IVA Debito Fiscal no Cobrados
A11: 141154001 | B11: 80 | C11: 83381 | D11: 42930 | E11: 0 | F11: 46142 | G11: 1753-01-01 | H11: 46142 | I11: 0 | J11: 0 | K11: 0 | L11: 0 | M11: 0 | N11: S | O11: Sit.Normal | P11: 999 | Q11: F | R11: 46142 | S11: 0 | T11: -3656.76 | U11: -2.65 | V11: -3656.76 | W11: 0 | X11: 36.57 | Y11: =TRIM(O11) -> Sit.Normal | Z11: =IF(Y11="Sit.Normal",1,IF(Y11="Riesgo potencia",2,IF(Y11="Con Problemas",3,IF(Y11="Alto Riesgo",4,IF(Y11="Irrecuperable",5,IF(Y11="Irrec Disp Tecn",6,IF(Y11="Sin identificación",0,""))))))) -> 1 | AB11: =VLOOKUP(A11,rubros_a_considerar!$A$2:$A$13,1,FALSE) -> 141154001 | AC11: =T11+W11 -> -3656.76 | AD11: =IF(Z11<=1,Diccionario!$M$2,Diccionario!$M$3) -> 0.015 | AE11: =1-(1-AD11)^(1/365) -> 4.140637e-05 | AF11: =+IFERROR(G11-$AR$1,0) -> 0 | AG11: =+IF(AF11<=0,10*365,AF11) -> 3650 | AH11: =+IF(Z11<=1,MIN(AG11,365),AG11) -> 365 | AI11: =+(1-(AG11+1)*(1-AE11)^AG11+AG11*(1-AE11)^(AG11+1))/((1-(1-AE11)^AG11)*AE11)-0.5 -> 1779.0468 | AJ11: =+IF(Z11<3,AD11,1) -> 0.015 | AK11: =IF(Z11<=3,Diccionario!$O$2,IF(Z11=4,Diccionario!$O$5,Diccionario!$O$6)) -> 0.66499986 | AL11: =+IF(Z11<=1,1,IF(Z11=2,2,3)) -> 1 | AM11: =+IF(AC11<0,-AC11,0) -> 3656.76 | AN11: =MIN(AJ11*AK11*AM11*(1+'[2]Pesos escenarios'!$F$8/2),AM11) -> 48.616199 | AO11: =IFERROR(VLOOKUP(A11,Diccionario!$C$2:$E$65,3,FALSE),"no") -> IVA Debito Fiscal no Cobrados
A12: 141154001 | B12: 80 | C12: 86245 | D12: 42921 | E12: 0 | F12: 46142 | G12: 1753-01-01 | H12: 46142 | I12: 0 | J12: 0 | K12: 0 | L12: 0 | M12: 0 | N12: S | O12: Sit.Normal | P12: 999 | Q12: F | R12: 46142 | S12: 0 | T12: -4976.63 | U12: -3.6 | V12: -4976.63 | W12: 0 | X12: 49.77 | Y12: =TRIM(O12) -> Sit.Normal | Z12: =IF(Y12="Sit.Normal",1,IF(Y12="Riesgo potencia",2,IF(Y12="Con Problemas",3,IF(Y12="Alto Riesgo",4,IF(Y12="Irrecuperable",5,IF(Y12="Irrec Disp Tecn",6,IF(Y12="Sin identificación",0,""))))))) -> 1 | AB12: =VLOOKUP(A12,rubros_a_considerar!$A$2:$A$13,1,FALSE) -> 141154001 | AC12: =T12+W12 -> -4976.63 | AD12: =IF(Z12<=1,Diccionario!$M$2,Diccionario!$M$3) -> 0.015 | AE12: =1-(1-AD12)^(1/365) -> 4.140637e-05 | AF12: =+IFERROR(G12-$AR$1,0) -> 0 | AG12: =+IF(AF12<=0,10*365,AF12) -> 3650 | AH12: =+IF(Z12<=1,MIN(AG12,365),AG12) -> 365 | AI12: =+(1-(AG12+1)*(1-AE12)^AG12+AG12*(1-AE12)^(AG12+1))/((1-(1-AE12)^AG12)*AE12)-0.5 -> 1779.0468 | AJ12: =+IF(Z12<3,AD12,1) -> 0.015 | AK12: =IF(Z12<=3,Diccionario!$O$2,IF(Z12=4,Diccionario!$O$5,Diccionario!$O$6)) -> 0.66499986 | AL12: =+IF(Z12<=1,1,IF(Z12=2,2,3)) -> 1 | AM12: =+IF(AC12<0,-AC12,0) -> 4976.63 | AN12: =MIN(AJ12*AK12*AM12*(1+'[2]Pesos escenarios'!$F$8/2),AM12) -> 66.163718 | AO12: =IFERROR(VLOOKUP(A12,Diccionario!$C$2:$E$65,3,FALSE),"no") -> IVA Debito Fiscal no Cobrados
A13: 141154001 | B13: 80 | C13: 86807 | D13: 42880 | E13: 0 | F13: 46142 | G13: 1753-01-01 | H13: 46142 | I13: 0 | J13: 0 | K13: 0 | L13: 0 | M13: 0 | N13: S | O13: Sit.Normal | P13: 999 | Q13: F | R13: 46142 | S13: 0 | T13: -6306.34 | U13: -4.57 | V13: -6306.34 | W13: 0 | X13: 63.06 | Y13: =TRIM(O13) -> Sit.Normal | Z13: =IF(Y13="Sit.Normal",1,IF(Y13="Riesgo potencia",2,IF(Y13="Con Problemas",3,IF(Y13="Alto Riesgo",4,IF(Y13="Irrecuperable",5,IF(Y13="Irrec Disp Tecn",6,IF(Y13="Sin identificación",0,""))))))) -> 1 | AB13: =VLOOKUP(A13,rubros_a_considerar!$A$2:$A$13,1,FALSE) -> 141154001 | AC13: =T13+W13 -> -6306.34 | AD13: =IF(Z13<=1,Diccionario!$M$2,Diccionario!$M$3) -> 0.015 | AE13: =1-(1-AD13)^(1/365) -> 4.140637e-05 | AF13: =+IFERROR(G13-$AR$1,0) -> 0 | AG13: =+IF(AF13<=0,10*365,AF13) -> 3650 | AH13: =+IF(Z13<=1,MIN(AG13,365),AG13) -> 365 | AI13: =+(1-(AG13+1)*(1-AE13)^AG13+AG13*(1-AE13)^(AG13+1))/((1-(1-AE13)^AG13)*AE13)-0.5 -> 1779.0468 | AJ13: =+IF(Z13<3,AD13,1) -> 0.015 | AK13: =IF(Z13<=3,Diccionario!$O$2,IF(Z13=4,Diccionario!$O$5,Diccionario!$O$6)) -> 0.66499986 | AL13: =+IF(Z13<=1,1,IF(Z13=2,2,3)) -> 1 | AM13: =+IF(AC13<0,-AC13,0) -> 6306.34 | AN13: =MIN(AJ13*AK13*AM13*(1+'[2]Pesos escenarios'!$F$8/2),AM13) -> 83.842058 | AO13: =IFERROR(VLOOKUP(A13,Diccionario!$C$2:$E$65,3,FALSE),"no") -> IVA Debito Fiscal no Cobrados
A14: 141154001 | B14: 80 | C14: 84457 | D14: 42922 | E14: 0 | F14: 46142 | G14: 1753-01-01 | H14: 46142 | I14: 0 | J14: 0 | K14: 0 | L14: 0 | M14: 0 | N14: S | O14: Sit.Normal | P14: 999 | Q14: F | R14: 46142 | S14: 0 | T14: -8847.35 | U14: -6.41 | V14: -8847.35 | W14: 0 | X14: 88.47 | Y14: =TRIM(O14) -> Sit.Normal | Z14: =IF(Y14="Sit.Normal",1,IF(Y14="Riesgo potencia",2,IF(Y14="Con Problemas",3,IF(Y14="Alto Riesgo",4,IF(Y14="Irrecuperable",5,IF(Y14="Irrec Disp Tecn",6,IF(Y14="Sin identificación",0,""))))))) -> 1 | AB14: =VLOOKUP(A14,rubros_a_considerar!$A$2:$A$13,1,FALSE) -> 141154001 | AC14: =T14+W14 -> -8847.35 | AD14: =IF(Z14<=1,Diccionario!$M$2,Diccionario!$M$3) -> 0.015 | AE14: =1-(1-AD14)^(1/365) -> 4.140637e-05 | AF14: =+IFERROR(G14-$AR$1,0) -> 0 | AG14: =+IF(AF14<=0,10*365,AF14) -> 3650 | AH14: =+IF(Z14<=1,MIN(AG14,365),AG14) -> 365 | AI14: =+(1-(AG14+1)*(1-AE14)^AG14+AG14*(1-AE14)^(AG14+1))/((1-(1-AE14)^AG14)*AE14)-0.5 -> 1779.0468 | AJ14: =+IF(Z14<3,AD14,1) -> 0.015 | AK14: =IF(Z14<=3,Diccionario!$O$2,IF(Z14=4,Diccionario!$O$5,Diccionario!$O$6)) -> 0.66499986 | AL14: =+IF(Z14<=1,1,IF(Z14=2,2,3)) -> 1 | AM14: =+IF(AC14<0,-AC14,0) -> 8847.35 | AN14: =MIN(AJ14*AK14*AM14*(1+'[2]Pesos escenarios'!$F$8/2),AM14) -> 117.62449 | AO14: =IFERROR(VLOOKUP(A14,Diccionario!$C$2:$E$65,3,FALSE),"no") -> IVA Debito Fiscal no Cobrados
A15: 141154001 | B15: 80 | C15: 55257 | D15: 42940 | E15: 0 | F15: 46142 | G15: 1753-01-01 | H15: 46142 | I15: 0 | J15: 0 | K15: 0 | L15: 0 | M15: 0 | N15: S | O15: Sit.Normal | P15: 999 | Q15: F | R15: 46142 | S15: 0 | T15: -9141.9 | U15: -6.62 | V15: -9141.9 | W15: 0 | X15: 91.42 | Y15: =TRIM(O15) -> Sit.Normal | Z15: =IF(Y15="Sit.Normal",1,IF(Y15="Riesgo potencia",2,IF(Y15="Con Problemas",3,IF(Y15="Alto Riesgo",4,IF(Y15="Irrecuperable",5,IF(Y15="Irrec Disp Tecn",6,IF(Y15="Sin identificación",0,""))))))) -> 1 | AB15: =VLOOKUP(A15,rubros_a_considerar!$A$2:$A$13,1,FALSE) -> 141154001 | AC15: =T15+W15 -> -9141.9 | AD15: =IF(Z15<=1,Diccionario!$M$2,Diccionario!$M$3) -> 0.015 | AE15: =1-(1-AD15)^(1/365) -> 4.140637e-05 | AF15: =+IFERROR(G15-$AR$1,0) -> 0 | AG15: =+IF(AF15<=0,10*365,AF15) -> 3650 | AH15: =+IF(Z15<=1,MIN(AG15,365),AG15) -> 365 | AI15: =+(1-(AG15+1)*(1-AE15)^AG15+AG15*(1-AE15)^(AG15+1))/((1-(1-AE15)^AG15)*AE15)-0.5 -> 1779.0468 | AJ15: =+IF(Z15<3,AD15,1) -> 0.015 | AK15: =IF(Z15<=3,Diccionario!$O$2,IF(Z15=4,Diccionario!$O$5,Diccionario!$O$6)) -> 0.66499986 | AL15: =+IF(Z15<=1,1,IF(Z15=2,2,3)) -> 1 | AM15: =+IF(AC15<0,-AC15,0) -> 9141.9 | AN15: =MIN(AJ15*AK15*AM15*(1+'[2]Pesos escenarios'!$F$8/2),AM15) -> 121.5405 | AO15: =IFERROR(VLOOKUP(A15,Diccionario!$C$2:$E$65,3,FALSE),"no") -> IVA Debito Fiscal no Cobrados
A16: 141154001 | B16: 80 | C16: 86774 | D16: 42931 | E16: 0 | F16: 46142 | G16: 1753-01-01 | H16: 46142 | I16: 0 | J16: 0 | K16: 0 | L16: 0 | M16: 0 | N16: S | O16: Sit.Normal | P16: 999 | Q16: F | R16: 46142 | S16: 0 | T16: -9141.9 | U16: -6.62 | V16: -9141.9 | W16: 0 | X16: 91.42 | Y16: =TRIM(O16) -> Sit.Normal | Z16: =IF(Y16="Sit.Normal",1,IF(Y16="Riesgo potencia",2,IF(Y16="Con Problemas",3,IF(Y16="Alto Riesgo",4,IF(Y16="Irrecuperable",5,IF(Y16="Irrec Disp Tecn",6,IF(Y16="Sin identificación",0,""))))))) -> 1 | AB16: =VLOOKUP(A16,rubros_a_considerar!$A$2:$A$13,1,FALSE) -> 141154001 | AC16: =T16+W16 -> -9141.9 | AD16: =IF(Z16<=1,Diccionario!$M$2,Diccionario!$M$3) -> 0.015 | AE16: =1-(1-AD16)^(1/365) -> 4.140637e-05 | AF16: =+IFERROR(G16-$AR$1,0) -> 0 | AG16: =+IF(AF16<=0,10*365,AF16) -> 3650 | AH16: =+IF(Z16<=1,MIN(AG16,365),AG16) -> 365 | AI16: =+(1-(AG16+1)*(1-AE16)^AG16+AG16*(1-AE16)^(AG16+1))/((1-(1-AE16)^AG16)*AE16)-0.5 -> 1779.0468 | AJ16: =+IF(Z16<3,AD16,1) -> 0.015 | AK16: =IF(Z16<=3,Diccionario!$O$2,IF(Z16=4,Diccionario!$O$5,Diccionario!$O$6)) -> 0.66499986 | AL16: =+IF(Z16<=1,1,IF(Z16=2,2,3)) -> 1 | AM16: =+IF(AC16<0,-AC16,0) -> 9141.9 | AN16: =MIN(AJ16*AK16*AM16*(1+'[2]Pesos escenarios'!$F$8/2),AM16) -> 121.5405 | AO16: =IFERROR(VLOOKUP(A16,Diccionario!$C$2:$E$65,3,FALSE),"no") -> IVA Debito Fiscal no Cobrados
A17: 141154001 | B17: 80 | C17: 57497 | D17: 42937 | E17: 0 | F17: 46142 | G17: 1753-01-01 | H17: 46142 | I17: 0 | J17: 0 | K17: 0 | L17: 0 | M17: 0 | N17: S | O17: Sit.Normal | P17: 999 | Q17: F | R17: 46142 | S17: 0 | T17: -9314.39 | U17: -6.74 | V17: -9314.39 | W17: 0 | X17: 93.14 | Y17: =TRIM(O17) -> Sit.Normal | Z17: =IF(Y17="Sit.Normal",1,IF(Y17="Riesgo potencia",2,IF(Y17="Con Problemas",3,IF(Y17="Alto Riesgo",4,IF(Y17="Irrecuperable",5,IF(Y17="Irrec Disp Tecn",6,IF(Y17="Sin identificación",0,""))))))) -> 1 | AB17: =VLOOKUP(A17,rubros_a_considerar!$A$2:$A$13,1,FALSE) -> 141154001 | AC17: =T17+W17 -> -9314.39 | AD17: =IF(Z17<=1,Diccionario!$M$2,Diccionario!$M$3) -> 0.015 | AE17: =1-(1-AD17)^(1/365) -> 4.140637e-05 | AF17: =+IFERROR(G17-$AR$1,0) -> 0 | AG17: =+IF(AF17<=0,10*365,AF17) -> 3650 | AH17: =+IF(Z17<=1,MIN(AG17,365),AG17) -> 365 | AI17: =+(1-(AG17+1)*(1-AE17)^AG17+AG17*(1-AE17)^(AG17+1))/((1-(1-AE17)^AG17)*AE17)-0.5 -> 1779.0468 | AJ17: =+IF(Z17<3,AD17,1) -> 0.015 | AK17: =IF(Z17<=3,Diccionario!$O$2,IF(Z17=4,Diccionario!$O$5,Diccionario!$O$6)) -> 0.66499986 | AL17: =+IF(Z17<=1,1,IF(Z17=2,2,3)) -> 1 | AM17: =+IF(AC17<0,-AC17,0) -> 9314.39 | AN17: =MIN(AJ17*AK17*AM17*(1+'[2]Pesos escenarios'!$F$8/2),AM17) -> 123.83373 | AO17: =IFERROR(VLOOKUP(A17,Diccionario!$C$2:$E$65,3,FALSE),"no") -> IVA Debito Fiscal no Cobrados | AS17: =AS15-AS16 -> 0
A18: 141154001 | B18: 80 | C18: 84662 | D18: 42960 | E18: 0 | F18: 46142 | G18: 1753-01-01 | H18: 46142 | I18: 0 | J18: 0 | K18: 0 | L18: 0 | M18: 0 | N18: S | O18: Sit.Normal | P18: 999 | Q18: F | R18: 46142 | S18: 0 | T18: -9450 | U18: -6.84 | V18: -9450 | W18: 0 | X18: 94.5 | Y18: =TRIM(O18) -> Sit.Normal | Z18: =IF(Y18="Sit.Normal",1,IF(Y18="Riesgo potencia",2,IF(Y18="Con Problemas",3,IF(Y18="Alto Riesgo",4,IF(Y18="Irrecuperable",5,IF(Y18="Irrec Disp Tecn",6,IF(Y18="Sin identificación",0,""))))))) -> 1 | AB18: =VLOOKUP(A18,rubros_a_considerar!$A$2:$A$13,1,FALSE) -> 141154001 | AC18: =T18+W18 -> -9450 | AD18: =IF(Z18<=1,Diccionario!$M$2,Diccionario!$M$3) -> 0.015 | AE18: =1-(1-AD18)^(1/365) -> 4.140637e-05 | AF18: =+IFERROR(G18-$AR$1,0) -> 0 | AG18: =+IF(AF18<=0,10*365,AF18) -> 3650 | AH18: =+IF(Z18<=1,MIN(AG18,365),AG18) -> 365 | AI18: =+(1-(AG18+1)*(1-AE18)^AG18+AG18*(1-AE18)^(AG18+1))/((1-(1-AE18)^AG18)*AE18)-0.5 -> 1779.0468 | AJ18: =+IF(Z18<3,AD18,1) -> 0.015 | AK18: =IF(Z18<=3,Diccionario!$O$2,IF(Z18=4,Diccionario!$O$5,Diccionario!$O$6)) -> 0.66499986 | AL18: =+IF(Z18<=1,1,IF(Z18=2,2,3)) -> 1 | AM18: =+IF(AC18<0,-AC18,0) -> 9450 | AN18: =MIN(AJ18*AK18*AM18*(1+'[2]Pesos escenarios'!$F$8/2),AM18) -> 125.63665 | AO18: =IFERROR(VLOOKUP(A18,Diccionario!$C$2:$E$65,3,FALSE),"no") -> IVA Debito Fiscal no Cobrados
A19: 141154001 | B19: 80 | C19: 85825 | D19: 42947 | E19: 0 | F19: 46142 | G19: 1753-01-01 | H19: 46142 | I19: 0 | J19: 0 | K19: 0 | L19: 0 | M19: 0 | N19: S | O19: Sit.Normal | P19: 999 | Q19: F | R19: 46142 | S19: 0 | T19: -9481.27 | U19: -6.87 | V19: -9481.27 | W19: 0 | X19: 94.81 | Y19: =TRIM(O19) -> Sit.Normal | Z19: =IF(Y19="Sit.Normal",1,IF(Y19="Riesgo potencia",2,IF(Y19="Con Problemas",3,IF(Y19="Alto Riesgo",4,IF(Y19="Irrecuperable",5,IF(Y19="Irrec Disp Tecn",6,IF(Y19="Sin identificación",0,""))))))) -> 1 | AB19: =VLOOKUP(A19,rubros_a_considerar!$A$2:$A$13,1,FALSE) -> 141154001 | AC19: =T19+W19 -> -9481.27 | AD19: =IF(Z19<=1,Diccionario!$M$2,Diccionario!$M$3) -> 0.015 | AE19: =1-(1-AD19)^(1/365) -> 4.140637e-05 | AF19: =+IFERROR(G19-$AR$1,0) -> 0 | AG19: =+IF(AF19<=0,10*365,AF19) -> 3650 | AH19: =+IF(Z19<=1,MIN(AG19,365),AG19) -> 365 | AI19: =+(1-(AG19+1)*(1-AE19)^AG19+AG19*(1-AE19)^(AG19+1))/((1-(1-AE19)^AG19)*AE19)-0.5 -> 1779.0468 | AJ19: =+IF(Z19<3,AD19,1) -> 0.015 | AK19: =IF(Z19<=3,Diccionario!$O$2,IF(Z19=4,Diccionario!$O$5,Diccionario!$O$6)) -> 0.66499986 | AL19: =+IF(Z19<=1,1,IF(Z19=2,2,3)) -> 1 | AM19: =+IF(AC19<0,-AC19,0) -> 9481.27 | AN19: =MIN(AJ19*AK19*AM19*(1+'[2]Pesos escenarios'!$F$8/2),AM19) -> 126.05238 | AO19: =IFERROR(VLOOKUP(A19,Diccionario!$C$2:$E$65,3,FALSE),"no") -> IVA Debito Fiscal no Cobrados
A20: 141154001 | B20: 80 | C20: 86883 | D20: 42962 | E20: 0 | F20: 46142 | G20: 1753-01-01 | H20: 46142 | I20: 0 | J20: 0 | K20: 0 | L20: 0 | M20: 0 | N20: S | O20: Sit.Normal | P20: 999 | Q20: F | R20: 46142 | S20: 0 | T20: -10416 | U20: -7.54 | V20: -10416 | W20: 0 | X20: 104.16 | Y20: =TRIM(O20) -> Sit.Normal | Z20: =IF(Y20="Sit.Normal",1,IF(Y20="Riesgo potencia",2,IF(Y20="Con Problemas",3,IF(Y20="Alto Riesgo",4,IF(Y20="Irrecuperable",5,IF(Y20="Irrec Disp Tecn",6,IF(Y20="Sin identificación",0,""))))))) -> 1 | AB20: =VLOOKUP(A20,rubros_a_considerar!$A$2:$A$13,1,FALSE) -> 141154001 | AC20: =T20+W20 -> -10416 | AD20: =IF(Z20<=1,Diccionario!$M$2,Diccionario!$M$3) -> 0.015 | AE20: =1-(1-AD20)^(1/365) -> 4.140637e-05 | AF20: =+IFERROR(G20-$AR$1,0) -> 0 | AG20: =+IF(AF20<=0,10*365,AF20) -> 3650 | AH20: =+IF(Z20<=1,MIN(AG20,365),AG20) -> 365 | AI20: =+(1-(AG20+1)*(1-AE20)^AG20+AG20*(1-AE20)^(AG20+1))/((1-(1-AE20)^AG20)*AE20)-0.5 -> 1779.0468 | AJ20: =+IF(Z20<3,AD20,1) -> 0.015 | AK20: =IF(Z20<=3,Diccionario!$O$2,IF(Z20=4,Diccionario!$O$5,Diccionario!$O$6)) -> 0.66499986 | AL20: =+IF(Z20<=1,1,IF(Z20=2,2,3)) -> 1 | AM20: =+IF(AC20<0,-AC20,0) -> 10416 | AN20: =MIN(AJ20*AK20*AM20*(1+'[2]Pesos escenarios'!$F$8/2),AM20) -> 138.47951 | AO20: =IFERROR(VLOOKUP(A20,Diccionario!$C$2:$E$65,3,FALSE),"no") -> IVA Debito Fiscal no Cobrados
A21: 131715001 | B21: 80 | C21: 6206 | D21: 36882 | E21: 0 | F21: 46142 | G21: 46178 | H21: 45082 | I21: 1080 | J21: 2 | K21: 66 | L21: 1 | M21: 2 | N21: S | O21: Sit.Normal | P21: 466 | Q21: J | R21: 45082 | S21: 1250000 | T21: -147670.72 | U21: -106.92 | V21: -147670.72 | W21: -6675.53 | X21: 1543.46 | Y21: =TRIM(O21) -> Sit.Normal | Z21: =IF(Y21="Sit.Normal",1,IF(Y21="Riesgo potencia",2,IF(Y21="Con Problemas",3,IF(Y21="Alto Riesgo",4,IF(Y21="Irrecuperable",5,IF(Y21="Irrec Disp Tecn",6,IF(Y21="Sin identificación",0,""))))))) -> 1 | AB21: =VLOOKUP(A21,rubros_a_considerar!$A$2:$A$13,1,FALSE) -> 131715001 | AC21: =T21+W21 -> -154346.25 | AD21: =IF(Z21<=1,Diccionario!$M$2,Diccionario!$M$3) -> 0.015 | AE21: =1-(1-AD21)^(1/365) -> 4.140637e-05 | AF21: =+IFERROR(G21-$AR$1,0) -> 36 | AG21: =+IF(AF21<=0,10*365,AF21) -> 36 | AH21: =+IF(Z21<=1,MIN(AG21,365),AG21) -> 36 | AI21: =+(1-(AG21+1)*(1-AE21)^AG21+AG21*(1-AE21)^(AG21+1))/((1-(1-AE21)^AG21)*AE21)-0.5 -> 17.995532 | AJ21: =+IF(Z21<3,AD21,1) -> 0.015 | AK21: =IF(Z21<=3,Diccionario!$O$2,IF(Z21=4,Diccionario!$O$5,Diccionario!$O$6)) -> 0.66499986 | AL21: =+IF(Z21<=1,1,IF(Z21=2,2,3)) -> 1 | AM21: =+IF(AC21<0,-AC21,0) -> 154346.25 | AN21: =MIN(AJ21*AK21*AM21*(1+'[2]Pesos escenarios'!$F$8/2),AM21) -> 2052.0155 | AO21: =IFERROR(VLOOKUP(A21,Diccionario!$C$2:$E$65,3,FALSE),"no") -> Prestamos a Sola Firma
A22: 131715001 | B22: 80 | C22: 13957 | D22: 36870 | E22: 0 | F22: 46142 | G22: 46307 | H22: 44845 | I22: 1441 | J22: 2 | K22: 66 | L22: 1 | M22: 2 | N22: S | O22: Sit.Normal | P22: 202 | Q22: J | R22: 44845 | S22: 2000000 | T22: -592060.45 | U22: -428.69 | V22: -592060.45 | W22: -19270.35 | X22: 6113.31 | Y22: =TRIM(O22) -> Sit.Normal | Z22: =IF(Y22="Sit.Normal",1,IF(Y22="Riesgo potencia",2,IF(Y22="Con Problemas",3,IF(Y22="Alto Riesgo",4,IF(Y22="Irrecuperable",5,IF(Y22="Irrec Disp Tecn",6,IF(Y22="Sin identificación",0,""))))))) -> 1 | AB22: =VLOOKUP(A22,rubros_a_considerar!$A$2:$A$13,1,FALSE) -> 131715001 | AC22: =T22+W22 -> -611330.8 | AD22: =IF(Z22<=1,Diccionario!$M$2,Diccionario!$M$3) -> 0.015 | AE22: =1-(1-AD22)^(1/365) -> 4.140637e-05 | AF22: =+IFERROR(G22-$AR$1,0) -> 165 | AG22: =+IF(AF22<=0,10*365,AF22) -> 165 | AH22: =+IF(Z22<=1,MIN(AG22,365),AG22) -> 165 | AI22: =+(1-(AG22+1)*(1-AE22)^AG22+AG22*(1-AE22)^(AG22+1))/((1-(1-AE22)^AG22)*AE22)-0.5 -> 82.406061 | AJ22: =+IF(Z22<3,AD22,1) -> 0.015 | AK22: =IF(Z22<=3,Diccionario!$O$2,IF(Z22=4,Diccionario!$O$5,Diccionario!$O$6)) -> 0.66499986 | AL22: =+IF(Z22<=1,1,IF(Z22=2,2,3)) -> 1 | AM22: =+IF(AC22<0,-AC22,0) -> 611330.8 | AN22: =MIN(AJ22*AK22*AM22*(1+'[2]Pesos escenarios'!$F$8/2),AM22) -> 8127.572 | AO22: =IFERROR(VLOOKUP(A22,Diccionario!$C$2:$E$65,3,FALSE),"no") -> Prestamos a Sola Firma
A23: 131715001 | B23: 80 | C23: 13957 | D23: 36869 | E23: 0 | F23: 46142 | G23: 46279 | H23: 44818 | I23: 1440 | J23: 2 | K23: 66 | L23: 1 | M23: 2 | N23: S | O23: Sit.Normal | P23: 202 | Q23: J | R23: 44818 | S23: 3000000 | T23: -756500.84 | U23: -547.75 | V23: -756500.84 | W23: -23254.63 | X23: 7797.55 | Y23: =TRIM(O23) -> Sit.Normal | Z23: =IF(Y23="Sit.Normal",1,IF(Y23="Riesgo potencia",2,IF(Y23="Con Problemas",3,IF(Y23="Alto Riesgo",4,IF(Y23="Irrecuperable",5,IF(Y23="Irrec Disp Tecn",6,IF(Y23="Sin identificación",0,""))))))) -> 1 | AB23: =VLOOKUP(A23,rubros_a_considerar!$A$2:$A$13,1,FALSE) -> 131715001 | AC23: =T23+W23 -> -779755.47 | AD23: =IF(Z23<=1,Diccionario!$M$2,Diccionario!$M$3) -> 0.015 | AE23: =1-(1-AD23)^(1/365) -> 4.140637e-05 | AF23: =+IFERROR(G23-$AR$1,0) -> 137 | AG23: =+IF(AF23<=0,10*365,AF23) -> 137 | AH23: =+IF(Z23<=1,MIN(AG23,365),AG23) -> 137 | AI23: =+(1-(AG23+1)*(1-AE23)^AG23+AG23*(1-AE23)^(AG23+1))/((1-(1-AE23)^AG23)*AE23)-0.5 -> 68.435239 | AJ23: =+IF(Z23<3,AD23,1) -> 0.015 | AK23: =IF(Z23<=3,Diccionario!$O$2,IF(Z23=4,Diccionario!$O$5,Diccionario!$O$6)) -> 0.66499986 | AL23: =+IF(Z23<=1,1,IF(Z23=2,2,3)) -> 1 | AM23: =+IF(AC23<0,-AC23,0) -> 779755.47 | AN23: =MIN(AJ23*AK23*AM23*(1+'[2]Pesos escenarios'!$F$8/2),AM23) -> 10366.758 | AO23: =IFERROR(VLOOKUP(A23,Diccionario!$C$2:$E$65,3,FALSE),"no") -> Prestamos a Sola Firma
A24: 131731003 | B24: 80 | C24: 82510 | D24: 42796 | E24: 0 | F24: 46142 | G24: 46147 | H24: 45782 | I24: 360 | J24: 2 | K24: 52 | L24: 1 | M24: 2 | N24: S | O24: Sit.Normal | P24: 999 | Q24: F | R24: 45782 | S24: 200000 | T24: -20801.48 | U24: -15.06 | V24: -20801.48 | W24: -740.87 | X24: 215.42 | Y24: =TRIM(O24) -> Sit.Normal | Z24: =IF(Y24="Sit.Normal",1,IF(Y24="Riesgo potencia",2,IF(Y24="Con Problemas",3,IF(Y24="Alto Riesgo",4,IF(Y24="Irrecuperable",5,IF(Y24="Irrec Disp Tecn",6,IF(Y24="Sin identificación",0,""))))))) -> 1 | AB24: =VLOOKUP(A24,rubros_a_considerar!$A$2:$A$13,1,FALSE) -> 131731003 | AC24: =T24+W24 -> -21542.35 | AD24: =IF(Z24<=1,Diccionario!$M$2,Diccionario!$M$3) -> 0.015 | AE24: =1-(1-AD24)^(1/365) -> 4.140637e-05 | AF24: =+IFERROR(G24-$AR$1,0) -> 5 | AG24: =+IF(AF24<=0,10*365,AF24) -> 5 | AH24: =+IF(Z24<=1,MIN(AG24,365),AG24) -> 5 | AI24: =+(1-(AG24+1)*(1-AE24)^AG24+AG24*(1-AE24)^(AG24+1))/((1-(1-AE24)^AG24)*AE24)-0.5 -> 2.4999171 | AJ24: =+IF(Z24<3,AD24,1) -> 0.015 | AK24: =IF(Z24<=3,Diccionario!$O$2,IF(Z24=4,Diccionario!$O$5,Diccionario!$O$6)) -> 0.66499986 | AL24: =+IF(Z24<=1,1,IF(Z24=2,2,3)) -> 1 | AM24: =+IF(AC24<0,-AC24,0) -> 21542.35 | AN24: =MIN(AJ24*AK24*AM24*(1+'[2]Pesos escenarios'!$F$8/2),AM24) -> 286.40304 | AO24: =IFERROR(VLOOKUP(A24,Diccionario!$C$2:$E$65,3,FALSE),"no") -> Prestamos Personales
A25: 131731003 | B25: 80 | C25: 85822 | D25: 42797 | E25: 0 | F25: 46142 | G25: 46147 | H25: 45782 | I25: 360 | J25: 2 | K25: 52 | L25: 1 | M25: 2 | N25: S | O25: Alto Riesgo | P25: 999 | Q25: F | R25: 45782 | S25: 400000 | T25: -41602.93 | U25: -30.12 | V25: -41602.93 | W25: -1481.75 | X25: 21542.34 | Y25: =TRIM(O25) -> Alto Riesgo | Z25: =IF(Y25="Sit.Normal",1,IF(Y25="Riesgo potencia",2,IF(Y25="Con Problemas",3,IF(Y25="Alto Riesgo",4,IF(Y25="Irrecuperable",5,IF(Y25="Irrec Disp Tecn",6,IF(Y25="Sin identificación",0,""))))))) -> 4 | AB25: =VLOOKUP(A25,rubros_a_considerar!$A$2:$A$13,1,FALSE) -> 131731003 | AC25: =T25+W25 -> -43084.68 | AD25: =IF(Z25<=1,Diccionario!$M$2,Diccionario!$M$3) -> 0.041599564 | AE25: =1-(1-AD25)^(1/365) -> 0.00011640308 | AF25: =+IFERROR(G25-$AR$1,0) -> 5 | AG25: =+IF(AF25<=0,10*365,AF25) -> 5 | AH25: =+IF(Z25<=1,MIN(AG25,365),AG25) -> 5 | AI25: =+(1-(AG25+1)*(1-AE25)^AG25+AG25*(1-AE25)^(AG25+1))/((1-(1-AE25)^AG25)*AE25)-0.5 -> 2.4997672 | AJ25: =+IF(Z25<3,AD25,1) -> 1 | AK25: =IF(Z25<=3,Diccionario!$O$2,IF(Z25=4,Diccionario!$O$5,Diccionario!$O$6)) -> 0.92250106 | AL25: =+IF(Z25<=1,1,IF(Z25=2,2,3)) -> 3 | AM25: =+IF(AC25<0,-AC25,0) -> 43084.68 | AN25: =MIN(AJ25*AK25*AM25*(1+'[2]Pesos escenarios'!$F$8/2),AM25) -> 43084.68 | AO25: =IFERROR(VLOOKUP(A25,Diccionario!$C$2:$E$65,3,FALSE),"no") -> Prestamos Personales
A26: 131731003 | B26: 80 | C26: 86152 | D26: 42805 | E26: 0 | F26: 46142 | G26: 46171 | H26: 45806 | I26: 360 | J26: 2 | K26: 52 | L26: 1 | M26: 2 | N26: S | O26: Sit.Normal | P26: 999 | Q26: F | R26: 45806 | S26: 400000 | T26: -81524.11 | U26: -59.03 | V26: -81524.11 | W26: -3486.58 | X26: 850.11 | Y26: =TRIM(O26) -> Sit.Normal | Z26: =IF(Y26="Sit.Normal",1,IF(Y26="Riesgo potencia",2,IF(Y26="Con Problemas",3,IF(Y26="Alto Riesgo",4,IF(Y26="Irrecuperable",5,IF(Y26="Irrec Disp Tecn",6,IF(Y26="Sin identificación",0,""))))))) -> 1 | AB26: =VLOOKUP(A26,rubros_a_considerar!$A$2:$A$13,1,FALSE) -> 131731003 | AC26: =T26+W26 -> -85010.69 | AD26: =IF(Z26<=1,Diccionario!$M$2,Diccionario!$M$3) -> 0.015 | AE26: =1-(1-AD26)^(1/365) -> 4.140637e-05 | AF26: =+IFERROR(G26-$AR$1,0) -> 29 | AG26: =+IF(AF26<=0,10*365,AF26) -> 29 | AH26: =+IF(Z26<=1,MIN(AG26,365),AG26) -> 29 | AI26: =+(1-(AG26+1)*(1-AE26)^AG26+AG26*(1-AE26)^(AG26+1))/((1-(1-AE26)^AG26)*AE26)-0.5 -> 14.497101 | AJ26: =+IF(Z26<3,AD26,1) -> 0.015 | AK26: =IF(Z26<=3,Diccionario!$O$2,IF(Z26=4,Diccionario!$O$5,Diccionario!$O$6)) -> 0.66499986 | AL26: =+IF(Z26<=1,1,IF(Z26=2,2,3)) -> 1 | AM26: =+IF(AC26<0,-AC26,0) -> 85010.69 | AN26: =MIN(AJ26*AK26*AM26*(1+'[2]Pesos escenarios'!$F$8/2),AM26) -> 1130.2072 | AO26: =IFERROR(VLOOKUP(A26,Diccionario!$C$2:$E$65,3,FALSE),"no") -> Prestamos Personales
A27: 131731003 | B27: 80 | C27: 86563 | D27: 42806 | E27: 0 | F27: 46142 | G27: 46178 | H27: 45813 | I27: 360 | J27: 2 | K27: 52 | L27: 1 | M27: 2 | N27: S | O27: Sit.Normal | P27: 999 | Q27: F | R27: 45813 | S27: 400000 | T27: -119545.37 | U27: -86.56 | V27: -119545.37 | W27: -9537.43 | X27: 1290.83 | Y27: =TRIM(O27) -> Sit.Normal | Z27: =IF(Y27="Sit.Normal",1,IF(Y27="Riesgo potencia",2,IF(Y27="Con Problemas",3,IF(Y27="Alto Riesgo",4,IF(Y27="Irrecuperable",5,IF(Y27="Irrec Disp Tecn",6,IF(Y27="Sin identificación",0,""))))))) -> 1 | AB27: =VLOOKUP(A27,rubros_a_considerar!$A$2:$A$13,1,FALSE) -> 131731003 | AC27: =T27+W27 -> -129082.8 | AD27: =IF(Z27<=1,Diccionario!$M$2,Diccionario!$M$3) -> 0.015 | AE27: =1-(1-AD27)^(1/365) -> 4.140637e-05 | AF27: =+IFERROR(G27-$AR$1,0) -> 36 | AG27: =+IF(AF27<=0,10*365,AF27) -> 36 | AH27: =+IF(Z27<=1,MIN(AG27,365),AG27) -> 36 | AI27: =+(1-(AG27+1)*(1-AE27)^AG27+AG27*(1-AE27)^(AG27+1))/((1-(1-AE27)^AG27)*AE27)-0.5 -> 17.995532 | AJ27: =+IF(Z27<3,AD27,1) -> 0.015 | AK27: =IF(Z27<=3,Diccionario!$O$2,IF(Z27=4,Diccionario!$O$5,Diccionario!$O$6)) -> 0.66499986 | AL27: =+IF(Z27<=1,1,IF(Z27=2,2,3)) -> 1 | AM27: =+IF(AC27<0,-AC27,0) -> 129082.8 | AN27: =MIN(AJ27*AK27*AM27*(1+'[2]Pesos escenarios'!$F$8/2),AM27) -> 1716.1408 | AO27: =IFERROR(VLOOKUP(A27,Diccionario!$C$2:$E$65,3,FALSE),"no") -> Prestamos Personales
A28: 131731003 | B28: 80 | C28: 59343 | D28: 42886 | E28: 0 | F28: 46142 | G28: 46301 | H28: 45936 | I28: 360 | J28: 2 | K28: 73 | L28: 1 | M28: 2 | N28: S | O28: Sit.Normal | P28: 999 | Q28: F | R28: 45936 | S28: 275000 | T28: -161429.59 | U28: -116.89 | V28: -161429.59 | W28: -8071.48 | X28: 1695.01 | Y28: =TRIM(O28) -> Sit.Normal | Z28: =IF(Y28="Sit.Normal",1,IF(Y28="Riesgo potencia",2,IF(Y28="Con Problemas",3,IF(Y28="Alto Riesgo",4,IF(Y28="Irrecuperable",5,IF(Y28="Irrec Disp Tecn",6,IF(Y28="Sin identificación",0,""))))))) -> 1 | AB28: =VLOOKUP(A28,rubros_a_considerar!$A$2:$A$13,1,FALSE) -> 131731003 | AC28: =T28+W28 -> -169501.07 | AD28: =IF(Z28<=1,Diccionario!$M$2,Diccionario!$M$3) -> 0.015 | AE28: =1-(1-AD28)^(1/365) -> 4.140637e-05 | AF28: =+IFERROR(G28-$AR$1,0) -> 159 | AG28: =+IF(AF28<=0,10*365,AF28) -> 159 | AH28: =+IF(Z28<=1,MIN(AG28,365),AG28) -> 159 | AI28: =+(1-(AG28+1)*(1-AE28)^AG28+AG28*(1-AE28)^(AG28+1))/((1-(1-AE28)^AG28)*AE28)-0.5 -> 79.412769 | AJ28: =+IF(Z28<3,AD28,1) -> 0.015 | AK28: =IF(Z28<=3,Diccionario!$O$2,IF(Z28=4,Diccionario!$O$5,Diccionario!$O$6)) -> 0.66499986 | AL28: =+IF(Z28<=1,1,IF(Z28=2,2,3)) -> 1 | AM28: =+IF(AC28<0,-AC28,0) -> 169501.07 | AN28: =MIN(AJ28*AK28*AM28*(1+'[2]Pesos escenarios'!$F$8/2),AM28) -> 2253.497 | AO28: =IFERROR(VLOOKUP(A28,Diccionario!$C$2:$E$65,3,FALSE),"no") -> Prestamos Personales
A29: 131731003 | B29: 80 | C29: 56944 | D29: 42843 | E29: 0 | F29: 46142 | G29: 46211 | H29: 45846 | I29: 360 | J29: 2 | K29: 52 | L29: 1 | M29: 2 | N29: S | O29: Sit.Normal | P29: 999 | Q29: F | R29: 45846 | S29: 550000 | T29: -164466.57 | U29: -119.08 | V29: -164466.57 | W29: -5389.1 | X29: 1698.56 | Y29: =TRIM(O29) -> Sit.Normal | Z29: =IF(Y29="Sit.Normal",1,IF(Y29="Riesgo potencia",2,IF(Y29="Con Problemas",3,IF(Y29="Alto Riesgo",4,IF(Y29="Irrecuperable",5,IF(Y29="Irrec Disp Tecn",6,IF(Y29="Sin identificación",0,""))))))) -> 1 | AB29: =VLOOKUP(A29,rubros_a_considerar!$A$2:$A$13,1,FALSE) -> 131731003 | AC29: =T29+W29 -> -169855.67 | AD29: =IF(Z29<=1,Diccionario!$M$2,Diccionario!$M$3) -> 0.015 | AE29: =1-(1-AD29)^(1/365) -> 4.140637e-05 | AF29: =+IFERROR(G29-$AR$1,0) -> 69 | AG29: =+IF(AF29<=0,10*365,AF29) -> 69 | AH29: =+IF(Z29<=1,MIN(AG29,365),AG29) -> 69 | AI29: =+(1-(AG29+1)*(1-AE29)^AG29+AG29*(1-AE29)^(AG29+1))/((1-(1-AE29)^AG29)*AE29)-0.5 -> 34.483575 | AJ29: =+IF(Z29<3,AD29,1) -> 0.015 | AK29: =IF(Z29<=3,Diccionario!$O$2,IF(Z29=4,Diccionario!$O$5,Diccionario!$O$6)) -> 0.66499986 | AL29: =+IF(Z29<=1,1,IF(Z29=2,2,3)) -> 1 | AM29: =+IF(AC29<0,-AC29,0) -> 169855.67 | AN29: =MIN(AJ29*AK29*AM29*(1+'[2]Pesos escenarios'!$F$8/2),AM29) -> 2258.2114 | AO29: =IFERROR(VLOOKUP(A29,Diccionario!$C$2:$E$65,3,FALSE),"no") -> Prestamos Personales
A30: 131731003 | B30: 80 | C30: 86747 | D30: 42952 | E30: 0 | F30: 46142 | G30: 46440 | H30: 46073 | I30: 362 | J30: 2 | K30: 73 | L30: 1 | M30: 2 | N30: S | O30: Sit.Normal | P30: 999 | Q30: F | R30: 46073 | S30: 200000 | T30: -175536.41 | U30: -127.1 | V30: -175536.41 | W30: -3861.8 | X30: 1793.98 | Y30: =TRIM(O30) -> Sit.Normal | Z30: =IF(Y30="Sit.Normal",1,IF(Y30="Riesgo potencia",2,IF(Y30="Con Problemas",3,IF(Y30="Alto Riesgo",4,IF(Y30="Irrecuperable",5,IF(Y30="Irrec Disp Tecn",6,IF(Y30="Sin identificación",0,""))))))) -> 1 | AB30: =VLOOKUP(A30,rubros_a_considerar!$A$2:$A$13,1,FALSE) -> 131731003 | AC30: =T30+W30 -> -179398.21 | AD30: =IF(Z30<=1,Diccionario!$M$2,Diccionario!$M$3) -> 0.015 | AE30: =1-(1-AD30)^(1/365) -> 4.140637e-05 | AF30: =+IFERROR(G30-$AR$1,0) -> 298 | AG30: =+IF(AF30<=0,10*365,AF30) -> 298 | AH30: =+IF(Z30<=1,MIN(AG30,365),AG30) -> 298 | AI30: =+(1-(AG30+1)*(1-AE30)^AG30+AG30*(1-AE30)^(AG30+1))/((1-(1-AE30)^AG30)*AE30)-0.5 -> 148.69358 | AJ30: =+IF(Z30<3,AD30,1) -> 0.015 | AK30: =IF(Z30<=3,Diccionario!$O$2,IF(Z30=4,Diccionario!$O$5,Diccionario!$O$6)) -> 0.66499986 | AL30: =+IF(Z30<=1,1,IF(Z30=2,2,3)) -> 1 | AM30: =+IF(AC30<0,-AC30,0) -> 179398.21 | AN30: =MIN(AJ30*AK30*AM30*(1+'[2]Pesos escenarios'!$F$8/2),AM30) -> 2385.0784 | AO30: =IFERROR(VLOOKUP(A30,Diccionario!$C$2:$E$65,3,FALSE),"no") -> Prestamos Personales
A31: 131731003 | B31: 80 | C31: 87159 | D31: 42857 | E31: 0 | F31: 46142 | G31: 46246 | H31: 45881 | I31: 360 | J31: 2 | K31: 52 | L31: 1 | M31: 2 | N31: S | O31: Sit.Normal | P31: 999 | Q31: F | R31: 45881 | S31: 450000 | T31: -175930.38 | U31: -127.38 | V31: -175930.38 | W31: -4511.53 | X31: 1804.42 | Y31: =TRIM(O31) -> Sit.Normal | Z31: =IF(Y31="Sit.Normal",1,IF(Y31="Riesgo potencia",2,IF(Y31="Con Problemas",3,IF(Y31="Alto Riesgo",4,IF(Y31="Irrecuperable",5,IF(Y31="Irrec Disp Tecn",6,IF(Y31="Sin identificación",0,""))))))) -> 1 | AB31: =VLOOKUP(A31,rubros_a_considerar!$A$2:$A$13,1,FALSE) -> 131731003 | AC31: =T31+W31 -> -180441.91 | AD31: =IF(Z31<=1,Diccionario!$M$2,Diccionario!$M$3) -> 0.015 | AE31: =1-(1-AD31)^(1/365) -> 4.140637e-05 | AF31: =+IFERROR(G31-$AR$1,0) -> 104 | AG31: =+IF(AF31<=0,10*365,AF31) -> 104 | AH31: =+IF(Z31<=1,MIN(AG31,365),AG31) -> 104 | AI31: =+(1-(AG31+1)*(1-AE31)^AG31+AG31*(1-AE31)^(AG31+1))/((1-(1-AE31)^AG31)*AE31)-0.5 -> 51.962682 | AJ31: =+IF(Z31<3,AD31,1) -> 0.015 | AK31: =IF(Z31<=3,Diccionario!$O$2,IF(Z31=4,Diccionario!$O$5,Diccionario!$O$6)) -> 0.66499986 | AL31: =+IF(Z31<=1,1,IF(Z31=2,2,3)) -> 1 | AM31: =+IF(AC31<0,-AC31,0) -> 180441.91 | AN31: =MIN(AJ31*AK31*AM31*(1+'[2]Pesos escenarios'!$F$8/2),AM31) -> 2398.9542 | AO31: =IFERROR(VLOOKUP(A31,Diccionario!$C$2:$E$65,3,FALSE),"no") -> Prestamos Personales
A32: 131731003 | B32: 80 | C32: 82822 | D32: 42950 | E32: 0 | F32: 46142 | G32: 46436 | H32: 46071 | I32: 360 | J32: 2 | K32: 73 | L32: 1 | M32: 2 | N32: S | O32: Sit.Normal | P32: 999 | Q32: F | R32: 46071 | S32: 200000 | T32: -176288.27 | U32: -127.64 | V32: -176288.27 | W32: -3878.34 | X32: 1801.67 | Y32: =TRIM(O32) -> Sit.Normal | Z32: =IF(Y32="Sit.Normal",1,IF(Y32="Riesgo potencia",2,IF(Y32="Con Problemas",3,IF(Y32="Alto Riesgo",4,IF(Y32="Irrecuperable",5,IF(Y32="Irrec Disp Tecn",6,IF(Y32="Sin identificación",0,""))))))) -> 1 | AB32: =VLOOKUP(A32,rubros_a_considerar!$A$2:$A$13,1,FALSE) -> 131731003 | AC32: =T32+W32 -> -180166.61 | AD32: =IF(Z32<=1,Diccionario!$M$2,Diccionario!$M$3) -> 0.015 | AE32: =1-(1-AD32)^(1/365) -> 4.140637e-05 | AF32: =+IFERROR(G32-$AR$1,0) -> 294 | AG32: =+IF(AF32<=0,10*365,AF32) -> 294 | AH32: =+IF(Z32<=1,MIN(AG32,365),AG32) -> 294 | AI32: =+(1-(AG32+1)*(1-AE32)^AG32+AG32*(1-AE32)^(AG32+1))/((1-(1-AE32)^AG32)*AE32)-0.5 -> 146.70175 | AJ32: =+IF(Z32<3,AD32,1) -> 0.015 | AK32: =IF(Z32<=3,Diccionario!$O$2,IF(Z32=4,Diccionario!$O$5,Diccionario!$O$6)) -> 0.66499986 | AL32: =+IF(Z32<=1,1,IF(Z32=2,2,3)) -> 1 | AM32: =+IF(AC32<0,-AC32,0) -> 180166.61 | AN32: =MIN(AJ32*AK32*AM32*(1+'[2]Pesos escenarios'!$F$8/2),AM32) -> 2395.2941 | AO32: =IFERROR(VLOOKUP(A32,Diccionario!$C$2:$E$65,3,FALSE),"no") -> Prestamos Personales
... A175: 131742001 | B175: 80 | C175: 59750 | D175: 0 | E175: 0 | F175: 46142 | G175: 46142 | H175: 40045 | I175: 0 | J175: 0 | K175: 101.99 | L175: 0 | M175: 0 | N175: S | O175: Sit.Normal | P175: 103 | Q175: J | R175: 40045 | S175: 0 | T175: -6673323.3 | U175: -4831.91 | V175: -6673323.3 | W175: 0 | X175: 66733.23 | Y175: =TRIM(O175) -> Sit.Normal | Z175: =IF(Y175="Sit.Normal",1,IF(Y175="Riesgo potencia",2,IF(Y175="Con Problemas",3,IF(Y175="Alto Riesgo",4,IF(Y175="Irrecuperable",5,IF(Y175="Irrec Disp Tecn",6,IF(Y175="Sin identificación",0,""))))))) -> 1 | AB175: =VLOOKUP(A175,rubros_a_considerar!$A$2:$A$13,1,FALSE) -> 131742001 | AC175: =T175+W175 -> -6673323.3 | AD175: =IF(Z175<=1,Diccionario!$M$2,Diccionario!$M$3) -> 0.015 | AE175: =1-(1-AD175)^(1/365) -> 4.140637e-05 | AF175: =+IFERROR(G175-$AR$1,0) -> 0 | AG175: =+IF(AF175<=0,10*365,AF175) -> 3650 | AH175: =+IF(Z175<=1,MIN(AG175,365),AG175) -> 365 | AI175: =+(1-(AG175+1)*(1-AE175)^AG175+AG175*(1-AE175)^(AG175+1))/((1-(1-AE175)^AG175)*AE175)-0.5 -> 1779.0468 | AJ175: =+IF(Z175<3,AD175,1) -> 0.015 | AK175: =IF(Z175<=3,Diccionario!$O$2,IF(Z175=4,Diccionario!$O$5,Diccionario!$O$6)) -> 0.66499986 | AL175: =+IF(Z175<=1,1,IF(Z175=2,2,3)) -> 1 | AM175: =+IF(AC175<0,-AC175,0) -> 6673323.3 | AN175: =MIN(AJ175*AK175*AM175*(1+'[2]Pesos escenarios'!$F$8/2),AM175) -> 88721.057 | AO175: =IFERROR(VLOOKUP(A175,Diccionario!$C$2:$E$65,3,FALSE),"no") -> Tarjetas_de_Crédito

Sheet Cartera_Viva-Calls
A1: Cuenta | B1: Descripcion | E1: CALL
A2: 131442001 | B2: call otorgado | E2: Mayorista - Financiero
A3: 135442001 | B3: call otorgado
A4: 135442002 | B4: call otorgado
A6: BCRubr | B6: BCMda | C6: BCCta | D6: BCOper | E6: BCSbOp | F6: BCFech | G6: BCFVto | H6: BCFVal | I6: BCPlaz | J6: BCTTasa | K6: BCTasa | L6: BCTDia | M6: BCTAno | N6: BCResi | O6: BCCate | P6: BCActi | Q6: BCTiCu | R6: BCFAtr | S6: BCSdOr | T6: BCSdMN | U6: BCSdUS | V6: BCSdMO | W6: BCInt | X6: BCPrev | Y6: BCCate_sin_esp | Z6: Situacion | AA6: rubros_considerados | AB6: rubros_considerados_2 | AC6: EAD | AD6: PD | AE6: PD o 100% | AF6: Stage | AG6: PD Ajustada FL | AH6: PD Ajustada FL Diaria | AI6: LGD | AJ6: PE Calls
A7: 131442001 | B7: 80 | C7: 86970 | D7: 7790 | E7: 0 | F7: 46142 | G7: 46146 | H7: 46142 | I7: 4 | J7: 2 | K7: 18.5 | L7: 2 | M7: 0 | N7: S | P7: 641 | Q7: I | R7: 46142 | S7: 650000000 | T7: -650000000 | U7: -470640.91 | V7: -650000000 | W7: -329451.85 | X7: 0 | Y7: =TRIM(O7) | Z7: 1 | AA7: #N/A | AB7: #N/A | AC7: =-T7-W7 -> 6.5032945e+08 | AD7: =Diccionario!$M$2 -> 0.015 | AE7: =+IF(Z7<3,AD7,1) -> 0.015 | AF7: =+IF(Z7<=1,1,IF(Z7=2,2,3)) -> 1 | AG7: =+AD7*(1+'[2]Pesos escenarios'!$F$8/2) -> 0.019992311 | AH7: =1-(1-AG7)^(1/365) -> 5.5326856e-05 | AI7: =IF(Z7<=3,Diccionario!$O$2,IF(Z7=4,Diccionario!$O$5,Diccionario!$O$6)) -> 0.66499986 | AJ7: =+AC7*AH7*AI7 -> 23927.15
A8: 131442001 | B8: 80 | C8: 500285 | D8: 7789 | E8: 0 | F8: 46142 | G8: 46146 | H8: 46142 | I8: 4 | J8: 2 | K8: 14 | L8: 2 | M8: 0 | N8: S | P8: 641 | Q8: I | R8: 46142 | S8: 250000000 | T8: -250000000 | U8: -181015.74 | V8: -250000000 | W8: -95890.5 | X8: 0 | Y8: =TRIM(O8) | Z8: 1 | AA8: #N/A | AB8: #N/A | AC8: =-T8-W8 -> 2.5009589e+08 | AD8: =Diccionario!$M$2 -> 0.015 | AE8: =+IF(Z8<3,AD8,1) -> 0.015 | AF8: =+IF(Z8<=1,1,IF(Z8=2,2,3)) -> 1 | AG8: =+AD8*(1+'[2]Pesos escenarios'!$F$8/2) -> 0.019992311 | AH8: =1-(1-AG8)^(1/365) -> 5.5326856e-05 | AI8: =IF(Z8<=3,Diccionario!$O$2,IF(Z8=4,Diccionario!$O$5,Diccionario!$O$6)) -> 0.66499986 | AJ8: =+AC8*AH8*AI8 -> 9201.6159

Sheet Saldos_No_Util
A1: CUENTA | B1: CATEGORIA | C1: Limite | D1: Consumos $ | E1: Consumos U$S | F1: SALDO NO UTILIZADO BRUTO | G1: SALDO NO UTILIZADO FINAL | H1: Rubro | I1: Categoria | J1: sit | K1: Stage | L1: PD | M1: LGD | N1: CCF Basilea | O1: PE Saldo No Util | P1: BCTiCu | Q1: Producto | T1: Dólar Oficial Mayorista Cierre Mes | W1: 1382.7578
A2: 59257 | B2: Alto Riesgo | C2: =VLOOKUP($A2,[3]Hoja1!$C$5:$BZ$72,3,FALSE) -> 1400000 | D2: =VLOOKUP($A2,[3]Hoja1!$C$5:$BZ$72,50,FALSE) -> 688025.3 | E2: =VLOOKUP($A2,[3]Hoja1!$C$5:$BZ$72,51,FALSE)*$W$1 -> 0 | F2: =+C2-D2-E2 -> 711974.7 | G2: =IF(F2>C2,C2,IF(F2>0,F2,0)) -> 711974.7 | I2: Alto Riesgo | J2: =IF(I2="Sit.Normal","1",IF(I2="Riesgo Potencia","2",IF(I2="Con problemas","3",IF(I2="Alto Riesgo","4",IF(I2="Irrecuperable","5",IF(I2="Irrec Disp Tecn","6",0))))))*1 -> 4 | K2: =+IF(J2<=1,1,IF(J2=2,2,3)) -> 3 | L2: =+IF(J2=1,Diccionario!$M$2,IF(J2=2,Diccionario!$M$3,1)) -> 1 | M2: =IF(J2<=3,Diccionario!$O$2,IF(J2=4,Diccionario!$O$5,Diccionario!$O$6)) -> 0.92250106 | N2: 0.4 | O2: =+G2*L2*M2*N2*(1+'[2]Pesos escenarios'!$F$8/2) -> 350157.28 | P2: F | Q2: =+IF(ISBLANK(H2),"Saldo no utilizado TC","Saldo no utilizado ACC") -> Saldo no utilizado TC
A3: 83994 | B3: Sit.Normal | C3: =VLOOKUP($A3,[3]Hoja1!$C$5:$BZ$72,3,FALSE) -> 4000000 | D3: =VLOOKUP($A3,[3]Hoja1!$C$5:$BZ$72,50,FALSE) -> 1559959 | E3: =VLOOKUP($A3,[3]Hoja1!$C$5:$BZ$72,51,FALSE)*$W$1 -> 18376.851 | F3: =+C3-D3-E3 -> 2421664.2 | G3: =IF(F3>C3,C3,IF(F3>0,F3,0)) -> 2421664.2 | I3: =+TRIM(B3) -> Sit.Normal | J3: =IF(I3="Sit.Normal","1",IF(I3="Riesgo Potencia","2",IF(I3="Con problemas","3",IF(I3="Alto Riesgo","4",IF(I3="Irrecuperable","5",IF(I3="Irrec Disp Tecn","6",0))))))*1 -> 1 | K3: =+IF(J3<=1,1,IF(J3=2,2,3)) -> 1 | L3: =+IF(J3=1,Diccionario!$M$2,IF(J3=2,Diccionario!$M$3,1)) -> 0.015 | M3: =IF(J3<=3,Diccionario!$O$2,IF(J3=4,Diccionario!$O$5,Diccionario!$O$6)) -> 0.66499986 | N3: 0.4 | O3: =+G3*L3*M3*N3*(1+'[2]Pesos escenarios'!$F$8/2) -> 12878.297 | P3: F | Q3: =+IF(ISBLANK(H3),"Saldo no utilizado TC","Saldo no utilizado ACC") -> Saldo no utilizado TC
A4: 53465 | B4: Sit.Normal | C4: =VLOOKUP($A4,[3]Hoja1!$C$5:$BZ$72,3,FALSE) -> 180000 | D4: =VLOOKUP($A4,[3]Hoja1!$C$5:$BZ$72,50,FALSE) -> 134.31 | E4: =VLOOKUP($A4,[3]Hoja1!$C$5:$BZ$72,51,FALSE)*$W$1 -> 0 | F4: =+C4-D4-E4 -> 179865.69 | G4: =IF(F4>C4,C4,IF(F4>0,F4,0)) -> 179865.69 | I4: =+TRIM(B4) -> Sit.Normal | J4: =IF(I4="Sit.Normal","1",IF(I4="Riesgo Potencia","2",IF(I4="Con problemas","3",IF(I4="Alto Riesgo","4",IF(I4="Irrecuperable","5",IF(I4="Irrec Disp Tecn","6",0))))))*1 -> 1 | K4: =+IF(J4<=1,1,IF(J4=2,2,3)) -> 1 | L4: =+IF(J4=1,Diccionario!$M$2,IF(J4=2,Diccionario!$M$3,1)) -> 0.015 | M4: =IF(J4<=3,Diccionario!$O$2,IF(J4=4,Diccionario!$O$5,Diccionario!$O$6)) -> 0.66499986 | N4: 0.4 | O4: =+G4*L4*M4*N4*(1+'[2]Pesos escenarios'!$F$8/2) -> 956.51738 | P4: F | Q4: =+IF(ISBLANK(H4),"Saldo no utilizado TC","Saldo no utilizado ACC") -> Saldo no utilizado TC
A5: 58922 | B5: Sit.Normal | C5: =VLOOKUP($A5,[3]Hoja1!$C$5:$BZ$72,3,FALSE) -> 1600000 | D5: =VLOOKUP($A5,[3]Hoja1!$C$5:$BZ$72,50,FALSE) -> 842958.19 | E5: =VLOOKUP($A5,[3]Hoja1!$C$5:$BZ$72,51,FALSE)*$W$1 -> 0 | F5: =+C5-D5-E5 -> 757041.81 | G5: =IF(F5>C5,C5,IF(F5>0,F5,0)) -> 757041.81 | I5: =+TRIM(B5) -> Sit.Normal | J5: =IF(I5="Sit.Normal","1",IF(I5="Riesgo Potencia","2",IF(I5="Con problemas","3",IF(I5="Alto Riesgo","4",IF(I5="Irrecuperable","5",IF(I5="Irrec Disp Tecn","6",0))))))*1 -> 1 | K5: =+IF(J5<=1,1,IF(J5=2,2,3)) -> 1 | L5: =+IF(J5=1,Diccionario!$M$2,IF(J5=2,Diccionario!$M$3,1)) -> 0.015 | M5: =IF(J5<=3,Diccionario!$O$2,IF(J5=4,Diccionario!$O$5,Diccionario!$O$6)) -> 0.66499986 | N5: 0.4 | O5: =+G5*L5*M5*N5*(1+'[2]Pesos escenarios'!$F$8/2) -> 4025.9132 | P5: F | Q5: =+IF(ISBLANK(H5),"Saldo no utilizado TC","Saldo no utilizado ACC") -> Saldo no utilizado TC
A6: 83020 | B6: Sit.Normal | C6: =VLOOKUP($A6,[3]Hoja1!$C$5:$BZ$72,3,FALSE) -> 9000000 | D6: =VLOOKUP($A6,[3]Hoja1!$C$5:$BZ$72,50,FALSE) -> 1236232.4 | E6: =VLOOKUP($A6,[3]Hoja1!$C$5:$BZ$72,51,FALSE)*$W$1 -> 0 | F6: =+C6-D6-E6 -> 7763767.6 | G6: =IF(F6>C6,C6,IF(F6>0,F6,0)) -> 7763767.6 | I6: =+TRIM(B6) -> Sit.Normal | J6: =IF(I6="Sit.Normal","1",IF(I6="Riesgo Potencia","2",IF(I6="Con problemas","3",IF(I6="Alto Riesgo","4",IF(I6="Irrecuperable","5",IF(I6="Irrec Disp Tecn","6",0))))))*1 -> 1 | K6: =+IF(J6<=1,1,IF(J6=2,2,3)) -> 1 | L6: =+IF(J6=1,Diccionario!$M$2,IF(J6=2,Diccionario!$M$3,1)) -> 0.015 | M6: =IF(J6<=3,Diccionario!$O$2,IF(J6=4,Diccionario!$O$5,Diccionario!$O$6)) -> 0.66499986 | N6: 0.4 | O6: =+G6*L6*M6*N6*(1+'[2]Pesos escenarios'!$F$8/2) -> 41287.355 | P6: F | Q6: =+IF(ISBLANK(H6),"Saldo no utilizado TC","Saldo no utilizado ACC") -> Saldo no utilizado TC
A7: 84164 | B7: Sit.Normal | C7: =VLOOKUP($A7,[3]Hoja1!$C$5:$BZ$72,3,FALSE) -> 3000000 | D7: =VLOOKUP($A7,[3]Hoja1!$C$5:$BZ$72,50,FALSE) -> 85134.34 | E7: =VLOOKUP($A7,[3]Hoja1!$C$5:$BZ$72,51,FALSE)*$W$1 -> 0 | F7: =+C7-D7-E7 -> 2914865.7 | G7: =IF(F7>C7,C7,IF(F7>0,F7,0)) -> 2914865.7 | I7: =+TRIM(B7) -> Sit.Normal | J7: =IF(I7="Sit.Normal","1",IF(I7="Riesgo Potencia","2",IF(I7="Con problemas","3",IF(I7="Alto Riesgo","4",IF(I7="Irrecuperable","5",IF(I7="Irrec Disp Tecn","6",0))))))*1 -> 1 | K7: =+IF(J7<=1,1,IF(J7=2,2,3)) -> 1 | L7: =+IF(J7=1,Diccionario!$M$2,IF(J7=2,Diccionario!$M$3,1)) -> 0.015 | M7: =IF(J7<=3,Diccionario!$O$2,IF(J7=4,Diccionario!$O$5,Diccionario!$O$6)) -> 0.66499986 | N7: 0.4 | O7: =+G7*L7*M7*N7*(1+'[2]Pesos escenarios'!$F$8/2) -> 15501.12 | P7: F | Q7: =+IF(ISBLANK(H7),"Saldo no utilizado TC","Saldo no utilizado ACC") -> Saldo no utilizado TC
A8: 84446 | B8: Sit.Normal | C8: =VLOOKUP($A8,[3]Hoja1!$C$5:$BZ$72,3,FALSE) -> 5000000 | D8: =VLOOKUP($A8,[3]Hoja1!$C$5:$BZ$72,50,FALSE) -> 969929.48 | E8: =VLOOKUP($A8,[3]Hoja1!$C$5:$BZ$72,51,FALSE)*$W$1 -> 0 | F8: =+C8-D8-E8 -> 4030070.5 | G8: =IF(F8>C8,C8,IF(F8>0,F8,0)) -> 4030070.5 | I8: =+TRIM(B8) -> Sit.Normal | J8: =IF(I8="Sit.Normal","1",IF(I8="Riesgo Potencia","2",IF(I8="Con problemas","3",IF(I8="Alto Riesgo","4",IF(I8="Irrecuperable","5",IF(I8="Irrec Disp Tecn","6",0))))))*1 -> 1 | K8: =+IF(J8<=1,1,IF(J8=2,2,3)) -> 1 | L8: =+IF(J8=1,Diccionario!$M$2,IF(J8=2,Diccionario!$M$3,1)) -> 0.015 | M8: =IF(J8<=3,Diccionario!$O$2,IF(J8=4,Diccionario!$O$5,Diccionario!$O$6)) -> 0.66499986 | N8: 0.4 | O8: =+G8*L8*M8*N8*(1+'[2]Pesos escenarios'!$F$8/2) -> 21431.728 | P8: F | Q8: =+IF(ISBLANK(H8),"Saldo no utilizado TC","Saldo no utilizado ACC") -> Saldo no utilizado TC
A9: 85001 | B9: Sit.Normal | C9: =VLOOKUP($A9,[3]Hoja1!$C$5:$BZ$72,3,FALSE) -> 38000 | D9: =VLOOKUP($A9,[3]Hoja1!$C$5:$BZ$72,50,FALSE) -> 134.31 | E9: =VLOOKUP($A9,[3]Hoja1!$C$5:$BZ$72,51,FALSE)*$W$1 -> 0 | F9: =+C9-D9-E9 -> 37865.69 | G9: =IF(F9>C9,C9,IF(F9>0,F9,0)) -> 37865.69 | I9: =+TRIM(B9) -> Sit.Normal | J9: =IF(I9="Sit.Normal","1",IF(I9="Riesgo Potencia","2",IF(I9="Con problemas","3",IF(I9="Alto Riesgo","4",IF(I9="Irrecuperable","5",IF(I9="Irrec Disp Tecn","6",0))))))*1 -> 1 | K9: =+IF(J9<=1,1,IF(J9=2,2,3)) -> 1 | L9: =+IF(J9=1,Diccionario!$M$2,IF(J9=2,Diccionario!$M$3,1)) -> 0.015 | M9: =IF(J9<=3,Diccionario!$O$2,IF(J9=4,Diccionario!$O$5,Diccionario!$O$6)) -> 0.66499986 | N9: 0.4 | O9: =+G9*L9*M9*N9*(1+'[2]Pesos escenarios'!$F$8/2) -> 201.36798 | P9: F | Q9: =+IF(ISBLANK(H9),"Saldo no utilizado TC","Saldo no utilizado ACC") -> Saldo no utilizado TC
A10: 85391 | B10: Sit.Normal | C10: =VLOOKUP($A10,[3]Hoja1!$C$5:$BZ$72,3,FALSE) -> 2400000 | D10: =VLOOKUP($A10,[3]Hoja1!$C$5:$BZ$72,50,FALSE) -> 1277996.4 | E10: =VLOOKUP($A10,[3]Hoja1!$C$5:$BZ$72,51,FALSE)*$W$1 -> 0 | F10: =+C10-D10-E10 -> 1122003.6 | G10: =IF(F10>C10,C10,IF(F10>0,F10,0)) -> 1122003.6 | I10: =+TRIM(B10) -> Sit.Normal | J10: =IF(I10="Sit.Normal","1",IF(I10="Riesgo Potencia","2",IF(I10="Con problemas","3",IF(I10="Alto Riesgo","4",IF(I10="Irrecuperable","5",IF(I10="Irrec Disp Tecn","6",0))))))*1 -> 1 | K10: =+IF(J10<=1,1,IF(J10=2,2,3)) -> 1 | L10: =+IF(J10=1,Diccionario!$M$2,IF(J10=2,Diccionario!$M$3,1)) -> 0.015 | M10: =IF(J10<=3,Diccionario!$O$2,IF(J10=4,Diccionario!$O$5,Diccionario!$O$6)) -> 0.66499986 | N10: 0.4 | O10: =+G10*L10*M10*N10*(1+'[2]Pesos escenarios'!$F$8/2) -> 5966.7632 | P10: F | Q10: =+IF(ISBLANK(H10),"Saldo no utilizado TC","Saldo no utilizado ACC") -> Saldo no utilizado TC
A11: 53660 | B11: Sit.Normal | C11: =VLOOKUP($A11,[3]Hoja1!$C$5:$BZ$72,3,FALSE) -> 1200000 | D11: =VLOOKUP($A11,[3]Hoja1!$C$5:$BZ$72,50,FALSE) -> 912477.01 | E11: =VLOOKUP($A11,[3]Hoja1!$C$5:$BZ$72,51,FALSE)*$W$1 -> 0 | F11: =+C11-D11-E11 -> 287522.99 | G11: =IF(F11>C11,C11,IF(F11>0,F11,0)) -> 287522.99 | I11: =+TRIM(B11) -> Sit.Normal | J11: =IF(I11="Sit.Normal","1",IF(I11="Riesgo Potencia","2",IF(I11="Con problemas","3",IF(I11="Alto Riesgo","4",IF(I11="Irrecuperable","5",IF(I11="Irrec Disp Tecn","6",0))))))*1 -> 1 | K11: =+IF(J11<=1,1,IF(J11=2,2,3)) -> 1 | L11: =+IF(J11=1,Diccionario!$M$2,IF(J11=2,Diccionario!$M$3,1)) -> 0.015 | M11: =IF(J11<=3,Diccionario!$O$2,IF(J11=4,Diccionario!$O$5,Diccionario!$O$6)) -> 0.66499986 | N11: 0.4 | O11: =+G11*L11*M11*N11*(1+'[2]Pesos escenarios'!$F$8/2) -> 1529.0339 | P11: F | Q11: =+IF(ISBLANK(H11),"Saldo no utilizado TC","Saldo no utilizado ACC") -> Saldo no utilizado TC
A12: 54512 | B12: Sit.Normal | C12: =VLOOKUP($A12,[3]Hoja1!$C$5:$BZ$72,3,FALSE) -> 2000000 | D12: =VLOOKUP($A12,[3]Hoja1!$C$5:$BZ$72,50,FALSE) -> 134.31 | E12: =VLOOKUP($A12,[3]Hoja1!$C$5:$BZ$72,51,FALSE)*$W$1 -> 0 | F12: =+C12-D12-E12 -> 1999865.7 | G12: =IF(F12>C12,C12,IF(F12>0,F12,0)) -> 1999865.7 | I12: =+TRIM(B12) -> Sit.Normal | J12: =IF(I12="Sit.Normal","1",IF(I12="Riesgo Potencia","2",IF(I12="Con problemas","3",IF(I12="Alto Riesgo","4",IF(I12="Irrecuperable","5",IF(I12="Irrec Disp Tecn","6",0))))))*1 -> 1 | K12: =+IF(J12<=1,1,IF(J12=2,2,3)) -> 1 | L12: =+IF(J12=1,Diccionario!$M$2,IF(J12=2,Diccionario!$M$3,1)) -> 0.015 | M12: =IF(J12<=3,Diccionario!$O$2,IF(J12=4,Diccionario!$O$5,Diccionario!$O$6)) -> 0.66499986 | N12: 0.4 | O12: =+G12*L12*M12*N12*(1+'[2]Pesos escenarios'!$F$8/2) -> 10635.193 | P12: F | Q12: =+IF(ISBLANK(H12),"Saldo no utilizado TC","Saldo no utilizado ACC") -> Saldo no utilizado TC
A13: 85773 | B13: Sit.Normal | C13: =VLOOKUP($A13,[3]Hoja1!$C$5:$BZ$72,3,FALSE) -> 3000000 | D13: =VLOOKUP($A13,[3]Hoja1!$C$5:$BZ$72,50,FALSE) -> 268345.43 | E13: =VLOOKUP($A13,[3]Hoja1!$C$5:$BZ$72,51,FALSE)*$W$1 -> 0 | F13: =+C13-D13-E13 -> 2731654.6 | G13: =IF(F13>C13,C13,IF(F13>0,F13,0)) -> 2731654.6 | I13: =+TRIM(B13) -> Sit.Normal | J13: =IF(I13="Sit.Normal","1",IF(I13="Riesgo Potencia","2",IF(I13="Con problemas","3",IF(I13="Alto Riesgo","4",IF(I13="Irrecuperable","5",IF(I13="Irrec Disp Tecn","6",0))))))*1 -> 1 | K13: =+IF(J13<=1,1,IF(J13=2,2,3)) -> 1 | L13: =+IF(J13=1,Diccionario!$M$2,IF(J13=2,Diccionario!$M$3,1)) -> 0.015 | M13: =IF(J13<=3,Diccionario!$O$2,IF(J13=4,Diccionario!$O$5,Diccionario!$O$6)) -> 0.66499986 | N13: 0.4 | O13: =+G13*L13*M13*N13*(1+'[2]Pesos escenarios'!$F$8/2) -> 14526.812 | P13: F | Q13: =+IF(ISBLANK(H13),"Saldo no utilizado TC","Saldo no utilizado ACC") -> Saldo no utilizado TC
A14: 86330 | B14: Sit.Normal | C14: =VLOOKUP($A14,[3]Hoja1!$C$5:$BZ$72,3,FALSE) -> 7500000 | D14: =VLOOKUP($A14,[3]Hoja1!$C$5:$BZ$72,50,FALSE) -> 1239719.3 | E14: =VLOOKUP($A14,[3]Hoja1!$C$5:$BZ$72,51,FALSE)*$W$1 -> 8974.0981 | F14: =+C14-D14-E14 -> 6251306.6 | G14: =IF(F14>C14,C14,IF(F14>0,F14,0)) -> 6251306.6 | I14: =+TRIM(B14) -> Sit.Normal | J14: =IF(I14="Sit.Normal","1",IF(I14="Riesgo Potencia","2",IF(I14="Con problemas","3",IF(I14="Alto Riesgo","4",IF(I14="Irrecuperable","5",IF(I14="Irrec Disp Tecn","6",0))))))*1 -> 1 | K14: =+IF(J14<=1,1,IF(J14=2,2,3)) -> 1 | L14: =+IF(J14=1,Diccionario!$M$2,IF(J14=2,Diccionario!$M$3,1)) -> 0.015 | M14: =IF(J14<=3,Diccionario!$O$2,IF(J14=4,Diccionario!$O$5,Diccionario!$O$6)) -> 0.66499986 | N14: 0.4 | O14: =+G14*L14*M14*N14*(1+'[2]Pesos escenarios'!$F$8/2) -> 33244.158 | P14: F | Q14: =+IF(ISBLANK(H14),"Saldo no utilizado TC","Saldo no utilizado ACC") -> Saldo no utilizado TC
... A62: 58781 | B62: Sit.Normal | C62: =VLOOKUP($A62,[3]Hoja1!$C$5:$BZ$72,3,FALSE) -> 1500000 | D62: =VLOOKUP($A62,[3]Hoja1!$C$5:$BZ$72,50,FALSE) -> 206376.71 | E62: =VLOOKUP($A62,[3]Hoja1!$C$5:$BZ$72,51,FALSE)*$W$1 -> 234930.55 | F62: =+C62-D62-E62 -> 1058692.7 | G62: =IF(F62>C62,C62,IF(F62>0,F62,0)) -> 1058692.7 | I62: =+TRIM(B62) -> Sit.Normal | J62: =IF(I62="Sit.Normal","1",IF(I62="Riesgo Potencia","2",IF(I62="Con problemas","3",IF(I62="Alto Riesgo","4",IF(I62="Irrecuperable","5",IF(I62="Irrec Disp Tecn","6",0))))))*1 -> 1 | K62: =+IF(J62<=1,1,IF(J62=2,2,3)) -> 1 | L62: =+IF(J62=1,Diccionario!$M$2,IF(J62=2,Diccionario!$M$3,1)) -> 0.015 | M62: =IF(J62<=3,Diccionario!$O$2,IF(J62=4,Diccionario!$O$5,Diccionario!$O$6)) -> 0.66499986 | N62: 0.4 | O62: =+G62*L62*M62*N62*(1+'[2]Pesos escenarios'!$F$8/2) -> 5630.0788 | P62: J | Q62: =+IF(ISBLANK(H62),"Saldo no utilizado TC","Saldo no utilizado ACC") -> Saldo no utilizado TC
A63: 6206 | B63: Sit.Normal | G63: 2977517.2 | H63: 711084004 | I63: =+TRIM(B63) -> Sit.Normal | J63: =IF(I63="Sit.Normal","1",IF(I63="Riesgo Potencia","2",IF(I63="Con problemas","3",IF(I63="Alto Riesgo","4",IF(I63="Irrecuperable","5",IF(I63="Irrec Disp Tecn","6",0))))))*1 -> 1 | K63: =+IF(J63<=1,1,IF(J63=2,2,3)) -> 1 | L63: =+IF(J63=1,Diccionario!$M$2,IF(J63=2,Diccionario!$M$3,1)) -> 0.015 | M63: =IF(J63<=3,Diccionario!$O$2,IF(J63=4,Diccionario!$O$5,Diccionario!$O$6)) -> 0.66499986 | N63: 0.4 | O63: =+G63*L63*M63*N63*(1+'[2]Pesos escenarios'!$F$8/2) -> 15834.298 | P63: J | Q63: Saldo no utilizado ACC
A64: 85455 | B64: Sit.Normal | G64: 7896543.9 | H64: 711084004 | I64: =+TRIM(B64) -> Sit.Normal | J64: =IF(I64="Sit.Normal","1",IF(I64="Riesgo Potencia","2",IF(I64="Con problemas","3",IF(I64="Alto Riesgo","4",IF(I64="Irrecuperable","5",IF(I64="Irrec Disp Tecn","6",0))))))*1 -> 1 | K64: =+IF(J64<=1,1,IF(J64=2,2,3)) -> 1 | L64: =+IF(J64=1,Diccionario!$M$2,IF(J64=2,Diccionario!$M$3,1)) -> 0.015 | M64: =IF(J64<=3,Diccionario!$O$2,IF(J64=4,Diccionario!$O$5,Diccionario!$O$6)) -> 0.66499986 | N64: 0.4 | O64: =+G64*L64*M64*N64*(1+'[2]Pesos escenarios'!$F$8/2) -> 41993.453 | P64: J | Q64: Saldo no utilizado ACC
A65: 59750 | B65: Sit.Normal | G65: 652544.85 | H65: 711084004 | I65: =+TRIM(B65) -> Sit.Normal | J65: =IF(I65="Sit.Normal","1",IF(I65="Riesgo Potencia","2",IF(I65="Con problemas","3",IF(I65="Alto Riesgo","4",IF(I65="Irrecuperable","5",IF(I65="Irrec Disp Tecn","6",0))))))*1 -> 1 | K65: =+IF(J65<=1,1,IF(J65=2,2,3)) -> 1 | L65: =+IF(J65=1,Diccionario!$M$2,IF(J65=2,Diccionario!$M$3,1)) -> 0.015 | M65: =IF(J65<=3,Diccionario!$O$2,IF(J65=4,Diccionario!$O$5,Diccionario!$O$6)) -> 0.66499986 | N65: 1.4 | O65: =+G65*L65*M65*N65*(1+'[2]Pesos escenarios'!$F$8/2) -> 12145.711 | P65: J | Q65: Saldo no utilizado ACC

Sheet Diccionario
B1: Codigo | C1: Cuenta | E1: Descripcion | I1: Desc | J1: Sit BCRA | M1: PD | O1: LGD
B2: Total | C2: 131709001 | D2: 131709 | E2: ACC | I2: Sit.Normal | J2: 1 | L2: Sit.Normal | M2: =MAX([4]Resumen!$D$11,R2) -> 0.015 | O2: =[4]Resumen!$B$21 -> 0.66499986 | Q2: PD límite inferior | R2: 0.015
B3: Total | C3: 131709002 | D3: 131709 | E3: ACC | I3: Riesgo Potencia | J3: 2 | L3: Riesgo Potencia | M3: =[4]Resumen!$D$12 -> 0.041599564
B4: Total | C4: 131711001 | D4: 131711 | E4: Con otras garantias Hipotecarias | I4: Con Problemas | J4: 3 | L4: Con Problemas | M4: 1
B5: Total | C5: 131714001 | D5: 131714 | E5: Con otras garantias prendarias | I5: Alto Riesgo | J5: 4 | L5: Alto Riesgo | M5: 1 | O5: =[4]Resumen!$B$22 -> 0.92250106
B6: Total | C6: 131715001 | D6: 131715 | E6: Prestamos a Sola Firma | I6: Irrecuperable | J6: 5 | L6: Irrecuperable | M6: 1 | O6: =[4]Resumen!$B$23 -> 0.98633635
B7: Total | C7: 131718001 | D7: 131718 | E7: Documentos descontados | I7: Irrec Disp Tecn | J7: 6 | L7: Irrec Disp Tecn | M7: 1 | O7: 1
B8: Total | C8: 131731003 | D8: 131731 | E8: Prestamos Personales
B9: Total | C9: 131731051 | D9: 131731 | E9: Prestamos Personales
B10: Total | C10: 131742001 | D10: 131742 | E10: Tarjetas_de_Crédito | F10: Privado no fin capitales
B11: Total | C11: 131742008 | D11: 131742 | E11: Tarjetas_de_Crédito | F11: Privado no fin capitales | G11: INCLUIDO EN SALDOS NO UTILIZADOS | J11: Producto | K11: Tipo de producto | M11: BP BROKERS SA | O11: 0
B12: Total | C12: 131791002 | D12: 131791 | E12: Otros Intereses Documentados | J12: ACC | K12: Linea | M12: VIVALCE SOCIEDAD ANONIMA | O12: 0
B13: Total | C13: 135742001 | D13: 135742 | E13: Tarjetas_de_Crédito | J13: Con otras garantias Hipotecarias | K13: No Linea | M13: ENTRE RIOS CRUSHING S.A. | O13: 0
B14: Total | C14: 141154001 | D14: 141154 | E14: IVA Debito Fiscal no Cobrados | J14: Con otras garantias prendarias | K14: No Linea
B15: Total | C15: 711046005 | D15: 711046 | E15: Créditos clasificados irrecuperables | J15: Documentos(a descontar?) | K15: No Linea
B16: Total | C16: 711046008 | D16: 711046 | E16: Créditos clasificados irrecuperables | J16: Prestamos Personales | K16: No Linea
B17: Total | C17: 711046013 | D17: 711046 | E17: Créditos clasificados irrecuperables | J17: Tarjetas de Crédito | K17: Linea
B18: Total | C18: 711046023 | D18: 711046 | E18: Créditos clasificados irrecuperables | J18: Otros Intereses Documentados | K18: No Linea
B19: Total | C19: 711084003 | D19: 711084 | E19: Cuenta contingente deudora por el contrario | J19: Cobros no aplicados | K19: No Linea
B20: Total | C20: 711084004 | D20: 711084 | E20: Cuenta contingente deudora por el contrario | J20: Diversos | K20: No Linea
C21: 131140001 | D21: 131140 | E21: Préstamos Garantizados - Dto 1387/01 FRB | J21: Créditos clasificados irrecuperables | K21: No Linea
C22: 131194001 | D22: 131194 | E22: (REGULARIZADORA COM. "A" 3911) | J22: Cuenta contingente deudora por el contrario | K22: No Linea
C23: 131213001 | D23: 131213 | E23: Intereses Dev a Cobrar - Dto 1387/01
C24: 131263001 | D24: 131263 | E24: Ajuste Dev a Cob Ptmo Garantizado CER
C25: 131442001 | D25: 131442 | E25: call otorgado
C26: 131711050 | D26: 131711 | E26: Prestamo Hipotecario
C27: 131712001 | D27: 131712 | E27: ACC
C28: 131714050 | D28: 131714 | E28: Prendarios
C29: 131715050 | D29: 131715 | E29: Documentos(a descontar?)
C30: 131741001 | D30: 131741 | E30: Otros
C31: 131741003 | D31: 131741 | E31: Otros
C32: 131741006 | D32: 131741 | E32: Otros
C33: 131742007 | D33: 131742 | E33: Tarjetas_de_Crédito
C34: 131791001 | D34: 131791 | E34: Intereses Documentados
... C65: 171112001 | D65: 171112 | E65: Prestamos Personales
C72: 131715001 | D72: =VLOOKUP(C72,$C$2:$E$64,3,FALSE) -> Prestamos a Sola Firma
C73: 131718001 | D73: =VLOOKUP(C73,$C$2:$E$64,3,FALSE) -> Documentos descontados
C74: 131792001 | D74: =VLOOKUP(C74,$C$2:$E$64,3,FALSE) -> Cobros no aplicados
C75: 141154001 | D75: =VLOOKUP(C75,$C$2:$E$64,3,FALSE) -> IVA Debito Fiscal no Cobrados

Sheet rubros_a_considerar
A1: Rubros Considerados
A2: 131442001 | B2: 1 | C2: CALL
A3: 131709001 | B3: 1
A4: 131709002 | B4: 1
A5: 131715001 | B5: 1
A6: 131731003 | B6: 1
A7: 131731051 | B7: 1
A8: 131742001 | B8: 1
A9: 131742008 | B9: 1
A10: 135742001 | B10: 1
A11: 141154001 | B11: 1
A12: 171112001 | B12: 1 | C12: Prestamos Personales a empleados del banco
A13: 711084004 | B13: 1 | C13: Saldo No utilizado en Acc CC

Sheet Cartera Completa
A1: BCRubr | B1: BCMda | C1: BCCta | D1: BCOper | E1: BCSbOp | F1: BCFech | G1: BCFVto | H1: BCFVal | I1: BCPlaz | J1: BCTTasa | K1: BCTasa | L1: BCTDia | M1: BCTAno | N1: BCResi | O1: BCCate | P1: BCActi | Q1: BCTiCu | R1: BCFAtr | S1: BCSdOr | T1: BCSdMN | U1: BCSdUS | V1: BCSdMO | W1: BCInt | X1: BCPrev | Y1: BCCate sin esp | Z1: Situación BCRA | AA1: rubros_considerados | AB1: rubros_considerados_2 | AC1: Deuda+int | AD1: PD | AE1: PD_diaria | AF1: Plazo1 | AG1: Plazo2 | AH1: Min(Plazo;365) | AI1: Plazo Prom | AJ1: PD o 100% | AK1: LGD | AL1: Stage | AM1: EAD | AN1: PE | AO1: Producto
A2: 131709001 | B2: 80 | C2: 6206 | D2: 3563 | E2: 0 | F2: 46142 | G2: 46417 | H2: 46052 | I2: 365 | J2: 2 | K2: 73 | L2: 0 | M2: 0 | N2: S | O2: Sit.Normal | P2: 466 | Q2: J | R2: 46136 | S2: 0 | T2: -22482.8 | U2: -16.28 | V2: -22482.8 | W2: 0 | X2: 224.83 | Y2: =TRIM(O2) -> Sit.Normal | Z2: =IF(Y2="Sit.Normal",1,IF(Y2="Riesgo potencia",2,IF(Y2="Con Problemas",3,IF(Y2="Alto Riesgo",4,IF(Y2="Irrecuperable",5,IF(Y2="Irrec Disp Tecn",6,IF(Y2="Sin identificación",0,""))))))) -> 1 | AB2: =VLOOKUP(A2,rubros_a_considerar!$A$2:$A$13,1,FALSE) -> 131709001 | AO2: =IFERROR(VLOOKUP(A2,Diccionario!$C$2:$E$65,3,FALSE),"no") -> ACC | AQ2: CALLS OTORGADOS y Cuenta Contingente deudora por el contrario NO VAN "CARTERA OTROS"
A3: 131709001 | B3: 80 | C3: 59750 | D3: 3553 | E3: 0 | F3: 46142 | G3: 46235 | H3: 45870 | I3: 365 | J3: 2 | K3: 52 | L3: 0 | M3: 0 | N3: S | O3: Sit.Normal | P3: 103 | Q3: J | R3: 45797 | S3: 0 | T3: -7347455.2 | U3: -5320.02 | V3: -7347455.2 | W3: 0 | X3: 73474.55 | Y3: =TRIM(O3) -> Sit.Normal | Z3: =IF(Y3="Sit.Normal",1,IF(Y3="Riesgo potencia",2,IF(Y3="Con Problemas",3,IF(Y3="Alto Riesgo",4,IF(Y3="Irrecuperable",5,IF(Y3="Irrec Disp Tecn",6,IF(Y3="Sin identificación",0,""))))))) -> 1 | AB3: =VLOOKUP(A3,rubros_a_considerar!$A$2:$A$13,1,FALSE) -> 131709001 | AO3: =IFERROR(VLOOKUP(A3,Diccionario!$C$2:$E$65,3,FALSE),"no") -> ACC
A4: 131709001 | B4: 80 | C4: 85455 | D4: 3560 | E4: 0 | F4: 46142 | G4: 46302 | H4: 45937 | I4: 365 | J4: 2 | K4: 73 | L4: 0 | M4: 0 | N4: S | O4: Sit.Normal | P4: 620 | Q4: J | R4: 46142 | S4: 0 | T4: -103456.1 | U4: -74.91 | V4: -103456.1 | W4: 0 | X4: 1034.56 | Y4: =TRIM(O4) -> Sit.Normal | Z4: =IF(Y4="Sit.Normal",1,IF(Y4="Riesgo potencia",2,IF(Y4="Con Problemas",3,IF(Y4="Alto Riesgo",4,IF(Y4="Irrecuperable",5,IF(Y4="Irrec Disp Tecn",6,IF(Y4="Sin identificación",0,""))))))) -> 1 | AB4: =VLOOKUP(A4,rubros_a_considerar!$A$2:$A$13,1,FALSE) -> 131709001 | AO4: =IFERROR(VLOOKUP(A4,Diccionario!$C$2:$E$65,3,FALSE),"no") -> ACC
A5: 711046009 | B5: 80 | C5: 58096 | D5: 1 | E5: 0 | F5: 46142 | G5: 1753-01-01 | H5: 44712 | I5: 0 | J5: 0 | K5: 0 | L5: 0 | M5: 0 | N5: S | O5: Irrecuperable | P5: 466 | Q5: J | R5: 44712 | S5: 0 | T5: -7147.25 | U5: -5.18 | V5: -7147.25 | W5: 0 | X5: 0 | Y5: =TRIM(O5) -> Irrecuperable | Z5: =IF(Y5="Sit.Normal",1,IF(Y5="Riesgo potencia",2,IF(Y5="Con Problemas",3,IF(Y5="Alto Riesgo",4,IF(Y5="Irrecuperable",5,IF(Y5="Irrec Disp Tecn",6,IF(Y5="Sin identificación",0,""))))))) -> 5 | AB5: =VLOOKUP(A5,rubros_a_considerar!$A$2:$A$13,1,FALSE) -> #N/A | AO5: =IFERROR(VLOOKUP(A5,Diccionario!$C$2:$E$65,3,FALSE),"no") -> Creditos Clasificados Irrecuperables
A6: 711046009 | B6: 80 | C6: 82147 | D6: 1 | E6: 0 | F6: 46142 | G6: 1753-01-01 | H6: 43174 | I6: 0 | J6: 0 | K6: 0 | L6: 0 | M6: 0 | N6: S | O6: Irrecuperable | P6: 462 | Q6: J | R6: 43174 | S6: 0 | T6: -1305379.7 | U6: -945.18 | V6: -1305379.7 | W6: 0 | X6: 0 | Y6: =TRIM(O6) -> Irrecuperable | Z6: =IF(Y6="Sit.Normal",1,IF(Y6="Riesgo potencia",2,IF(Y6="Con Problemas",3,IF(Y6="Alto Riesgo",4,IF(Y6="Irrecuperable",5,IF(Y6="Irrec Disp Tecn",6,IF(Y6="Sin identificación",0,""))))))) -> 5 | AB6: =VLOOKUP(A6,rubros_a_considerar!$A$2:$A$13,1,FALSE) -> #N/A | AO6: =IFERROR(VLOOKUP(A6,Diccionario!$C$2:$E$65,3,FALSE),"no") -> Creditos Clasificados Irrecuperables
A7: 711046009 | B7: 80 | C7: 84568 | D7: 1 | E7: 0 | F7: 46142 | G7: 1753-01-01 | H7: 44769 | I7: 0 | J7: 0 | K7: 0 | L7: 0 | M7: 0 | N7: S | O7: Irrecuperable | P7: 662 | Q7: J | R7: 44769 | S7: 0 | T7: -1680.74 | U7: -1.22 | V7: -1680.74 | W7: 0 | X7: 0 | Y7: =TRIM(O7) -> Irrecuperable | Z7: =IF(Y7="Sit.Normal",1,IF(Y7="Riesgo potencia",2,IF(Y7="Con Problemas",3,IF(Y7="Alto Riesgo",4,IF(Y7="Irrecuperable",5,IF(Y7="Irrec Disp Tecn",6,IF(Y7="Sin identificación",0,""))))))) -> 5 | AB7: =VLOOKUP(A7,rubros_a_considerar!$A$2:$A$13,1,FALSE) -> #N/A | AO7: =IFERROR(VLOOKUP(A7,Diccionario!$C$2:$E$65,3,FALSE),"no") -> Creditos Clasificados Irrecuperables
A8: 711046009 | B8: 80 | C8: 85126 | D8: 1 | E8: 0 | F8: 46142 | G8: 1753-01-01 | H8: 44301 | I8: 0 | J8: 0 | K8: 0 | L8: 0 | M8: 0 | N8: S | O8: Irrecuperable | P8: 619 | Q8: J | R8: 44301 | S8: 0 | T8: -9055314.3 | U8: -6556.62 | V8: -9055314.3 | W8: 0 | X8: 0 | Y8: =TRIM(O8) -> Irrecuperable | Z8: =IF(Y8="Sit.Normal",1,IF(Y8="Riesgo potencia",2,IF(Y8="Con Problemas",3,IF(Y8="Alto Riesgo",4,IF(Y8="Irrecuperable",5,IF(Y8="Irrec Disp Tecn",6,IF(Y8="Sin identificación",0,""))))))) -> 5 | AB8: =VLOOKUP(A8,rubros_a_considerar!$A$2:$A$13,1,FALSE) -> #N/A | AO8: =IFERROR(VLOOKUP(A8,Diccionario!$C$2:$E$65,3,FALSE),"no") -> Creditos Clasificados Irrecuperables | AQ8: Creditos resaltados en celeste no se consideran porque se netean los saldos negativos y positivos
A9: 711046021 | B9: 80 | C9: 85995 | D9: 36463 | E9: 0 | F9: 46142 | G9: 1753-01-01 | H9: 43994 | I9: 0 | J9: 0 | K9: 0 | L9: 0 | M9: 0 | N9: S | O9: Irrecuperable | P9: 451 | Q9: J | R9: 43994 | S9: 0 | T9: -6422.26 | U9: -4.65 | V9: -6422.26 | W9: 0 | X9: 0 | Y9: =TRIM(O9) -> Irrecuperable | Z9: =IF(Y9="Sit.Normal",1,IF(Y9="Riesgo potencia",2,IF(Y9="Con Problemas",3,IF(Y9="Alto Riesgo",4,IF(Y9="Irrecuperable",5,IF(Y9="Irrec Disp Tecn",6,IF(Y9="Sin identificación",0,""))))))) -> 5 | AB9: =VLOOKUP(A9,rubros_a_considerar!$A$2:$A$13,1,FALSE) -> #N/A | AO9: =IFERROR(VLOOKUP(A9,Diccionario!$C$2:$E$65,3,FALSE),"no") -> Creditos Clasificados Irrecuperables
A10: 711046009 | B10: 80 | C10: 85995 | D10: 1 | E10: 0 | F10: 46142 | G10: 1753-01-01 | H10: 43994 | I10: 0 | J10: 0 | K10: 0 | L10: 0 | M10: 0 | N10: S | O10: Irrecuperable | P10: 451 | Q10: J | R10: 43994 | S10: 0 | T10: -3505334.4 | U10: -2538.08 | V10: -3505334.4 | W10: 0 | X10: 0 | Y10: =TRIM(O10) -> Irrecuperable | Z10: =IF(Y10="Sit.Normal",1,IF(Y10="Riesgo potencia",2,IF(Y10="Con Problemas",3,IF(Y10="Alto Riesgo",4,IF(Y10="Irrecuperable",5,IF(Y10="Irrec Disp Tecn",6,IF(Y10="Sin identificación",0,""))))))) -> 5 | AB10: =VLOOKUP(A10,rubros_a_considerar!$A$2:$A$13,1,FALSE) -> #N/A | AO10: =IFERROR(VLOOKUP(A10,Diccionario!$C$2:$E$65,3,FALSE),"no") -> Creditos Clasificados Irrecuperables
A11: 711046021 | B11: 80 | C11: 86002 | D11: 36469 | E11: 0 | F11: 46142 | G11: 1753-01-01 | H11: 43993 | I11: 0 | J11: 0 | K11: 0 | L11: 0 | M11: 0 | N11: S | O11: Irrecuperable | P11: 475 | Q11: J | R11: 43993 | S11: 0 | T11: -4228.77 | U11: -3.06 | V11: -4228.77 | W11: 0 | X11: 0 | Y11: =TRIM(O11) -> Irrecuperable | Z11: =IF(Y11="Sit.Normal",1,IF(Y11="Riesgo potencia",2,IF(Y11="Con Problemas",3,IF(Y11="Alto Riesgo",4,IF(Y11="Irrecuperable",5,IF(Y11="Irrec Disp Tecn",6,IF(Y11="Sin identificación",0,""))))))) -> 5 | AB11: =VLOOKUP(A11,rubros_a_considerar!$A$2:$A$13,1,FALSE) -> #N/A | AO11: =IFERROR(VLOOKUP(A11,Diccionario!$C$2:$E$65,3,FALSE),"no") -> Creditos Clasificados Irrecuperables
A12: 711046009 | B12: 80 | C12: 86002 | D12: 1 | E12: 0 | F12: 46142 | G12: 1753-01-01 | H12: 43993 | I12: 0 | J12: 0 | K12: 0 | L12: 0 | M12: 0 | N12: S | O12: Irrecuperable | P12: 475 | Q12: J | R12: 43993 | S12: 0 | T12: -1037626.7 | U12: -751.31 | V12: -1037626.7 | W12: 0 | X12: 0 | Y12: =TRIM(O12) -> Irrecuperable | Z12: =IF(Y12="Sit.Normal",1,IF(Y12="Riesgo potencia",2,IF(Y12="Con Problemas",3,IF(Y12="Alto Riesgo",4,IF(Y12="Irrecuperable",5,IF(Y12="Irrec Disp Tecn",6,IF(Y12="Sin identificación",0,""))))))) -> 5 | AB12: =VLOOKUP(A12,rubros_a_considerar!$A$2:$A$13,1,FALSE) -> #N/A | AO12: =IFERROR(VLOOKUP(A12,Diccionario!$C$2:$E$65,3,FALSE),"no") -> Creditos Clasificados Irrecuperables
A13: 711046008 | B13: 80 | C13: 14073 | D13: 39110 | E13: 0 | F13: 46142 | G13: 1753-01-01 | H13: 42944 | I13: 0 | J13: 0 | K13: 0 | L13: 0 | M13: 0 | N13: S | O13: Irrecuperable | P13: 999 | Q13: F | R13: 42944 | S13: 0 | T13: -8291.85 | U13: -6 | V13: -8291.85 | W13: 0 | X13: 0 | Y13: =TRIM(O13) -> Irrecuperable | Z13: =IF(Y13="Sit.Normal",1,IF(Y13="Riesgo potencia",2,IF(Y13="Con Problemas",3,IF(Y13="Alto Riesgo",4,IF(Y13="Irrecuperable",5,IF(Y13="Irrec Disp Tecn",6,IF(Y13="Sin identificación",0,""))))))) -> 5 | AB13: =VLOOKUP(A13,rubros_a_considerar!$A$2:$A$13,1,FALSE) -> #N/A | AO13: =IFERROR(VLOOKUP(A13,Diccionario!$C$2:$E$65,3,FALSE),"no") -> Créditos clasificados irrecuperables
A14: 711046013 | B14: 80 | C14: 23483 | D14: 23483 | E14: 0 | F14: 46142 | G14: 1753-01-01 | H14: 43724 | I14: 0 | J14: 0 | K14: 0 | L14: 0 | M14: 0 | N14: S | O14: Irrecuperable | P14: 999 | Q14: F | R14: 43724 | S14: 0 | T14: -16261.71 | U14: -11.77 | V14: -16261.71 | W14: 0 | X14: 0 | Y14: =TRIM(O14) -> Irrecuperable | Z14: =IF(Y14="Sit.Normal",1,IF(Y14="Riesgo potencia",2,IF(Y14="Con Problemas",3,IF(Y14="Alto Riesgo",4,IF(Y14="Irrecuperable",5,IF(Y14="Irrec Disp Tecn",6,IF(Y14="Sin identificación",0,""))))))) -> 5 | AB14: =VLOOKUP(A14,rubros_a_considerar!$A$2:$A$13,1,FALSE) -> #N/A | AO14: =IFERROR(VLOOKUP(A14,Diccionario!$C$2:$E$65,3,FALSE),"no") -> Créditos clasificados irrecuperables
A15: 711046013 | B15: 80 | C15: 54076 | D15: 54076 | E15: 0 | F15: 46142 | G15: 1753-01-01 | H15: 45288 | I15: 0 | J15: 0 | K15: 0 | L15: 0 | M15: 0 | N15: S | O15: Irrecuperable | P15: 999 | Q15: F | R15: 45288 | S15: 0 | T15: -2147.09 | U15: -1.55 | V15: -2147.09 | W15: 0 | X15: 0 | Y15: =TRIM(O15) -> Irrecuperable | Z15: =IF(Y15="Sit.Normal",1,IF(Y15="Riesgo potencia",2,IF(Y15="Con Problemas",3,IF(Y15="Alto Riesgo",4,IF(Y15="Irrecuperable",5,IF(Y15="Irrec Disp Tecn",6,IF(Y15="Sin identificación",0,""))))))) -> 5 | AB15: =VLOOKUP(A15,rubros_a_considerar!$A$2:$A$13,1,FALSE) -> #N/A | AO15: =IFERROR(VLOOKUP(A15,Diccionario!$C$2:$E$65,3,FALSE),"no") -> Créditos clasificados irrecuperables
A16: 711046013 | B16: 80 | C16: 54113 | D16: 54113 | E16: 0 | F16: 46142 | G16: 1753-01-01 | H16: 45099 | I16: 0 | J16: 0 | K16: 0 | L16: 0 | M16: 0 | N16: S | O16: Irrecuperable | P16: 999 | Q16: F | R16: 45099 | S16: 0 | T16: -1959.28 | U16: -1.42 | V16: -1959.28 | W16: 0 | X16: 0 | Y16: =TRIM(O16) -> Irrecuperable | Z16: =IF(Y16="Sit.Normal",1,IF(Y16="Riesgo potencia",2,IF(Y16="Con Problemas",3,IF(Y16="Alto Riesgo",4,IF(Y16="Irrecuperable",5,IF(Y16="Irrec Disp Tecn",6,IF(Y16="Sin identificación",0,""))))))) -> 5 | AB16: =VLOOKUP(A16,rubros_a_considerar!$A$2:$A$13,1,FALSE) -> #N/A | AO16: =IFERROR(VLOOKUP(A16,Diccionario!$C$2:$E$65,3,FALSE),"no") -> Créditos clasificados irrecuperables
A17: 711046008 | B17: 80 | C17: 54595 | D17: 37939 | E17: 0 | F17: 46142 | G17: 1753-01-01 | H17: 42082 | I17: 0 | J17: 0 | K17: 0 | L17: 0 | M17: 0 | N17: S | O17: Irrecuperable | P17: 999 | Q17: F | R17: 42082 | S17: 0 | T17: -349.69 | U17: -0.25 | V17: -349.69 | W17: 0 | X17: 0 | Y17: =TRIM(O17) -> Irrecuperable | Z17: =IF(Y17="Sit.Normal",1,IF(Y17="Riesgo potencia",2,IF(Y17="Con Problemas",3,IF(Y17="Alto Riesgo",4,IF(Y17="Irrecuperable",5,IF(Y17="Irrec Disp Tecn",6,IF(Y17="Sin identificación",0,""))))))) -> 5 | AB17: =VLOOKUP(A17,rubros_a_considerar!$A$2:$A$13,1,FALSE) -> #N/A | AO17: =IFERROR(VLOOKUP(A17,Diccionario!$C$2:$E$65,3,FALSE),"no") -> Créditos clasificados irrecuperables
A18: 711046008 | B18: 80 | C18: 55325 | D18: 37969 | E18: 0 | F18: 46142 | G18: 1753-01-01 | H18: 41988 | I18: 0 | J18: 0 | K18: 0 | L18: 0 | M18: 0 | N18: S | O18: Irrecuperable | P18: 999 | Q18: F | R18: 41988 | S18: 0 | T18: -4467.72 | U18: -3.23 | V18: -4467.72 | W18: 0 | X18: 0 | Y18: =TRIM(O18) -> Irrecuperable | Z18: =IF(Y18="Sit.Normal",1,IF(Y18="Riesgo potencia",2,IF(Y18="Con Problemas",3,IF(Y18="Alto Riesgo",4,IF(Y18="Irrecuperable",5,IF(Y18="Irrec Disp Tecn",6,IF(Y18="Sin identificación",0,""))))))) -> 5 | AB18: =VLOOKUP(A18,rubros_a_considerar!$A$2:$A$13,1,FALSE) -> #N/A | AO18: =IFERROR(VLOOKUP(A18,Diccionario!$C$2:$E$65,3,FALSE),"no") -> Créditos clasificados irrecuperables
A19: 711046008 | B19: 80 | C19: 56390 | D19: 35830 | E19: 0 | F19: 46142 | G19: 1753-01-01 | H19: 40175 | I19: 0 | J19: 0 | K19: 0 | L19: 0 | M19: 0 | N19: S | O19: Irrecuperable | P19: 999 | Q19: F | R19: 40175 | S19: 0 | T19: -404.87 | U19: -0.29 | V19: -404.87 | W19: 0 | X19: 0 | Y19: =TRIM(O19) -> Irrecuperable | Z19: =IF(Y19="Sit.Normal",1,IF(Y19="Riesgo potencia",2,IF(Y19="Con Problemas",3,IF(Y19="Alto Riesgo",4,IF(Y19="Irrecuperable",5,IF(Y19="Irrec Disp Tecn",6,IF(Y19="Sin identificación",0,""))))))) -> 5 | AB19: =VLOOKUP(A19,rubros_a_considerar!$A$2:$A$13,1,FALSE) -> #N/A | AO19: =IFERROR(VLOOKUP(A19,Diccionario!$C$2:$E$65,3,FALSE),"no") -> Créditos clasificados irrecuperables
A20: 711046008 | B20: 80 | C20: 56784 | D20: 38644 | E20: 0 | F20: 46142 | G20: 1753-01-01 | H20: 42695 | I20: 0 | J20: 0 | K20: 0 | L20: 0 | M20: 0 | N20: S | O20: Irrecuperable | P20: 999 | Q20: F | R20: 42695 | S20: 0 | T20: -765.25 | U20: -0.55 | V20: -765.25 | W20: 0 | X20: 0 | Y20: =TRIM(O20) -> Irrecuperable | Z20: =IF(Y20="Sit.Normal",1,IF(Y20="Riesgo potencia",2,IF(Y20="Con Problemas",3,IF(Y20="Alto Riesgo",4,IF(Y20="Irrecuperable",5,IF(Y20="Irrec Disp Tecn",6,IF(Y20="Sin identificación",0,""))))))) -> 5 | AB20: =VLOOKUP(A20,rubros_a_considerar!$A$2:$A$13,1,FALSE) -> #N/A | AO20: =IFERROR(VLOOKUP(A20,Diccionario!$C$2:$E$65,3,FALSE),"no") -> Créditos clasificados irrecuperables
... A75: 711046008 | B75: 80 | C75: 86708 | D75: 42098 | E75: 0 | F75: 46142 | G75: 1753-01-01 | H75: 45504 | I75: 0 | J75: 0 | K75: 0 | L75: 0 | M75: 0 | N75: S | O75: Irrecuperable | P75: 999 | Q75: F | R75: 45504 | S75: 0 | T75: -7821.17 | U75: -5.66 | V75: -7821.17 | W75: 0 | X75: 0 | Y75: =TRIM(O75) -> Irrecuperable | Z75: =IF(Y75="Sit.Normal",1,IF(Y75="Riesgo potencia",2,IF(Y75="Con Problemas",3,IF(Y75="Alto Riesgo",4,IF(Y75="Irrecuperable",5,IF(Y75="Irrec Disp Tecn",6,IF(Y75="Sin identificación",0,""))))))) -> 5 | AB75: =VLOOKUP(A75,rubros_a_considerar!$A$2:$A$13,1,FALSE) -> #N/A | AO75: =IFERROR(VLOOKUP(A75,Diccionario!$C$2:$E$65,3,FALSE),"no") -> Créditos clasificados irrecuperables
A76: 711084004 | B76: 80 | C76: 6206 | D76: 3563 | E76: 0 | F76: 46142 | G76: 46417 | H76: 46052 | I76: 365 | J76: 2 | K76: 73 | L76: 0 | M76: 0 | N76: S | O76: Sit.Normal | P76: 466 | Q76: J | R76: 46052 | S76: 3000000 | T76: -2977517.2 | U76: -2155.91 | V76: -2977517.2 | W76: 0 | X76: 29775.17 | Y76: =TRIM(O76) -> Sit.Normal | Z76: =IF(Y76="Sit.Normal",1,IF(Y76="Riesgo potencia",2,IF(Y76="Con Problemas",3,IF(Y76="Alto Riesgo",4,IF(Y76="Irrecuperable",5,IF(Y76="Irrec Disp Tecn",6,IF(Y76="Sin identificación",0,""))))))) -> 1 | AB76: =VLOOKUP(A76,rubros_a_considerar!$A$2:$A$13,1,FALSE) -> 711084004 | AO76: =IFERROR(VLOOKUP(A76,Diccionario!$C$2:$E$65,3,FALSE),"no") -> Cuenta contingente deudora por el contrario
A77: 711084004 | B77: 80 | C77: 59750 | D77: 3553 | E77: 0 | F77: 46142 | G77: 46235 | H77: 45870 | I77: 365 | J77: 2 | K77: 52 | L77: 0 | M77: 0 | N77: S | O77: Sit.Normal | P77: 103 | Q77: J | R77: 46129 | S77: 8000000 | T77: -652544.85 | U77: -472.48 | V77: -652544.85 | W77: 0 | X77: 6525.45 | Y77: =TRIM(O77) -> Sit.Normal | Z77: =IF(Y77="Sit.Normal",1,IF(Y77="Riesgo potencia",2,IF(Y77="Con Problemas",3,IF(Y77="Alto Riesgo",4,IF(Y77="Irrecuperable",5,IF(Y77="Irrec Disp Tecn",6,IF(Y77="Sin identificación",0,""))))))) -> 1 | AB77: =VLOOKUP(A77,rubros_a_considerar!$A$2:$A$13,1,FALSE) -> 711084004 | AO77: =IFERROR(VLOOKUP(A77,Diccionario!$C$2:$E$65,3,FALSE),"no") -> Cuenta contingente deudora por el contrario
A78: 711084004 | B78: 80 | C78: 85455 | D78: 3560 | E78: 0 | F78: 46142 | G78: 46302 | H78: 45937 | I78: 365 | J78: 2 | K78: 73 | L78: 0 | M78: 0 | N78: S | O78: Sit.Normal | P78: 620 | Q78: J | R78: 45937 | S78: 8000000 | T78: -7896543.9 | U78: -5717.59 | V78: -7896543.9 | W78: 0 | X78: 78965.44 | Y78: =TRIM(O78) -> Sit.Normal | Z78: =IF(Y78="Sit.Normal",1,IF(Y78="Riesgo potencia",2,IF(Y78="Con Problemas",3,IF(Y78="Alto Riesgo",4,IF(Y78="Irrecuperable",5,IF(Y78="Irrec Disp Tecn",6,IF(Y78="Sin identificación",0,""))))))) -> 1 | AB78: =VLOOKUP(A78,rubros_a_considerar!$A$2:$A$13,1,FALSE) -> 711084004 | AO78: =IFERROR(VLOOKUP(A78,Diccionario!$C$2:$E$65,3,FALSE),"no") -> Cuenta contingente deudora por el contrario
A79: 141154001 | B79: 80 | C79: 55257 | D79: 42940 | E79: 0 | F79: 46142 | G79: 1753-01-01 | H79: 46142 | I79: 0 | J79: 0 | K79: 0 | L79: 0 | M79: 0 | N79: S | O79: Sit.Normal | P79: 999 | Q79: F | R79: 46142 | S79: 0 | T79: -9141.9 | U79: -6.62 | V79: -9141.9 | W79: 0 | X79: 91.42 | Y79: =TRIM(O79) -> Sit.Normal | Z79: =IF(Y79="Sit.Normal",1,IF(Y79="Riesgo potencia",2,IF(Y79="Con Problemas",3,IF(Y79="Alto Riesgo",4,IF(Y79="Irrecuperable",5,IF(Y79="Irrec Disp Tecn",6,IF(Y79="Sin identificación",0,""))))))) -> 1 | AB79: =VLOOKUP(A79,rubros_a_considerar!$A$2:$A$13,1,FALSE) -> 141154001 | AO79: =IFERROR(VLOOKUP(A79,Diccionario!$C$2:$E$65,3,FALSE),"no") -> IVA Debito Fiscal no Cobrados
A80: 141154001 | B80: 80 | C80: 55476 | D80: 42932 | E80: 0 | F80: 46142 | G80: 1753-01-01 | H80: 46142 | I80: 0 | J80: 0 | K80: 0 | L80: 0 | M80: 0 | N80: S | O80: Sit.Normal | P80: 999 | Q80: F | R80: 46142 | S80: 0 | T80: -3428.21 | U80: -2.48 | V80: -3428.21 | W80: 0 | X80: 34.28 | Y80: =TRIM(O80) -> Sit.Normal | Z80: =IF(Y80="Sit.Normal",1,IF(Y80="Riesgo potencia",2,IF(Y80="Con Problemas",3,IF(Y80="Alto Riesgo",4,IF(Y80="Irrecuperable",5,IF(Y80="Irrec Disp Tecn",6,IF(Y80="Sin identificación",0,""))))))) -> 1 | AB80: =VLOOKUP(A80,rubros_a_considerar!$A$2:$A$13,1,FALSE) -> 141154001 | AO80: =IFERROR(VLOOKUP(A80,Diccionario!$C$2:$E$65,3,FALSE),"no") -> IVA Debito Fiscal no Cobrados
A81: 141154001 | B81: 80 | C81: 56956 | D81: 42856 | E81: 0 | F81: 46142 | G81: 1753-01-01 | H81: 46142 | I81: 0 | J81: 0 | K81: 0 | L81: 0 | M81: 0 | N81: S | O81: Sit.Normal | P81: 999 | Q81: F | R81: 46142 | S81: 0 | T81: -2691.65 | U81: -1.95 | V81: -2691.65 | W81: 0 | X81: 26.92 | Y81: =TRIM(O81) -> Sit.Normal | Z81: =IF(Y81="Sit.Normal",1,IF(Y81="Riesgo potencia",2,IF(Y81="Con Problemas",3,IF(Y81="Alto Riesgo",4,IF(Y81="Irrecuperable",5,IF(Y81="Irrec Disp Tecn",6,IF(Y81="Sin identificación",0,""))))))) -> 1 | AB81: =VLOOKUP(A81,rubros_a_considerar!$A$2:$A$13,1,FALSE) -> 141154001 | AO81: =IFERROR(VLOOKUP(A81,Diccionario!$C$2:$E$65,3,FALSE),"no") -> IVA Debito Fiscal no Cobrados
A82: 141154001 | B82: 80 | C82: 57332 | D82: 42861 | E82: 0 | F82: 46142 | G82: 1753-01-01 | H82: 46142 | I82: 0 | J82: 0 | K82: 0 | L82: 0 | M82: 0 | N82: S | O82: Sit.Normal | P82: 999 | Q82: F | R82: 46142 | S82: 0 | T82: -3217.07 | U82: -2.33 | V82: -3217.07 | W82: 0 | X82: 32.17 | Y82: =TRIM(O82) -> Sit.Normal | Z82: =IF(Y82="Sit.Normal",1,IF(Y82="Riesgo potencia",2,IF(Y82="Con Problemas",3,IF(Y82="Alto Riesgo",4,IF(Y82="Irrecuperable",5,IF(Y82="Irrec Disp Tecn",6,IF(Y82="Sin identificación",0,""))))))) -> 1 | AB82: =VLOOKUP(A82,rubros_a_considerar!$A$2:$A$13,1,FALSE) -> 141154001 | AO82: =IFERROR(VLOOKUP(A82,Diccionario!$C$2:$E$65,3,FALSE),"no") -> IVA Debito Fiscal no Cobrados
A83: 141154001 | B83: 80 | C83: 57497 | D83: 42937 | E83: 0 | F83: 46142 | G83: 1753-01-01 | H83: 46142 | I83: 0 | J83: 0 | K83: 0 | L83: 0 | M83: 0 | N83: S | O83: Sit.Normal | P83: 999 | Q83: F | R83: 46142 | S83: 0 | T83: -9314.39 | U83: -6.74 | V83: -9314.39 | W83: 0 | X83: 93.14 | Y83: =TRIM(O83) -> Sit.Normal | Z83: =IF(Y83="Sit.Normal",1,IF(Y83="Riesgo potencia",2,IF(Y83="Con Problemas",3,IF(Y83="Alto Riesgo",4,IF(Y83="Irrecuperable",5,IF(Y83="Irrec Disp Tecn",6,IF(Y83="Sin identificación",0,""))))))) -> 1 | AB83: =VLOOKUP(A83,rubros_a_considerar!$A$2:$A$13,1,FALSE) -> 141154001 | AO83: =IFERROR(VLOOKUP(A83,Diccionario!$C$2:$E$65,3,FALSE),"no") -> IVA Debito Fiscal no Cobrados
A84: 141154001 | B84: 80 | C84: 57649 | D84: 42906 | E84: 0 | F84: 46142 | G84: 1753-01-01 | H84: 46142 | I84: 0 | J84: 0 | K84: 0 | L84: 0 | M84: 0 | N84: S | O84: Sit.Normal | P84: 999 | Q84: F | R84: 46142 | S84: 0 | T84: -2625.33 | U84: -1.9 | V84: -2625.33 | W84: 0 | X84: 26.25 | Y84: =TRIM(O84) -> Sit.Normal | Z84: =IF(Y84="Sit.Normal",1,IF(Y84="Riesgo potencia",2,IF(Y84="Con Problemas",3,IF(Y84="Alto Riesgo",4,IF(Y84="Irrecuperable",5,IF(Y84="Irrec Disp Tecn",6,IF(Y84="Sin identificación",0,""))))))) -> 1 | AB84: =VLOOKUP(A84,rubros_a_considerar!$A$2:$A$13,1,FALSE) -> 141154001 | AO84: =IFERROR(VLOOKUP(A84,Diccionario!$C$2:$E$65,3,FALSE),"no") -> IVA Debito Fiscal no Cobrados
A85: 141154001 | B85: 80 | C85: 83381 | D85: 42930 | E85: 0 | F85: 46142 | G85: 1753-01-01 | H85: 46142 | I85: 0 | J85: 0 | K85: 0 | L85: 0 | M85: 0 | N85: S | O85: Sit.Normal | P85: 999 | Q85: F | R85: 46142 | S85: 0 | T85: -3656.76 | U85: -2.65 | V85: -3656.76 | W85: 0 | X85: 36.57 | Y85: =TRIM(O85) -> Sit.Normal | Z85: =IF(Y85="Sit.Normal",1,IF(Y85="Riesgo potencia",2,IF(Y85="Con Problemas",3,IF(Y85="Alto Riesgo",4,IF(Y85="Irrecuperable",5,IF(Y85="Irrec Disp Tecn",6,IF(Y85="Sin identificación",0,""))))))) -> 1 | AB85: =VLOOKUP(A85,rubros_a_considerar!$A$2:$A$13,1,FALSE) -> 141154001 | AO85: =IFERROR(VLOOKUP(A85,Diccionario!$C$2:$E$65,3,FALSE),"no") -> IVA Debito Fiscal no Cobrados
A86: 141154001 | B86: 80 | C86: 84457 | D86: 42922 | E86: 0 | F86: 46142 | G86: 1753-01-01 | H86: 46142 | I86: 0 | J86: 0 | K86: 0 | L86: 0 | M86: 0 | N86: S | O86: Sit.Normal | P86: 999 | Q86: F | R86: 46142 | S86: 0 | T86: -8847.35 | U86: -6.41 | V86: -8847.35 | W86: 0 | X86: 88.47 | Y86: =TRIM(O86) -> Sit.Normal | Z86: =IF(Y86="Sit.Normal",1,IF(Y86="Riesgo potencia",2,IF(Y86="Con Problemas",3,IF(Y86="Alto Riesgo",4,IF(Y86="Irrecuperable",5,IF(Y86="Irrec Disp Tecn",6,IF(Y86="Sin identificación",0,""))))))) -> 1 | AB86: =VLOOKUP(A86,rubros_a_considerar!$A$2:$A$13,1,FALSE) -> 141154001 | AO86: =IFERROR(VLOOKUP(A86,Diccionario!$C$2:$E$65,3,FALSE),"no") -> IVA Debito Fiscal no Cobrados
A87: 141154001 | B87: 80 | C87: 84662 | D87: 42960 | E87: 0 | F87: 46142 | G87: 1753-01-01 | H87: 46142 | I87: 0 | J87: 0 | K87: 0 | L87: 0 | M87: 0 | N87: S | O87: Sit.Normal | P87: 999 | Q87: F | R87: 46142 | S87: 0 | T87: -9450 | U87: -6.84 | V87: -9450 | W87: 0 | X87: 94.5 | Y87: =TRIM(O87) -> Sit.Normal | Z87: =IF(Y87="Sit.Normal",1,IF(Y87="Riesgo potencia",2,IF(Y87="Con Problemas",3,IF(Y87="Alto Riesgo",4,IF(Y87="Irrecuperable",5,IF(Y87="Irrec Disp Tecn",6,IF(Y87="Sin identificación",0,""))))))) -> 1 | AB87: =VLOOKUP(A87,rubros_a_considerar!$A$2:$A$13,1,FALSE) -> 141154001 | AO87: =IFERROR(VLOOKUP(A87,Diccionario!$C$2:$E$65,3,FALSE),"no") -> IVA Debito Fiscal no Cobrados
A88: 141154001 | B88: 80 | C88: 85825 | D88: 42947 | E88: 0 | F88: 46142 | G88: 1753-01-01 | H88: 46142 | I88: 0 | J88: 0 | K88: 0 | L88: 0 | M88: 0 | N88: S | O88: Sit.Normal | P88: 999 | Q88: F | R88: 46142 | S88: 0 | T88: -9481.27 | U88: -6.87 | V88: -9481.27 | W88: 0 | X88: 94.81 | Y88: =TRIM(O88) -> Sit.Normal | Z88: =IF(Y88="Sit.Normal",1,IF(Y88="Riesgo potencia",2,IF(Y88="Con Problemas",3,IF(Y88="Alto Riesgo",4,IF(Y88="Irrecuperable",5,IF(Y88="Irrec Disp Tecn",6,IF(Y88="Sin identificación",0,""))))))) -> 1 | AB88: =VLOOKUP(A88,rubros_a_considerar!$A$2:$A$13,1,FALSE) -> 141154001 | AO88: =IFERROR(VLOOKUP(A88,Diccionario!$C$2:$E$65,3,FALSE),"no") -> IVA Debito Fiscal no Cobrados
A89: 141154001 | B89: 80 | C89: 86152 | D89: 42805 | E89: 0 | F89: 46142 | G89: 1753-01-01 | H89: 46142 | I89: 0 | J89: 0 | K89: 0 | L89: 0 | M89: 0 | N89: S | O89: Sit.Normal | P89: 999 | Q89: F | R89: 46142 | S89: 0 | T89: -707.32 | U89: -0.51 | V89: -707.32 | W89: 0 | X89: 7.07 | Y89: =TRIM(O89) -> Sit.Normal | Z89: =IF(Y89="Sit.Normal",1,IF(Y89="Riesgo potencia",2,IF(Y89="Con Problemas",3,IF(Y89="Alto Riesgo",4,IF(Y89="Irrecuperable",5,IF(Y89="Irrec Disp Tecn",6,IF(Y89="Sin identificación",0,""))))))) -> 1 | AB89: =VLOOKUP(A89,rubros_a_considerar!$A$2:$A$13,1,FALSE) -> 141154001 | AO89: =IFERROR(VLOOKUP(A89,Diccionario!$C$2:$E$65,3,FALSE),"no") -> IVA Debito Fiscal no Cobrados
A90: 141154001 | B90: 80 | C90: 86245 | D90: 42921 | E90: 0 | F90: 46142 | G90: 1753-01-01 | H90: 46142 | I90: 0 | J90: 0 | K90: 0 | L90: 0 | M90: 0 | N90: S | O90: Sit.Normal | P90: 999 | Q90: F | R90: 46142 | S90: 0 | T90: -4976.63 | U90: -3.6 | V90: -4976.63 | W90: 0 | X90: 49.77 | Y90: =TRIM(O90) -> Sit.Normal | Z90: =IF(Y90="Sit.Normal",1,IF(Y90="Riesgo potencia",2,IF(Y90="Con Problemas",3,IF(Y90="Alto Riesgo",4,IF(Y90="Irrecuperable",5,IF(Y90="Irrec Disp Tecn",6,IF(Y90="Sin identificación",0,""))))))) -> 1 | AB90: =VLOOKUP(A90,rubros_a_considerar!$A$2:$A$13,1,FALSE) -> 141154001 | AO90: =IFERROR(VLOOKUP(A90,Diccionario!$C$2:$E$65,3,FALSE),"no") -> IVA Debito Fiscal no Cobrados
... A94: 141154001 | B94: 80 | C94: 86883 | D94: 42962 | E94: 0 | F94: 46142 | G94: 1753-01-01 | H94: 46142 | I94: 0 | J94: 0 | K94: 0 | L94: 0 | M94: 0 | N94: S | O94: Sit.Normal | P94: 999 | Q94: F | R94: 46142 | S94: 0 | T94: -10416 | U94: -7.54 | V94: -10416 | W94: 0 | X94: 104.16 | Y94: =TRIM(O94) -> Sit.Normal | Z94: =IF(Y94="Sit.Normal",1,IF(Y94="Riesgo potencia",2,IF(Y94="Con Problemas",3,IF(Y94="Alto Riesgo",4,IF(Y94="Irrecuperable",5,IF(Y94="Irrec Disp Tecn",6,IF(Y94="Sin identificación",0,""))))))) -> 1 | AB94: =VLOOKUP(A94,rubros_a_considerar!$A$2:$A$13,1,FALSE) -> 141154001 | AO94: =IFERROR(VLOOKUP(A94,Diccionario!$C$2:$E$65,3,FALSE),"no") -> IVA Debito Fiscal no Cobrados
A95: 131715001 | B95: 80 | C95: 6206 | D95: 36882 | E95: 0 | F95: 46142 | G95: 46178 | H95: 45082 | I95: 1080 | J95: 2 | K95: 66 | L95: 1 | M95: 2 | N95: S | O95: Sit.Normal | P95: 466 | Q95: J | R95: 45082 | S95: 1250000 | T95: -147670.72 | U95: -106.92 | V95: -147670.72 | W95: -6675.53 | X95: 1543.46 | Y95: =TRIM(O95) -> Sit.Normal | Z95: =IF(Y95="Sit.Normal",1,IF(Y95="Riesgo potencia",2,IF(Y95="Con Problemas",3,IF(Y95="Alto Riesgo",4,IF(Y95="Irrecuperable",5,IF(Y95="Irrec Disp Tecn",6,IF(Y95="Sin identificación",0,""))))))) -> 1 | AB95: =VLOOKUP(A95,rubros_a_considerar!$A$2:$A$13,1,FALSE) -> 131715001 | AO95: =IFERROR(VLOOKUP(A95,Diccionario!$C$2:$E$65,3,FALSE),"no") -> Prestamos a Sola Firma
A96: 131715001 | B96: 80 | C96: 13957 | D96: 36870 | E96: 0 | F96: 46142 | G96: 46307 | H96: 44845 | I96: 1441 | J96: 2 | K96: 66 | L96: 1 | M96: 2 | N96: S | O96: Sit.Normal | P96: 202 | Q96: J | R96: 44845 | S96: 2000000 | T96: -592060.45 | U96: -428.69 | V96: -592060.45 | W96: -19270.35 | X96: 6113.31 | Y96: =TRIM(O96) -> Sit.Normal | Z96: =IF(Y96="Sit.Normal",1,IF(Y96="Riesgo potencia",2,IF(Y96="Con Problemas",3,IF(Y96="Alto Riesgo",4,IF(Y96="Irrecuperable",5,IF(Y96="Irrec Disp Tecn",6,IF(Y96="Sin identificación",0,""))))))) -> 1 | AB96: =VLOOKUP(A96,rubros_a_considerar!$A$2:$A$13,1,FALSE) -> 131715001 | AO96: =IFERROR(VLOOKUP(A96,Diccionario!$C$2:$E$65,3,FALSE),"no") -> Prestamos a Sola Firma
A97: 131715001 | B97: 80 | C97: 13957 | D97: 36869 | E97: 0 | F97: 46142 | G97: 46279 | H97: 44818 | I97: 1440 | J97: 2 | K97: 66 | L97: 1 | M97: 2 | N97: S | O97: Sit.Normal | P97: 202 | Q97: J | R97: 44818 | S97: 3000000 | T97: -756500.84 | U97: -547.75 | V97: -756500.84 | W97: -23254.63 | X97: 7797.55 | Y97: =TRIM(O97) -> Sit.Normal | Z97: =IF(Y97="Sit.Normal",1,IF(Y97="Riesgo potencia",2,IF(Y97="Con Problemas",3,IF(Y97="Alto Riesgo",4,IF(Y97="Irrecuperable",5,IF(Y97="Irrec Disp Tecn",6,IF(Y97="Sin identificación",0,""))))))) -> 1 | AB97: =VLOOKUP(A97,rubros_a_considerar!$A$2:$A$13,1,FALSE) -> 131715001 | AO97: =IFERROR(VLOOKUP(A97,Diccionario!$C$2:$E$65,3,FALSE),"no") -> Prestamos a Sola Firma
A98: 171112001 | B98: 80 | C98: 2366 | D98: 42674 | E98: 0 | F98: 46142 | G98: 46605 | H98: 45510 | I98: 1095 | J98: 2 | K98: 46 | L98: 2 | M98: 2 | N98: S | O98: Sit.Normal | P98: 999 | Q98: F | R98: 45510 | S98: 2000000 | T98: -1136349.6 | U98: -822.79 | V98: -1136349.6 | W98: -26462.94 | X98: 11628.13 | Y98: =TRIM(O98) -> Sit.Normal | Z98: =IF(Y98="Sit.Normal",1,IF(Y98="Riesgo potencia",2,IF(Y98="Con Problemas",3,IF(Y98="Alto Riesgo",4,IF(Y98="Irrecuperable",5,IF(Y98="Irrec Disp Tecn",6,IF(Y98="Sin identificación",0,""))))))) -> 1 | AB98: =VLOOKUP(A98,rubros_a_considerar!$A$2:$A$13,1,FALSE) -> 171112001 | AO98: =IFERROR(VLOOKUP(A98,Diccionario!$C$2:$E$65,3,FALSE),"no") -> Prestamos Personales
A99: 171112001 | B99: 80 | C99: 3833 | D99: 42898 | E99: 0 | F99: 46142 | G99: 46321 | H99: 45954 | I99: 367 | J99: 2 | K99: 46 | L99: 2 | M99: 2 | N99: S | O99: Sit.Normal | P99: 999 | Q99: F | R99: 45954 | S99: 3500000 | T99: -1983381.9 | U99: -1436.09 | V99: -1983381.9 | W99: -20920.6 | X99: 20043.03 | Y99: =TRIM(O99) -> Sit.Normal | Z99: =IF(Y99="Sit.Normal",1,IF(Y99="Riesgo potencia",2,IF(Y99="Con Problemas",3,IF(Y99="Alto Riesgo",4,IF(Y99="Irrecuperable",5,IF(Y99="Irrec Disp Tecn",6,IF(Y99="Sin identificación",0,""))))))) -> 1 | AB99: =VLOOKUP(A99,rubros_a_considerar!$A$2:$A$13,1,FALSE) -> 171112001 | AO99: =IFERROR(VLOOKUP(A99,Diccionario!$C$2:$E$65,3,FALSE),"no") -> Prestamos Personales
A100: 171112001 | B100: 80 | C100: 13377 | D100: 42672 | E100: 0 | F100: 46142 | G100: 46591 | H100: 45496 | I100: 1095 | J100: 2 | K100: 46 | L100: 2 | M100: 2 | N100: S | O100: Sit.Normal | P100: 999 | Q100: F | R100: 45496 | S100: 10000000 | T100: -5399443.6 | U100: -3909.54 | V100: -5399443.6 | W100: -40236.95 | X100: 54396.81 | Y100: =TRIM(O100) -> Sit.Normal | Z100: =IF(Y100="Sit.Normal",1,IF(Y100="Riesgo potencia",2,IF(Y100="Con Problemas",3,IF(Y100="Alto Riesgo",4,IF(Y100="Irrecuperable",5,IF(Y100="Irrec Disp Tecn",6,IF(Y100="Sin identificación",0,""))))))) -> 1 | AB100: =VLOOKUP(A100,rubros_a_considerar!$A$2:$A$13,1,FALSE) -> 171112001 | AO100: =IFERROR(VLOOKUP(A100,Diccionario!$C$2:$E$65,3,FALSE),"no") -> Prestamos Personales
A101: 171112001 | B101: 80 | C101: 14998 | D101: 42985 | E101: 0 | F101: 46142 | G101: 47602 | H101: 46140 | I101: 1441 | J101: 2 | K101: 55 | L101: 1 | M101: 2 | N101: S | O101: Sit.Normal | P101: 999 | Q101: F | R101: 46140 | S101: 10000000 | T101: -10000000 | U101: -7240.63 | V101: -10000000 | W101: -45205.48 | X101: 100452.05 | Y101: =TRIM(O101) -> Sit.Normal | Z101: =IF(Y101="Sit.Normal",1,IF(Y101="Riesgo potencia",2,IF(Y101="Con Problemas",3,IF(Y101="Alto Riesgo",4,IF(Y101="Irrecuperable",5,IF(Y101="Irrec Disp Tecn",6,IF(Y101="Sin identificación",0,""))))))) -> 1 | AB101: =VLOOKUP(A101,rubros_a_considerar!$A$2:$A$13,1,FALSE) -> 171112001 | AO101: =IFERROR(VLOOKUP(A101,Diccionario!$C$2:$E$65,3,FALSE),"no") -> Prestamos Personales
A102: 171112001 | B102: 80 | C102: 19542 | D102: 42968 | E102: 0 | F102: 46142 | G102: 46842 | H102: 46101 | I102: 730 | J102: 2 | K102: 46 | L102: 1 | M102: 2 | N102: S | O102: Sit.Normal | P102: 999 | Q102: F | R102: 46101 | S102: 1500000 | T102: -1485192.6 | U102: -1075.37 | V102: -1485192.6 | W102: -2237.96 | X102: 14874.31 | Y102: =TRIM(O102) -> Sit.Normal | Z102: =IF(Y102="Sit.Normal",1,IF(Y102="Riesgo potencia",2,IF(Y102="Con Problemas",3,IF(Y102="Alto Riesgo",4,IF(Y102="Irrecuperable",5,IF(Y102="Irrec Disp Tecn",6,IF(Y102="Sin identificación",0,""))))))) -> 1 | AB102: =VLOOKUP(A102,rubros_a_considerar!$A$2:$A$13,1,FALSE) -> 171112001 | AO102: =IFERROR(VLOOKUP(A102,Diccionario!$C$2:$E$65,3,FALSE),"no") -> Prestamos Personales
A103: 171112001 | B103: 80 | C103: 19542 | D103: 42901 | E103: 0 | F103: 46142 | G103: 47053 | H103: 45957 | I103: 1096 | J103: 2 | K103: 46 | L103: 2 | M103: 2 | N103: S | O103: Sit.Normal | P103: 999 | Q103: F | R103: 45957 | S103: 2750000 | T103: -2537115.4 | U103: -1837.03 | V103: -2537115.4 | W103: -15292.2 | X103: 25524.08 | Y103: =TRIM(O103) -> Sit.Normal | Z103: =IF(Y103="Sit.Normal",1,IF(Y103="Riesgo potencia",2,IF(Y103="Con Problemas",3,IF(Y103="Alto Riesgo",4,IF(Y103="Irrecuperable",5,IF(Y103="Irrec Disp Tecn",6,IF(Y103="Sin identificación",0,""))))))) -> 1 | AB103: =VLOOKUP(A103,rubros_a_considerar!$A$2:$A$13,1,FALSE) -> 171112001 | AO103: =IFERROR(VLOOKUP(A103,Diccionario!$C$2:$E$65,3,FALSE),"no") -> Prestamos Personales
A104: 171112001 | B104: 80 | C104: 19542 | D104: 42680 | E104: 0 | F104: 46142 | G104: 46611 | H104: 45516 | I104: 1095 | J104: 2 | K104: 46 | L104: 2 | M104: 2 | N104: S | O104: Sit.Normal | P104: 999 | Q104: F | R104: 45516 | S104: 10000000 | T104: -5687761.9 | U104: -4118.3 | V104: -5687761.9 | W104: -95367.4 | X104: 57831.29 | Y104: =TRIM(O104) -> Sit.Normal | Z104: =IF(Y104="Sit.Normal",1,IF(Y104="Riesgo potencia",2,IF(Y104="Con Problemas",3,IF(Y104="Alto Riesgo",4,IF(Y104="Irrecuperable",5,IF(Y104="Irrec Disp Tecn",6,IF(Y104="Sin identificación",0,""))))))) -> 1 | AB104: =VLOOKUP(A104,rubros_a_considerar!$A$2:$A$13,1,FALSE) -> 171112001 | AO104: =IFERROR(VLOOKUP(A104,Diccionario!$C$2:$E$65,3,FALSE),"no") -> Prestamos Personales
A105: 171112001 | B105: 80 | C105: 54541 | D105: 42833 | E105: 0 | F105: 46142 | G105: 47287 | H105: 45825 | I105: 1462 | J105: 2 | K105: 34 | L105: 2 | M105: 2 | N105: S | O105: Sit.Normal | P105: 999 | Q105: F | R105: 45825 | S105: 10000000 | T105: -8856137.5 | U105: -6412.4 | V105: -8856137.5 | W105: -115493.74 | X105: 89716.31 | Y105: =TRIM(O105) -> Sit.Normal | Z105: =IF(Y105="Sit.Normal",1,IF(Y105="Riesgo potencia",2,IF(Y105="Con Problemas",3,IF(Y105="Alto Riesgo",4,IF(Y105="Irrecuperable",5,IF(Y105="Irrec Disp Tecn",6,IF(Y105="Sin identificación",0,""))))))) -> 1 | AB105: =VLOOKUP(A105,rubros_a_considerar!$A$2:$A$13,1,FALSE) -> 171112001 | AO105: =IFERROR(VLOOKUP(A105,Diccionario!$C$2:$E$65,3,FALSE),"no") -> Prestamos Personales
A106: 171112001 | B106: 80 | C106: 54541 | D106: 42832 | E106: 0 | F106: 46142 | G106: 47282 | H106: 45821 | I106: 1461 | J106: 2 | K106: 34 | L106: 2 | M106: 2 | N106: S | O106: Sit.Normal | P106: 999 | Q106: F | R106: 45821 | S106: 10000000 | T106: -8856599.2 | U106: -6412.74 | V106: -8856599.2 | W106: -148499.69 | X106: 90050.99 | Y106: =TRIM(O106) -> Sit.Normal | Z106: =IF(Y106="Sit.Normal",1,IF(Y106="Riesgo potencia",2,IF(Y106="Con Problemas",3,IF(Y106="Alto Riesgo",4,IF(Y106="Irrecuperable",5,IF(Y106="Irrec Disp Tecn",6,IF(Y106="Sin identificación",0,""))))))) -> 1 | AB106: =VLOOKUP(A106,rubros_a_considerar!$A$2:$A$13,1,FALSE) -> 171112001 | AO106: =IFERROR(VLOOKUP(A106,Diccionario!$C$2:$E$65,3,FALSE),"no") -> Prestamos Personales
... A249: 131742001 | B249: 80 | C249: 87039 | D249: 0 | E249: 0 | F249: 46142 | G249: 46142 | H249: 45957 | I249: 0 | J249: 0 | K249: 101.99 | L249: 0 | M249: 0 | N249: S | O249: Sit.Normal | P249: 999 | Q249: F | R249: 45958 | S249: 0 | T249: -654502.03 | U249: -473.9 | V249: -654502.03 | W249: 0 | X249: 6545.02 | Y249: =TRIM(O249) -> Sit.Normal | Z249: =IF(Y249="Sit.Normal",1,IF(Y249="Riesgo potencia",2,IF(Y249="Con Problemas",3,IF(Y249="Alto Riesgo",4,IF(Y249="Irrecuperable",5,IF(Y249="Irrec Disp Tecn",6,IF(Y249="Sin identificación",0,""))))))) -> 1 | AB249: =VLOOKUP(A249,rubros_a_considerar!$A$2:$A$13,1,FALSE) -> 131742001 | AO249: =IFERROR(VLOOKUP(A249,Diccionario!$C$2:$E$65,3,FALSE),"no") -> Tarjetas_de_Crédito
